Workbook
Name adv: [1]Exp.PaymentTerms!$E$12
Name hand: [1]Exp.PaymentTerms!$G$12

Sheet СравнениеPnl 
B1: Без перегородок | C1: С перегородками
A2: Реализуемая площадь, м2 | B2: =SUM(B3:B6) -> 6901 | C2: =SUM(C3:C6) -> 17982.736 | D2: =C2-B2 -> 11081.736
A3: Квартиры (себес м2 * площадь) | B3: ='Dashboard все'!L16 -> 0 | C3: ='PnL (с перегор)'!B8 -> 11081.736 | D3: =C3-B3 -> 11081.736
A4: Коммерческие помещения | B4: ='Dashboard все'!L17 -> 6232 | C4: ='PnL (с перегор)'!B9 -> 6232 | D4: =C4-B4 -> 0
A5: Кладовые помещения | B5: ='Dashboard все'!L18 -> 253 | C5: ='PnL (с перегор)'!B10 -> 253 | D5: =C5-B5 -> 0
A6: Паркинги | B6: ='Dashboard все'!L19 -> 416 | C6: ='PnL (с перегор)'!B11 -> 416 | D6: =C6-B6 -> 0
A7: Реализуемое количество, шт | B7: =SUM(B8:B11) -> 50 | C7: =SUM(C8:C11) -> 469 | D7: =C7-B7 -> 419
A8: Квартиры (себес м2 * площадь) | B8: ='Dashboard все'!L23 -> 0 | C8: ='Dashboard (с перегор)'!L23 -> 240 | D8: =C8-B8 -> 240
A9: Коммерческие помещения | B9: ='Dashboard все'!L24 -> 22 | C9: ='Dashboard (с перегор)'!L24 -> 0 | D9: =C9-B9 -> -22
A10: Кладовые помещения | B10: ='Dashboard все'!L25 -> 2 | C10: ='Dashboard (с перегор)'!L25 -> 153 | D10: =C10-B10 -> 151
A11: Паркинги | B11: ='Dashboard все'!L26 -> 26 | C11: ='Dashboard (с перегор)'!L26 -> 76 | D11: =C11-B11 -> 50
A12: Средние цены реализации: | B12: =B22/B2 -> 1552427.2 | C12: =C22/C2 -> 428025.99 | D12: =C12-B12 -> -1124401.2
A13: Квартиры (себес м2 * площадь) | B13: ='Dashboard все'!F16 -> 0 | C13: ='Dashboard (с перегор)'!F16 -> 650000 | D13: =C13-B13 -> 650000
A14: Коммерческие помещения | B14: ='Dashboard все'!F17 -> 1600000 | C14: ='Dashboard (с перегор)'!F17 -> 0 | D14: =C14-B14 -> -1600000
A15: Кладовые помещения | B15: ='Dashboard все'!F18 -> 1700000 | C15: ='Dashboard (с перегор)'!F18 -> 150000 | D15: =C15-B15 -> -1550000
A16: Паркинги | B16: ='Dashboard все'!F19 -> 12000000 | C16: ='Dashboard (с перегор)'!F19 -> 6000000 | D16: =C16-B16 -> -6000000
A17: Cебестоимость СМР за м2: | B17: =(B29)/(B3+B4+B5+B6) -> 665927.82 | C17: =(C29)/(C3+720+C4+C5+C6) -> 665927.82 | D17: =C17-B17 -> 0
A18: Квартиры (себес м2 * площадь) | B18: ='Dashboard все'!I16 -> 665927.82 | C18: ='Dashboard (с перегор)'!I16 -> 285417.25 | D18: =C18-B18 -> -380510.57
A19: Коммерческие помещения | B19: 0 | C19: 0 | D19: =C19-B19 -> 0
A20: Кладовые помещения | B20: 0 | C20: 0 | D20: =C20-B20 -> 0
A21: Паркинги | D21: =C21-B21 -> 0
A22: Выручка итого в т.ч. | B22: =SUM(B23:B26) -> 10713300000 | C22: =SUM(C23:C26) -> 7.6970782e+09 | D22: =C22-B22 -> -3.0162218e+09
A23: Квартиры (себес м2 * площадь) | B23: =(B3*B13) -> 0 | C23: =(C3*C13) -> 7.2031282e+09 | D23: =C23-B23 -> 7.2031282e+09
A24: Коммерческие помещения | B24: =(B4*B14) -> 9971200000 | C24: =(C4*C14) -> 0 | D24: =C24-B24 -> -9971200000
A25: Кладовые помещения | B25: =(B5*B15) -> 430100000 | C25: =(C5*C15) -> 37950000 | D25: =C25-B25 -> -392150000
A26: Паркинги | B26: =(B11*B16) -> 312000000 | C26: =(C11*C16) -> 456000000 | D26: =C26-B26 -> 144000000
A27: Расходы итого: | B27: =B28+B30+B32+B34+B39+B41 -> 7.505397e+09 | C27: =C28+C30+C32+C34+C39+C41 -> #REF! | D27: =C27-B27 -> #REF!
A28: СМР в т.ч.: | B28: =SUM(B29:B29) -> 4595567890 | C28: =SUM(C29:C29) -> 1.2454672e+10 | D28: =C28-B28 -> 7.8591041e+09
A29: СМР(себес м2 * площадь) | B29: =B2*B18 -> 4595567890 | C29: ='PnL (с перегор)'!B41 -> 1.2454672e+10 | D29: =C29-B29 -> 7.8591041e+09
A30: ЗУ в т.ч.: | B30: =B31 -> 675000000 | C30: =C31 -> 675000000 | D30: =C30-B30 -> 0
A31: Земельный участок | B31: ='PnL все'!B49 -> 675000000 | C31: ='PnL (с перегор)'!B49 -> 675000000 | D31: =C31-B31 -> 0
A32: ПИР в т.ч.: | B32: =SUM(B33:B33) -> 197152741 | C32: =SUM(C33:C33) -> 5.3431323e+08 | D32: =C32-B32 -> 3.3716049e+08
A33: ПИР, тг | B33: ='PnL все'!B51 -> 197152741 | C33: ='PnL (с перегор)'!B51 -> 5.3431323e+08 | D33: =C33-B33 -> 3.3716049e+08
A34: Накладные расходы вт.ч. | B34: =SUM(B35:B38) -> 1.2377462e+09 | C34: =SUM(C35:C38) -> 1.8506659e+09 | D34: =C34-B34 -> 6.1291969e+08
A35: Накладные расходы, тг | B35: ='PnL все'!B53 -> 447216142 | C35: ='PnL (с перегор)'!B53 -> 1.2120222e+09 | D35: =C35-B35 -> 7.6480607e+08
A36: Административные расходы проекта, 1% | B36: ='PnL все'!B54 -> 45955679 | C36: ='PnL (с перегор)'!B54 -> 1.2454672e+08 | D36: =C36-B36 -> 78591041
A37: Содержание HCG (11+6 этаж), 2,4% | B37: ='PnL все'!B58 -> 257119200 | C37: ='PnL (с перегор)'!B58 -> 1.7752988e+08 | D37: =C37-B37 -> -79589324
A38: Расходы на реализацию, тг 4,55% | B38: ='PnL все'!B61 -> 487455150 | C38: ='PnL (с перегор)'!B61 -> 3.3656706e+08 | D38: =C38-B38 -> -1.5088809e+08
A39: % по кредиту | B39: =SUM(B40:B40) -> 112218750 | C39: =SUM(C40:C40) -> 112218750 | D39: =C39-B39 -> 0
A40: % по кредиту | B40: ='PnL все'!B66 -> 112218750 | C40: ='PnL (с перегор)'!B66 -> 112218750 | D40: =C40-B40 -> 0
A41: НДС не разрешенный в зачет | B41: =SUM(B42:B42) -> 6.8771146e+08 | C41: =SUM(C42:C42) -> #REF! | D41: =C41-B41 -> #REF!
A42: НДС не разрешенный в зачет | B42: ='PnL все'!B70 -> 6.8771146e+08 | C42: ='PnL (с перегор)'!B70 -> #REF! | D42: =C42-B42 -> #REF!
A43: Прибыль до налогообложения | B43: ='PnL все'!B72 -> 3.207903e+09 | C43: ='PnL (с перегор)'!B72 -> #REF! | D43: =C43-B43 -> #REF!
A44: КПН, 20% | B44: =IF((B43)>0,(B43)*20%,0) -> 6.415806e+08 | C44: =IF((C43)>0,(C43)*20%,0) -> #REF! | D44: =C44-B44 -> #REF!
A45: Чистая прибыль | B45: =B43-B44 -> 2.5663224e+09 | C45: =C43-C44 -> #REF! | D45: =C45-B45 -> #REF!
A46: Рентабельность | B46: =B45/B22 -> 0.23954546 | C46: =C45/C22 -> #REF! | D46: =C46-B46 -> #REF!

Sheet Сравнение
B1: Цена | C1: ='Dashboard все'!F16 -> 0 | D1: ='Dashboard (с перегор)'!F16 -> 650000
B2: Korkem | C2: Без перегородок | D2: С перегородками | E2: Отклонение
B3: Выручка | C3: ='PnL все'!B34 -> 10713300000 | D3: ='PnL (с перегор)'!B34 -> 7.3970782e+09 | E3: =D3-C3 -> -3.3162218e+09
B4: ЗУ | C4: ='PnL все'!B48 -> 675000000 | D4: ='PnL (с перегор)'!B48 -> 675000000 | E4: =D4-C4 -> 0
B5: СМР | C5: ='PnL все'!B40 -> 4595567890 | D5: ='PnL (с перегор)'!B40 -> 1.2454672e+10 | E5: =D5-C5 -> 7.8591041e+09
B6: Накладные+ПИР | C6: ='PnL все'!B53+'PnL все'!B50 -> 644368883 | D6: ='PnL (с перегор)'!B50+'PnL (с перегор)'!B53 -> 1.7463354e+09 | E6: =D6-C6 -> 1.1019666e+09
B7: РР | C7: ='PnL все'!B61 -> 487455150 | D7: ='PnL (с перегор)'!B61 -> 3.3656706e+08 | E7: =D7-C7 -> -1.5088809e+08
B8: HO | C8: ='PnL все'!B58 -> 257119200 | D8: ='PnL (с перегор)'!B58 -> 1.7752988e+08 | E8: =D8-C8 -> -79589324
B9: Адм.расходы | C9: ='PnL все'!B54 -> 45955679 | D9: ='PnL (с перегор)'!B54 -> 1.2454672e+08 | E9: =D9-C9 -> 78591041
B10: Кредит,%% | C10: ='PnL все'!B66 -> 112218750 | D10: ='PnL (с перегор)'!B66 -> 112218750 | E10: =D10-C10 -> 0
B11: Налоги(НДС, КПН) | C11: ='PnL все'!B70+'PnL все'!B73 -> 1.3292921e+09 | D11: ='PnL (с перегор)'!B70+'PnL (с перегор)'!B73 -> #REF! | E11: =D11-C11 -> #REF!
B12: ЧП | C12: =C3-C4-C5-C6-C7-C8-C9-C10-C11 -> 2.5663224e+09 | D12: =D3-D4-D5-D6-D7-D8-D9-D10-D11 -> #REF! | E12: =D12-C12 -> #REF!
B13: Рентабельность | C13: =C12/C3 -> 0.23954546 | D13: =D12/D3 -> #REF! | E13: =D13-C13 -> #REF!

Sheet Сравнительная
A2: Итоговые показатели | B2: все этажи | C2: 2-8 этажи | D2: Откл.
A3: Revenue | B3: ='PnL все'!B34 -> 10713300000 | C3: ='PnL2-8'!B34 -> 8049600000 | D3: =B3-C3 -> 2663700000
A4: Net Profit | B4: ='Dashboard все'!C4 -> 2.5663224e+09 | C4: ='Dashboard2-8'!C4 -> 9.488255e+08 | D4: =B4-C4 -> 1.6174969e+09
A5: ROS, % | B5: =B4/B3 -> 0.23954546 | C5: =C4/C3 -> 0.11787238 | D5: =B5-C5 -> 0.12167308
A6: NPV | B6: ='Dashboard все'!C9 -> 1.8777444e+09 | C6: ='Dashboard2-8'!C9 -> 9.7260965e+08 | D6: =B6-C6 -> 9.0513475e+08

Sheet Dashboard все
B3: Итоговые показатели
B4: Net Profit | C4: ='PnL все'!B74 -> 2.5663224e+09
B5: ROS, % | C5: ='PnL все'!B75 -> 0.23954546
B6: ROE (Отдача на капитал) | C6: =DCF!C44 -> 0
B7: WACC (Годовой) | C7: =DCF!C47*12 -> 0.21
B8: IRR (Минимальная ставка доходности) | C8: =DCF!C41 -> 15.142248
B9: NPV | C9: =DCF!C42 -> 1.8777444e+09
B10: PP | C10: =DCF!C37 -> 1
B11: DPP | C11: =DCF!C46 -> 1
B14: Основные вводные
B15: LAND | E15: SALES | H15: COSTS | K15: Sellable Area, sq.m | L15: =SUM(L16:L19) -> 6901
B16: Площадь ЗУ, га | C16: 0.15 | E16: Цена за м2 квартиры | F16: 0 | H16: Себестоимость за м2 | I16: =(4550567890+45000000)/L15 -> 665927.82 | K16: Квартиры | L16: 0 | N16: =N17/L17 -> 0.22400513
B17: Курс ЗУ | C17: 500 | E17: Цена за м2 офиса | F17: 1600000 | H17: Накладные расходы | I17: =447216142/L15 -> 64804.542 | K17: Офисы | L17: 6232 | M17: 4836 | N17: =L17-M17 -> 1396 | O17: =F17 -> 1600000 | P17: =N17*O17 -> 2233600000
B18: Стоимость за сотку, USD | C18: 90000 | E18: Цена за м2 коммерция | F18: 1700000 | H18: Расходы на реализацию | I18: 0.0455 | K18: Коммерция | L18: 253 | M18: 0 | N18: =L18-M18 -> 253 | O18: =F18 -> 1700000 | P18: =N18*O18 -> 430100000
B19: Стоимость участка итого, KZT | C19: =C16*100*C18*C17 -> 675000000 | E19: Цена за 1 м/м | F19: 12000000 | H19: Расходы офиса | I19: 0.024 | K19: Паркинг | L19: =L26*16 -> 416 | M19: 416
H20: ПИРы | I20: =197152741/L15 -> 28568.721
B22: CONSTRUCTION | E22: CASH FLOW | H22: TAXES | K22: Sellable Units, pcs | L22: =SUM(L23:L26) -> 50
B23: Этажность | C23: 10 | E23: Собственный капитал | H23: НДС | I23: ='PnL все'!B70 -> 6.8771146e+08 | K23: Квартиры | L23: 0
B24: Застраиваемая площадь | E24: Кредит | F24: =C19 -> 675000000 | H24: КПН | I24: ='PnL все'!B73 -> 6.415806e+08 | K24: Офисы | L24: 22
B25: Продаваемая площадь | C25: ='PnL все'!B7 -> 6901 | E25: Срок займа, мес | F25: 18 | K25: Коммерция | L25: 2
B26: Прод площ 1 очереди | C26: =C25 -> 6901 | E26: Дивиденды | F26: ='PnL все'!B74 -> 2.5663224e+09 | K26: Паркинг | L26: 26
E27: Дата займа | F27: 46204
B28: ЖЦП, мес | C28: 18 | E28: Ставка, % | F28: 21
B29: Дата старта | C29: 46204 | E29: Льготный период, мес | F29: 0
I32: 4.5505679e+09
B34: Собственный капитал | C34: 0
B35: Ставка займа (годовая) | C35: 0.21
B36: Стоимость акционерских денег | C36: 0.25

Sheet PnL все
A2: Показатель | B2: KZT | C2: USD
A3: Цена за сотку (Общая), USD | B3: =B48/B5/100/B4 -> 90000
A4: Курс $ | B4: ='Dashboard все'!C17 -> 500
A5: Земельный участок га | B5: ='Dashboard все'!C16 -> 0.15
A6: Этажность | B6: ='Dashboard все'!C23 -> 10
A7: Реализуемая площадь, м2 | B7: =SUM(B8:B11) -> 6901 | C7: =SUM(C8:C11) -> 6901
A8: Квартиры (себес м2 * площадь) | B8: ='Dashboard все'!L16 -> 0 | C8: =B8 -> 0
A9: Коммерческие помещения | B9: ='Dashboard все'!L17 -> 6232 | C9: =B9 -> 6232
A10: Коммерция | B10: ='Dashboard все'!L18 -> 253 | C10: =B10 -> 253
A11: Паркинги | B11: ='Dashboard все'!L19 -> 416 | C11: =B11 -> 416
A12: Реализуемое количество, шт | B12: =SUM(B13:B16) -> 50 | C12: =SUM(C13:C16) -> 50
A13: Квартиры (себес м2 * площадь) | B13: ='Dashboard все'!L23 -> 0 | C13: =B13 -> 0
A14: Офисы | B14: ='Dashboard все'!L24 -> 22 | C14: =B14 -> 22
A15: Коммерция | B15: 2 | C15: =B15 -> 2
A16: Паркинги | B16: ='Dashboard все'!L26 -> 26 | C16: =B16 -> 26
A17: Средние цены реализации: | B17: =B34/B7 -> 1552427.2 | C17: =C34/C7 -> 3104.8544
A18: Квартиры (себес м2 * площадь) | B18: ='Dashboard все'!F16 -> 0 | C18: =B18/$B$4 -> 0
A19: Офис | B19: ='Dashboard все'!F17 -> 1600000 | C19: =B19/$B$4 -> 3200
A20: Коммерческие помещения | B20: ='Dashboard все'!F18 -> 1700000 | C20: =B20/$B$4 -> 3400
A21: Паркинги | B21: ='Dashboard все'!F19 -> 12000000 | C21: =B21/$B$4 -> 24000
A22: Cебестоимость СМР за м2: | B22: =(B41+B42+B43+B44)/(B8+B9+B10+B11) -> 665927.82 | C22: =B22/$B$4 -> 1331.8556
A23: Квартиры (себес м2 * площадь) | B23: ='Dashboard все'!I16 -> 665927.82 | C23: =B23/$B$4 -> 1331.8556
A24: Коммерческие помещения | B24: 0 | C24: =B24/$B$4 -> 0
A25: Кладовые помещения | B25: 0 | C25: =B25/$B$4 -> 0
A26: Паркинги | B26: 0 | C26: =B26/$B$4 -> 0
A27: Средняя себестоимость (СМР+ПСД+опер.+накл.) | B27: =SUM(B28:B33) -> 971665.96 | C27: =B27/$B$4 -> 1943.3319
A28: Строительно-монтажные работы | B28: =B40/(B8+B9+B10+B11) -> 665927.82 | C28: =B28/$B$4 -> 1331.8556
A29: Земельный участок | B29: =B48/B7 -> 97811.911 | C29: =B29/$B$4 -> 195.62382
A30: Расходы заказчика | B30: =B50/B7 -> 28568.721 | C30: =B30/$B$4 -> 57.137441
A31: Накладные расходы | B31: =B52/B7 -> 179357.51 | C31: =B31/$B$4 -> 358.71502
A32: Социальная нагрузка | B32: 0 | C32: =B32/$B$4 -> 0
A33: % по кредиту | B33: 0 | C33: =B33/$B$4 -> 0
A34: Выручка итого в т.ч. | B34: =SUM(B35:B38) -> 10713300000 | C34: =B34/$B$4 -> 21426600
A35: Квартиры (себес м2 * площадь) | B35: =(B8*B18) -> 0 | C35: =B35/$B$4 -> 0
A36: Офис | B36: =(B9*B19) -> 9971200000 | C36: =B36/$B$4 -> 19942400
A37: Коммерческие помещения | B37: =(B10*B20) -> 430100000 | C37: =B37/$B$4 -> 860200
A38: Паркинги | B38: =(B16*B21) -> 312000000 | C38: =B38/$B$4 -> 624000
A39: Расходы итого: | B39: =B40+B48+B50+B52+B62+B66+B68+B70 -> 7.505397e+09 | C39: =B39/$B$4 -> 15010794
A40: СМР в т.ч.: | B40: =SUM(B41:B47) -> 4595567890 | C40: =B40/$B$4 -> 9191135.8 | F40: =B40/20 -> 2.2977839e+08
A41: СМР(себес м2 * площадь) | B41: =B7*'Dashboard все'!I16 -> 4595567890 | C41: =B41/$B$4 -> 9191135.8
A42: Коммерческие помещения (себес м2 * площадь) | B42: =B25*B7 -> 0 | C42: =B42/$B$4 -> 0
A43: Кладовки (себес м2 * площадь) | C43: =B43/$B$4 -> 0
A44: Паркинги (себес м2 * площадь) | C44: =B44/$B$4 -> 0
A45: Снос строении | C45: =B45/$B$4 -> 0
A46: Изменение целевого назначения | C46: =B46/$B$4 -> 0
A47: Подключение к сетям | C47: =B47/$B$4 -> 0
A48: ЗУ в т.ч.: | B48: =B49 -> 675000000 | C48: =B48/$B$4 -> 1350000 | D48: добавить вознаграждение по кредиту | F48: =B34/24 -> 446387500
A49: Земельный участок | B49: ='Dashboard все'!C19 -> 675000000 | C49: =B49/$B$4 -> 1350000
A50: ПИР в т.ч.: | B50: =SUM(B51:B51) -> 197152741 | C50: =B50/$B$4 -> 394305.48 | F50: =F48*45% -> 200874375
A51: ПИР, тг | B51: =B7*'Dashboard все'!I20 -> 197152741 | C51: =B51/$B$4 -> 394305.48
A52: Накладные расходы вт.ч. | B52: =SUM(B53:B61) -> 1.2377462e+09 | C52: =B52/$B$4 -> 2475492.3
A53: Накладные расходы, тг | B53: ='Dashboard все'!I17*'PnL все'!B7 -> 447216142 | C53: =B53/$B$4 -> 894432.28 | D53: =B53/B41 -> 0.097314663
A54: Административные расходы проекта, 1% | B54: =B40*1% -> 45955679 | C54: =B54/$B$4 -> 91911.358
A55: Подготовительные работы 1% | B55: 0 | C55: =B55/$B$4 -> 0
A56: Управление проектом | B56: 0 | C56: =B56/$B$4 -> 0
A57: Представительские расходы, тг 1% | B57: 0 | C57: =B57/$B$4 -> 0
A58: Содержание HCG (11+6 этаж), 2,4% | B58: =B34*'Dashboard все'!I19 -> 257119200 | C58: =B58/$B$4 -> 514238.4
A59: Гарантийный Резерв, 0,8% | B59: 0 | C59: =B59/$B$4 -> 0
A60: Ипотека 5% на 30% квартир | B60: =B35*5%*30%*0 -> 0 | C60: =B60/$B$4 -> 0
A61: Расходы на реализацию, тг 4,55% | B61: =B34*'Dashboard все'!I18 -> 487455150 | C61: =B61/$B$4 -> 974910.3
A62: Соц. Инфраструктура в т.ч.: | B62: =SUM(B63:B65) -> 0 | C62: =B62/$B$4 -> 0
A63: Школа | B63: 0 | C63: =B63/$B$4 -> 0
A64: Дет. Сад | B64: 0 | C64: =B64/$B$4 -> 0
A65: Парк | B65: 0 | C65: =B65/$B$4 -> 0
A66: % по кредиту | B66: =SUM(B67:B67) -> 112218750 | C66: =B66/$B$4 -> 224437.5
A67: % по кредиту | B67: =Credit!D8 -> 112218750 | C67: =B67/$B$4 -> 224437.5
A68: НДС не разрешенный в зачет | B68: =SUM(B69:B69) -> 0 | C68: =B68/$B$4 -> 0
A69: НДС не разрешенный в зачет | C69: =B69/$B$4 -> 0
A70: НДС | B70: =SUM(B71:B71) -> 6.8771146e+08 | C70: =B70/$B$4 -> 1375422.9
A71: НДС | B71: =IF('НДС расчет'!C8<0,0,'НДС расчет'!C8) -> 6.8771146e+08 | C71: =B71/$B$4 -> 1375422.9
A72: Прибыль до налогообложения | B72: =B34-B39 -> 3.207903e+09 | C72: =C34-C39 -> 6415806
A73: КПН, 20% | B73: =IF((B72)>0,(B72)*20%,0) -> 6.415806e+08 | C73: =IF((C72)>0,(C72)*20%,0) -> 1283161.2
A74: Чистая прибыль | B74: =B72-B73 -> 2.5663224e+09 | C74: =C72-C73 -> 5132644.8
A75: Рентабельность | B75: =B74/B34 -> 0.23954546 | C75: =C74/C34 -> 0.23954546

Sheet Dashboard2-8
B3: Итоговые показатели
B4: Net Profit | C4: ='PnL2-8'!B74 -> 9.488255e+08
B5: ROS, % | C5: =[2]PnL!B75 -> 0.18947345
B6: ROE (Отдача на капитал) | C6: =[2]DCF!C44 -> 0
B7: WACC (Годовой) | C7: =[2]DCF!C47*12 -> 0.21
B8: IRR (Минимальная ставка доходности) | C8: =[2]DCF!C41 -> 1.7278268
B9: NPV | C9: =[2]DCF!C42 -> 9.7260965e+08
B10: PP | C10: =[2]DCF!C37 -> 1
B11: DPP | C11: =[2]DCF!C46 -> 1
B14: Основные вводные
B15: LAND | E15: SALES | H15: COSTS | K15: Sellable Area, sq.m | L15: =SUM(L16:L19) -> 5252
B16: Площадь ЗУ, га | C16: 0.15 | E16: Цена за м2 квартиры | F16: 0 | H16: Себестоимость за м2 | I16: =(4550567890+45000000)/L15 -> 875012.93 | K16: Квартиры | L16: 0
B17: Курс ЗУ | C17: 500 | E17: Цена за м2 офиса | F17: 1600000 | H17: Накладные расходы | I17: =447216142/L15 -> 85151.588 | K17: Офисы | L17: 4836
B18: Стоимость за сотку, USD | C18: 90000 | E18: Цена за м2 коммерция | H18: Расходы на реализацию | I18: 0.0455 | K18: Коммерция | L18: 0
B19: Стоимость участка итого, KZT | C19: =C16*100*C18*C17 -> 675000000 | E19: Цена за 1 м/м | F19: 12000000 | H19: Расходы офиса | I19: 0.024 | K19: Паркинг | L19: =L26*16 -> 416
H20: ПИРы | I20: =197152741/L15 -> 37538.603
B22: CONSTRUCTION | E22: CASH FLOW | H22: TAXES | K22: Sellable Units, pcs | L22: =SUM(L23:L26) -> 50
B23: Этажность | C23: 10 | E23: Собственный капитал | H23: НДС | I23: =[2]PnL!B70 -> 3.4322847e+08 | K23: Квартиры | L23: 0
B24: Застраиваемая площадь | E24: Кредит | F24: =C19 -> 675000000 | H24: КПН | I24: =[2]PnL!B73 -> 3.8129638e+08 | K24: Офисы | L24: 22
B25: Продаваемая площадь | C25: =[2]PnL!B7 -> 5252 | E25: Срок займа, мес | F25: 18 | K25: Коммерция | L25: 2
B26: Прод площ 1 очереди | C26: =C25 -> 5252 | E26: Дивиденды | F26: =[2]PnL!B74 -> 1.5251855e+09 | K26: Паркинг | L26: 26
E27: Дата займа | F27: 46204
B28: ЖЦП, мес | C28: 18 | E28: Ставка, % | F28: 21
B29: Дата старта | C29: 46204 | E29: Льготный период, мес | F29: 0
I33: 4.5505679e+09
B34: Собственный капитал | C34: 0
B35: Ставка займа (годовая) | C35: 0.21
B36: Стоимость акционерских денег | C36: 0.25

Sheet PnL2-8
A2: Показатель | B2: KZT | C2: USD
A3: Цена за сотку (Общая), USD | B3: =B48/B5/100/B4 -> 90000
A4: Курс $ | B4: =[2]Dashboard!C17 -> 500
A5: Земельный участок га | B5: =[2]Dashboard!C16 -> 0.15
A6: Этажность | B6: =[2]Dashboard!C23 -> 10
A7: Реализуемая площадь, м2 | B7: =SUM(B8:B11) -> 5252 | C7: =SUM(C8:C11) -> 5252
A8: Квартиры (себес м2 * площадь) | B8: =[2]Dashboard!L16 -> 0 | C8: =B8 -> 0
A9: Коммерческие помещения | B9: ='Dashboard2-8'!L17 -> 4836 | C9: =B9 -> 4836
A10: Кладовые помещения | B10: =[2]Dashboard!L18 -> 0 | C10: =B10 -> 0
A11: Паркинги | B11: ='Dashboard2-8'!L19 -> 416 | C11: =B11 -> 416
A12: Реализуемое количество, шт | B12: =SUM(B13:B16) -> 48 | C12: =SUM(C13:C16) -> 48
A13: Квартиры (себес м2 * площадь) | B13: =[2]Dashboard!L23 -> 0 | C13: =B13 -> 0
A14: Коммерческие помещения | B14: ='Dashboard2-8'!L24 -> 22 | C14: =B14 -> 22
A15: Кладовые помещения | C15: =B15 -> 0
A16: Паркинги | B16: ='Dashboard2-8'!L26 -> 26 | C16: =B16 -> 26
A17: Средние цены реализации: | B17: =B34/B7 -> 1532673.3 | C17: =C34/C7 -> 3065.3465
A18: Квартиры (себес м2 * площадь) | B18: =[2]Dashboard!F16 -> 0 | C18: =B18/$B$4 -> 0
A19: Офис | B19: ='Dashboard2-8'!F17 -> 1600000 | C19: =B19/$B$4 -> 3200
A20: Коммерческие помещения | B20: =[2]Dashboard!F18 -> 0 | C20: =B20/$B$4 -> 0
A21: Паркинги | B21: ='Dashboard2-8'!F19 -> 12000000 | C21: =B21/$B$4 -> 24000
A22: Cебестоимость СМР за м2: | B22: =(B41+B42+B43+B44)/(B8+B9+B10+B11) -> 875012.93 | C22: =B22/$B$4 -> 1750.0259
A23: Квартиры (себес м2 * площадь) | B23: ='Dashboard2-8'!I16 -> 875012.93 | C23: =B23/$B$4 -> 1750.0259
A24: Коммерческие помещения | B24: 0 | C24: =B24/$B$4 -> 0
A25: Кладовые помещения | B25: 0 | C25: =B25/$B$4 -> 0
A26: Паркинги | B26: 0 | C26: =B26/$B$4 -> 0
A27: Средняя себестоимость (СМР+ПСД+опер.+накл.) | B27: =SUM(B28:B33) -> 1241496.5 | C27: =B27/$B$4 -> 2482.993
A28: Строительно-монтажные работы | B28: =B40/(B8+B9+B10+B11) -> 875012.93 | C28: =B28/$B$4 -> 1750.0259
A29: Земельный участок | B29: =B48/B7 -> 128522.47 | C29: =B29/$B$4 -> 257.04494
A30: Расходы заказчика | B30: =B50/B7 -> 37538.603 | C30: =B30/$B$4 -> 75.077205
A31: Накладные расходы | B31: =B52/B7 -> 200422.51 | C31: =B31/$B$4 -> 400.84502
A32: Социальная нагрузка | B32: 0 | C32: =B32/$B$4 -> 0
A33: % по кредиту | B33: 0 | C33: =B33/$B$4 -> 0
A34: Выручка итого в т.ч. | B34: =SUM(B35:B38) -> 8049600000 | C34: =B34/$B$4 -> 16099200
A35: Квартиры (себес м2 * площадь) | B35: =(B8*B18) -> 0 | C35: =B35/$B$4 -> 0
A36: Офис | B36: =(B9*B19) -> 7737600000 | C36: =B36/$B$4 -> 15475200
A37: Коммерческие помещения | B37: =(B10*B20) -> 0 | C37: =B37/$B$4 -> 0
A38: Паркинги | B38: =(B16*B21) -> 312000000 | C38: =B38/$B$4 -> 624000
A39: Расходы итого: | B39: =B40+B48+B50+B52+B62+B66+B68+B70 -> 6.8635681e+09 | C39: =B39/$B$4 -> 13727136
A40: СМР в т.ч.: | B40: =SUM(B41:B47) -> 4595567890 | C40: =B40/$B$4 -> 9191135.8
A41: СМР(себес м2 * площадь) | B41: =B7*B23 -> 4595567890 | C41: =B41/$B$4 -> 9191135.8
A42: Коммерческие помещения (себес м2 * площадь) | B42: =B25*B7 -> 0 | C42: =B42/$B$4 -> 0
A43: Кладовки (себес м2 * площадь) | C43: =B43/$B$4 -> 0
A44: Паркинги (себес м2 * площадь) | C44: =B44/$B$4 -> 0
A45: Снос строении | C45: =B45/$B$4 -> 0
A46: Изменение целевого назначения | C46: =B46/$B$4 -> 0
A47: Подключение к сетям | C47: =B47/$B$4 -> 0
A48: ЗУ в т.ч.: | B48: =B49 -> 675000000 | C48: =B48/$B$4 -> 1350000
A49: Земельный участок | B49: ='Dashboard2-8'!C19 -> 675000000 | C49: =B49/$B$4 -> 1350000
A50: ПИР в т.ч.: | B50: =SUM(B51:B51) -> 197152741 | C50: =B50/$B$4 -> 394305.48
A51: ПИР, тг | B51: =B7*'Dashboard2-8'!I20 -> 197152741 | C51: =B51/$B$4 -> 394305.48
A52: Накладные расходы вт.ч. | B52: =SUM(B53:B61) -> 1.052619e+09 | C52: =B52/$B$4 -> 2105238
A53: Накладные расходы, тг | B53: ='Dashboard2-8'!I17*'PnL2-8'!B7 -> 4.4721614e+08 | C53: =B53/$B$4 -> 894432.28 | D53: =B53/B41 -> 0.097314663
A54: Административные расходы проекта, 1% | B54: =B40*1% -> 45955679 | C54: =B54/$B$4 -> 91911.358
A55: Подготовительные работы 1% | B55: 0 | C55: =B55/$B$4 -> 0
A56: Управление проектом | B56: 0 | C56: =B56/$B$4 -> 0
A57: Представительские расходы, тг 1% | B57: 0 | C57: =B57/$B$4 -> 0
A58: Содержание HCG (11+6 этаж), 2,4% | B58: =B34*'Dashboard2-8'!I19 -> 193190400 | C58: =B58/$B$4 -> 386380.8
A59: Гарантийный Резерв, 0,8% | B59: 0 | C59: =B59/$B$4 -> 0
A60: Ипотека 5% на 30% квартир | B60: =B35*5%*30%*0 -> 0 | C60: =B60/$B$4 -> 0
A61: Расходы на реализацию, тг 4,55% | B61: =B34*'Dashboard2-8'!I18 -> 366256800 | C61: =B61/$B$4 -> 732513.6
A62: Соц. Инфраструктура в т.ч.: | B62: =SUM(B63:B65) -> 0 | C62: =B62/$B$4 -> 0
A63: Школа | B63: 0 | C63: =B63/$B$4 -> 0
A64: Дет. Сад | B64: 0 | C64: =B64/$B$4 -> 0
A65: Парк | B65: 0 | C65: =B65/$B$4 -> 0
A66: % по кредиту | B66: =SUM(B67:B67) -> 0 | C66: =B66/$B$4 -> 0
A67: % по кредиту | B67: =[2]Credit!D8 -> 0 | C67: =B67/$B$4 -> 0
A68: НДС не разрешенный в зачет | B68: =SUM(B69:B69) -> 0 | C68: =B68/$B$4 -> 0
A69: НДС не разрешенный в зачет | C69: =B69/$B$4 -> 0
A70: НДС | B70: =SUM(B71:B71) -> 3.4322847e+08 | C70: =B70/$B$4 -> 686456.95
A71: НДС | B71: =IF('[2]НДС расчет'!C8<0,0,'[2]НДС расчет'!C8) -> 3.4322847e+08 | C71: =B71/$B$4 -> 686456.95
A72: Прибыль до налогообложения | B72: =B34-B39 -> 1.1860319e+09 | C72: =C34-C39 -> 2372063.8
A73: КПН, 20% | B73: =IF((B72)>0,(B72)*20%,0) -> 2.3720638e+08 | C73: =IF((C72)>0,(C72)*20%,0) -> 474412.75
A74: Чистая прибыль | B74: =B72-B73 -> 9.488255e+08 | C74: =C72-C73 -> 1897651
A75: Рентабельность | B75: =B74/B34 -> 0.11787238 | C75: =C74/C34 -> 0.11787238

Sheet DCF
D3: =YEAR(D6) -> 2026 | E3: =YEAR(E6) -> 2026 | F3: =YEAR(F6) -> 2026 | G3: =YEAR(G6) -> 2026 | H3: =YEAR(H6) -> 2026 | I3: =YEAR(I6) -> 2026 | J3: =YEAR(J6) -> 2027 | K3: =YEAR(K6) -> 2027 | ... KQ3: =YEAR(KQ6) -> 2051
D4: 1 | E4: =D4+1 -> 2 | F4: =E4+1 -> 3 | G4: =F4+1 -> 4 | H4: =G4+1 -> 5 | I4: =H4+1 -> 6 | J4: =I4+1 -> 7 | K4: =J4+1 -> 8 | L4: =K4+1 -> 9 | ... KQ4: =KP4+1 -> 300
D5: =MONTH(D6) -> 7 | E5: =MONTH(E6) -> 8 | F5: =MONTH(F6) -> 9 | G5: =MONTH(G6) -> 10 | H5: =MONTH(H6) -> 11 | I5: =MONTH(I6) -> 12 | J5: =MONTH(J6) -> 1 | K5: =MONTH(K6) -> 2 | ... KQ5: =MONTH(KQ6) -> 6
B6: Дисконтированные денежные потоки | C6: Total | D6: ='Dashboard все'!C29 -> 46204 | E6: =EDATE(D6,1) -> 46235 | F6: =EDATE(E6,1) -> 46266 | G6: =EDATE(F6,1) -> 46296 | H6: =EDATE(G6,1) -> 46327 | I6: =EDATE(H6,1) -> 46357 | J6: =EDATE(I6,1) -> 46388 | K6: =EDATE(J6,1) -> 46419 | L6: =EDATE(K6,1) -> 46447 | ... KQ6: =EDATE(KP6,1) -> 55305
B7: Поступления по операционной деятельности | C7: =SUM(D7:KQ7) -> 10713300000 | D7: =SUM(D8:D8) -> 321399000 | E7: =SUM(E8:E8) -> 321399000 | F7: =SUM(F8:F8) -> 321399000 | G7: =SUM(G8:G8) -> 321399000 | H7: =SUM(H8:H8) -> 332112300 | I7: =SUM(I8:I8) -> 332112300 | J7: =SUM(J8:J8) -> 332112300 | K7: =SUM(K8:K8) -> 332112300 | ... KQ7: =SUM(KQ8:KQ8) -> 0
B8: Релизация помещений | C8: =SUM(D8:KQ8) -> 10713300000 | D8: =Sales!E15 -> 321399000 | E8: =Sales!F15 -> 321399000 | F8: =Sales!G15 -> 321399000 | G8: =Sales!H15 -> 321399000 | H8: =Sales!I15 -> 332112300 | I8: =Sales!J15 -> 332112300 | J8: =Sales!K15 -> 332112300 | K8: =Sales!L15 -> 332112300 | ... GB8: =Sales!GC15 -> 0 | GC8: =Sales!FU36 -> 0 | GD8: =Sales!FV36 -> 0 | GE8: =Sales!FW36 -> 0 | GF8: =Sales!FX36 -> 0 | GG8: =Sales!FY36 -> 0 | GH8: =Sales!FZ36 -> 0 | GI8: =Sales!GA36 -> 0 | GJ8: =Sales!GB36 -> 0 | ... KQ8: =Sales!KI36 -> 0
B9: Выбытие по операционной деятельности | C9: =SUM(D9:KQ9) -> 5.8333141e+09 | D9: =SUM(D10:D10) -> 2.3333256e+08 | E9: =SUM(E10:E10) -> 2.3333256e+08 | F9: =SUM(F10:F10) -> 2.3333256e+08 | G9: =SUM(G10:G10) -> 2.916657e+08 | H9: =SUM(H10:H10) -> 2.916657e+08 | I9: =SUM(I10:I10) -> 2.916657e+08 | J9: =SUM(J10:J10) -> 2.916657e+08 | K9: =SUM(K10:K10) -> 3.4999884e+08 | ... KQ9: =SUM(KQ10:KQ10) -> 0
B10: Расходы проекта | C10: =SUM(D10:KQ10) -> 5.8333141e+09 | D10: =Costs!E16 -> 2.3333256e+08 | E10: =Costs!F16 -> 2.3333256e+08 | F10: =Costs!G16 -> 2.3333256e+08 | G10: =Costs!H16 -> 2.916657e+08 | H10: =Costs!I16 -> 2.916657e+08 | I10: =Costs!J16 -> 2.916657e+08 | J10: =Costs!K16 -> 2.916657e+08 | K10: =Costs!L16 -> 3.4999884e+08 | ... FU10: =Costs!FV16 -> 0 | FV10: =Costs!FQ37 -> 0 | FW10: =Costs!FR37 -> 0 | FX10: =Costs!FS37 -> 0 | FY10: =Costs!FT37 -> 0 | FZ10: =Costs!FU37 -> 0 | GA10: =Costs!FV37 -> 0 | GB10: =Costs!FW37 -> 0 | GC10: =Costs!FX37 -> 0 | ... KQ10: =Costs!KL37 -> 0
B11: Операционная прибыль EBITDA | C11: =SUM(D11:KQ11) -> 4.8799859e+09 | D11: =D7-D9 -> 88066438 | E11: =E7-E9 -> 88066438 | F11: =F7-F9 -> 88066438 | G11: =G7-G9 -> 29733297 | H11: =H7-H9 -> 40446597 | I11: =I7-I9 -> 40446597 | J11: =J7-J9 -> 40446597 | K11: =K7-K9 -> -17886544 | ... KQ11: =KQ7-KQ9 -> 0
B12: НДС к уплате | C12: =SUM(D12:KQ12) -> 6.8771146e+08 | D12: {=TRANSPOSE(SUMIFS(Графики!$I$7:$I$306,Графики!$D$7:$D$306,DCF!D$6))} -> 0 | E12: {=TRANSPOSE(SUMIFS(Графики!$I$7:$I$306,Графики!$D$7:$D$306,DCF!E$6))} -> 0 | F12: {=TRANSPOSE(SUMIFS(Графики!$I$7:$I$306,Графики!$D$7:$D$306,DCF!F$6))} -> 0 | G12: {=TRANSPOSE(SUMIFS(Графики!$I$7:$I$306,Графики!$D$7:$D$306,DCF!G$6))} -> 0 | H12: {=TRANSPOSE(SUMIFS(Графики!$I$7:$I$306,Графики!$D$7:$D$306,DCF!H$6))} -> 34385573 | I12: {=TRANSPOSE(SUMIFS(Графики!$I$7:$I$306,Графики!$D$7:$D$306,DCF!I$6))} -> 0 | J12: {=TRANSPOSE(SUMIFS(Графики!$I$7:$I$306,Графики!$D$7:$D$306,DCF!J$6))} -> 0 | K12: {=TRANSPOSE(SUMIFS(Графики!$I$7:$I$306,Графики!$D$7:$D$306,DCF!K$6))} -> 34385573 | ... ED12: {=TRANSPOSE(SUMIFS(Графики!$I$7:$I$306,Графики!$D$7:$D$306,DCF!ED$6))} -> 0 | EE12: {=TRANSPOSE(SUMIFS(Графики!$I$7:$I$306,Графики!$D$7:$D$306,DCF!EE6))} -> 0 | EF12: {=TRANSPOSE(SUMIFS(Графики!$I$7:$I$306,Графики!$D$7:$D$306,DCF!EF6))} -> 0 | EG12: {=TRANSPOSE(SUMIFS(Графики!$I$7:$I$306,Графики!$D$7:$D$306,DCF!EG6))} -> 0 | EH12: {=TRANSPOSE(SUMIFS(Графики!$I$7:$I$306,Графики!$D$7:$D$306,DCF!EH6))} -> 0 | EI12: {=TRANSPOSE(SUMIFS(Графики!$I$7:$I$306,Графики!$D$7:$D$306,DCF!EI6))} -> 0 | EJ12: {=TRANSPOSE(SUMIFS(Графики!$I$7:$I$306,Графики!$D$7:$D$306,DCF!EJ6))} -> 0 | EK12: {=TRANSPOSE(SUMIFS(Графики!$I$7:$I$306,Графики!$D$7:$D$306,DCF!EK6))} -> 0 | EL12: {=TRANSPOSE(SUMIFS(Графики!$I$7:$I$306,Графики!$D$7:$D$306,DCF!EL6))} -> 0 | ... KQ12: {=TRANSPOSE(SUMIFS(Графики!$I$7:$I$306,Графики!$D$7:$D$306,DCF!KQ6))} -> 0
B13: КПН | C13: =SUM(D13:KQ13) -> 6.415806e+08 | D13: {=TRANSPOSE(SUMIFS(Графики!$H$7:$H$306,Графики!$D$7:$D$306,DCF!D$6))} -> 0 | E13: {=TRANSPOSE(SUMIFS(Графики!$H$7:$H$306,Графики!$D$7:$D$306,DCF!E$6))} -> 0 | F13: {=TRANSPOSE(SUMIFS(Графики!$H$7:$H$306,Графики!$D$7:$D$306,DCF!F$6))} -> 0 | G13: {=TRANSPOSE(SUMIFS(Графики!$H$7:$H$306,Графики!$D$7:$D$306,DCF!G$6))} -> 0 | H13: {=TRANSPOSE(SUMIFS(Графики!$H$7:$H$306,Графики!$D$7:$D$306,DCF!H$6))} -> 0 | I13: {=TRANSPOSE(SUMIFS(Графики!$H$7:$H$306,Графики!$D$7:$D$306,DCF!I$6))} -> 0 | J13: {=TRANSPOSE(SUMIFS(Графики!$H$7:$H$306,Графики!$D$7:$D$306,DCF!J$6))} -> 0 | K13: {=TRANSPOSE(SUMIFS(Графики!$H$7:$H$306,Графики!$D$7:$D$306,DCF!K$6))} -> 0 | ... KQ13: {=TRANSPOSE(SUMIFS(Графики!$H$7:$H$306,Графики!$D$7:$D$306,DCF!KQ$6))} -> 0
B14: Вознаграждение по займам | C14: =SUM(D14:KQ14) -> 112218750 | D14: {=TRANSPOSE(SUMIFS(Графики!$J$7:$J$306,Графики!$D$7:$D$306,DCF!D$6))} -> 11812500 | E14: {=TRANSPOSE(SUMIFS(Графики!$J$7:$J$306,Графики!$D$7:$D$306,DCF!E$6))} -> 11156250 | F14: {=TRANSPOSE(SUMIFS(Графики!$J$7:$J$306,Графики!$D$7:$D$306,DCF!F$6))} -> 10500000 | G14: {=TRANSPOSE(SUMIFS(Графики!$J$7:$J$306,Графики!$D$7:$D$306,DCF!G$6))} -> 9843750 | H14: {=TRANSPOSE(SUMIFS(Графики!$J$7:$J$306,Графики!$D$7:$D$306,DCF!H$6))} -> 9187500 | I14: {=TRANSPOSE(SUMIFS(Графики!$J$7:$J$306,Графики!$D$7:$D$306,DCF!I$6))} -> 8531250 | J14: {=TRANSPOSE(SUMIFS(Графики!$J$7:$J$306,Графики!$D$7:$D$306,DCF!J$6))} -> 7875000 | K14: {=TRANSPOSE(SUMIFS(Графики!$J$7:$J$306,Графики!$D$7:$D$306,DCF!K$6))} -> 7218750 | ... KQ14: {=TRANSPOSE(SUMIFS(Графики!$J$7:$J$306,Графики!$D$7:$D$306,DCF!KQ$6))} -> 0
B15: Свободный денежный поток по опер. деятельности | C15: =SUM(D15:KQ15) -> 3.4384751e+09 | D15: =D11-SUM(D12:D14) -> 76253938 | E15: =E11-SUM(E12:E14) -> 76910188 | F15: =F11-SUM(F12:F14) -> 77566438 | G15: =G11-SUM(G12:G14) -> 19889547 | H15: =H11-SUM(H12:H14) -> -3126476 | I15: =I11-SUM(I12:I14) -> 31915347 | J15: =J11-SUM(J12:J14) -> 32571597 | K15: =K11-SUM(K12:K14) -> -59490867 | ... KQ15: =KQ11-SUM(KQ12:KQ14) -> 0
B16: Приобретение ЗУ | C16: =SUM(D16:KQ16) -> 675000000 | D16: {=TRANSPOSE(SUMIFS(Графики!$E$7:$E$306,Графики!$D$7:$D$306,DCF!D$6))} -> 0 | E16: {=TRANSPOSE(SUMIFS(Графики!$E$7:$E$306,Графики!$D$7:$D$306,DCF!E$6))} -> 0 | F16: {=TRANSPOSE(SUMIFS(Графики!$E$7:$E$306,Графики!$D$7:$D$306,DCF!F$6))} -> 0 | G16: {=TRANSPOSE(SUMIFS(Графики!$E$7:$E$306,Графики!$D$7:$D$306,DCF!G$6))} -> 0 | H16: {=TRANSPOSE(SUMIFS(Графики!$E$7:$E$306,Графики!$D$7:$D$306,DCF!H$6))} -> 0 | I16: {=TRANSPOSE(SUMIFS(Графики!$E$7:$E$306,Графики!$D$7:$D$306,DCF!I$6))} -> 0 | J16: {=TRANSPOSE(SUMIFS(Графики!$E$7:$E$306,Графики!$D$7:$D$306,DCF!J$6))} -> 0 | K16: {=TRANSPOSE(SUMIFS(Графики!$E$7:$E$306,Графики!$D$7:$D$306,DCF!K$6))} -> 0 | ... KQ16: {=TRANSPOSE(SUMIFS(Графики!$E$7:$E$306,Графики!$D$7:$D$306,DCF!KQ$6))} -> 0
B17: Соц нагрузка | C17: =SUM(D17:KQ17) -> 0 | D17: {=TRANSPOSE(SUMIFS(Графики!$G$7:$G$306,Графики!$D$7:$D$306,DCF!D$6))} -> 0 | E17: {=TRANSPOSE(SUMIFS(Графики!$G$7:$G$306,Графики!$D$7:$D$306,DCF!E$6))} -> 0 | F17: {=TRANSPOSE(SUMIFS(Графики!$G$7:$G$306,Графики!$D$7:$D$306,DCF!F$6))} -> 0 | G17: {=TRANSPOSE(SUMIFS(Графики!$G$7:$G$306,Графики!$D$7:$D$306,DCF!G$6))} -> 0 | H17: {=TRANSPOSE(SUMIFS(Графики!$G$7:$G$306,Графики!$D$7:$D$306,DCF!H$6))} -> 0 | I17: {=TRANSPOSE(SUMIFS(Графики!$G$7:$G$306,Графики!$D$7:$D$306,DCF!I$6))} -> 0 | J17: {=TRANSPOSE(SUMIFS(Графики!$G$7:$G$306,Графики!$D$7:$D$306,DCF!J$6))} -> 0 | K17: {=TRANSPOSE(SUMIFS(Графики!$G$7:$G$306,Графики!$D$7:$D$306,DCF!K$6))} -> 0 | ... JY17: {=TRANSPOSE(SUMIFS(Графики!$G$7:$G$306,Графики!$D$7:$D$306,DCF!JY$6))} -> 0 | JZ17: {=TRANSPOSE(SUMIFS(Графики!$E$7:$E$306,Графики!$D$7:$D$306,DCF!JZ$6))} -> 0 | KA17: {=TRANSPOSE(SUMIFS(Графики!$G$7:$G$306,Графики!$D$7:$D$306,DCF!KA$6))} -> 0 | KB17: {=TRANSPOSE(SUMIFS(Графики!$G$7:$G$306,Графики!$D$7:$D$306,DCF!KB$6))} -> 0 | KC17: {=TRANSPOSE(SUMIFS(Графики!$G$7:$G$306,Графики!$D$7:$D$306,DCF!KC$6))} -> 0 | KD17: {=TRANSPOSE(SUMIFS(Графики!$G$7:$G$306,Графики!$D$7:$D$306,DCF!KD$6))} -> 0 | KE17: {=TRANSPOSE(SUMIFS(Графики!$G$7:$G$306,Графики!$D$7:$D$306,DCF!KE$6))} -> 0 | KF17: {=TRANSPOSE(SUMIFS(Графики!$G$7:$G$306,Графики!$D$7:$D$306,DCF!KF$6))} -> 0 | KG17: {=TRANSPOSE(SUMIFS(Графики!$G$7:$G$306,Графики!$D$7:$D$306,DCF!KG$6))} -> 0 | KH17: {=TRANSPOSE(SUMIFS(Графики!$G$7:$G$306,Графики!$D$7:$D$306,DCF!KH$6))} -> 0 | ... KQ17: {=TRANSPOSE(SUMIFS(Графики!$G$7:$G$306,Графики!$D$7:$D$306,DCF!KQ$6))} -> 0
B18: Проектирование | C18: =SUM(D18:KQ18) -> 197152741 | D18: {=TRANSPOSE(SUMIFS(Графики!$F$7:$F$306,Графики!$D$7:$D$306,DCF!D$6))} -> 15772219 | E18: {=TRANSPOSE(SUMIFS(Графики!$F$7:$F$306,Графики!$D$7:$D$306,DCF!E$6))} -> 15772219 | F18: {=TRANSPOSE(SUMIFS(Графики!$F$7:$F$306,Графики!$D$7:$D$306,DCF!F$6))} -> 15772219 | G18: {=TRANSPOSE(SUMIFS(Графики!$F$7:$F$306,Графики!$D$7:$D$306,DCF!G$6))} -> 15772219 | H18: {=TRANSPOSE(SUMIFS(Графики!$F$7:$F$306,Графики!$D$7:$D$306,DCF!H$6))} -> 15772219 | I18: {=TRANSPOSE(SUMIFS(Графики!$F$7:$F$306,Графики!$D$7:$D$306,DCF!I$6))} -> 15772219 | J18: {=TRANSPOSE(SUMIFS(Графики!$F$7:$F$306,Графики!$D$7:$D$306,DCF!J$6))} -> 15772219 | K18: {=TRANSPOSE(SUMIFS(Графики!$F$7:$F$306,Графики!$D$7:$D$306,DCF!K$6))} -> 15772219 | ... KQ18: {=TRANSPOSE(SUMIFS(Графики!$F$7:$F$306,Графики!$D$7:$D$306,DCF!KQ$6))} -> 0
B19: Свободный денежный поток от инвестиционной деятельности | C19: =SUM(D19:KQ19) -> -872152741 | D19: =-SUM(D16:D18) -> -15772219 | E19: =-SUM(E16:E18) -> -15772219 | F19: =-SUM(F16:F18) -> -15772219 | G19: =-SUM(G16:G18) -> -15772219 | H19: =-SUM(H16:H18) -> -15772219 | I19: =-SUM(I16:I18) -> -15772219 | J19: =-SUM(J16:J18) -> -15772219 | K19: =-SUM(K16:K18) -> -15772219 | ... KQ19: =-SUM(KQ16:KQ18) -> 0
B21: FCFF | C21: =SUM(D21:KQ21) -> 2.5663224e+09 | D21: =D15+D19 -> 60481718 | E21: =E15+E19 -> 61137968 | F21: =F15+F19 -> 61794218 | G21: =G15+G19 -> 4117327.7 | H21: =H15+H19 -> -18898695 | I21: =I15+I19 -> 16143128 | J21: =J15+J19 -> 16799378 | K21: =K15+K19 -> -75263086 | ... KQ21: =KQ15+KQ19 -> 0
B22: Поступление по фин.деят (ОД) | C22: =SUM(D22:KQ22) -> 675000000 | H22: ='Dashboard все'!F24 -> 675000000
B23: Equity | C23: =SUM(D23:KQ23) -> 0
B24: Партнеры/рассрочка | C24: =SUM(D24:KQ24) -> 0
B25: Оттоки по фин.деят (ОД) | C25: =SUM(D25:KQ25) -> 675000000 | D25: {=TRANSPOSE(SUMIFS(Графики!$K$7:$K$306,Графики!$D$7:$D$306,DCF!D$6))} -> 37500000 | E25: {=TRANSPOSE(SUMIFS(Графики!$K$7:$K$306,Графики!$D$7:$D$306,DCF!E$6))} -> 37500000 | F25: {=TRANSPOSE(SUMIFS(Графики!$K$7:$K$306,Графики!$D$7:$D$306,DCF!F$6))} -> 37500000 | G25: {=TRANSPOSE(SUMIFS(Графики!$K$7:$K$306,Графики!$D$7:$D$306,DCF!G$6))} -> 37500000 | H25: {=TRANSPOSE(SUMIFS(Графики!$K$7:$K$306,Графики!$D$7:$D$306,DCF!H$6))} -> 37500000 | I25: {=TRANSPOSE(SUMIFS(Графики!$K$7:$K$306,Графики!$D$7:$D$306,DCF!I$6))} -> 37500000 | J25: {=TRANSPOSE(SUMIFS(Графики!$K$7:$K$306,Графики!$D$7:$D$306,DCF!J$6))} -> 37500000 | K25: {=TRANSPOSE(SUMIFS(Графики!$K$7:$K$306,Графики!$D$7:$D$306,DCF!K$6))} -> 37500000 | ... KQ25: {=TRANSPOSE(SUMIFS(Графики!$K$7:$K$306,Графики!$D$7:$D$306,DCF!KQ$6))} -> 0
B26: Возврат Equity | C26: =SUM(D26:KQ26) -> 0
B27: Возврат партнеры/рассрочка | C27: =SUM(D27:KQ27) -> 0
B28: Выплата ДВД | C28: =SUM(D28:KQ28) -> 0
B29: Свободный денежный поток от ФИН деятельности | C29: =SUM(D29:KQ29) -> 0 | D29: =D22+D23+D24-D25-D26-D28-D27 -> -37500000 | E29: =E22+E23+E24-E25-E26-E28-E27 -> -37500000 | F29: =F22+F23+F24-F25-F26-F28-F27 -> -37500000 | G29: =G22+G23+G24-G25-G26-G28-G27 -> -37500000 | H29: =H22+H23+H24-H25-H26-H28-H27 -> 637500000 | I29: =I22+I23+I24-I25-I26-I28-I27 -> -37500000 | J29: =J22+J23+J24-J25-J26-J28-J27 -> -37500000 | K29: =K22+K23+K24-K25-K26-K28-K27 -> -37500000 | ... KQ29: =KQ22+KQ23+KQ24-KQ25-KQ26-KQ28-KQ27 -> 0
B31: FCFE | C31: =SUM(D31:KQ31) -> 2.5663224e+09 | D31: =D21+D29 -> 22981718 | E31: =E21+E29 -> 23637968 | F31: =F21+F29 -> 24294218 | G31: =G21+G29 -> -33382672 | H31: =H21+H29 -> 6.186013e+08 | I31: =I21+I29 -> -21356872 | J31: =J21+J29 -> -20700622 | K31: =K21+K29 -> -1.1276309e+08 | ... KQ31: =KQ21+KQ29 -> 0
B34: Накопительный денежный поток | C34: KZT | D34: =D31 -> 22981718 | E34: =D34+E31 -> 46619687 | F34: =E34+F31 -> 70913905 | G34: =F34+G31 -> 37531233 | H34: =G34+H31 -> 6.5613254e+08 | I34: =H34+I31 -> 6.3477566e+08 | J34: =I34+J31 -> 6.1407504e+08 | K34: =J34+K31 -> 5.0131196e+08 | L34: =K34+L31 -> 4.3430399e+08 | ... KQ34: =KP34+KQ31 -> 2.5663224e+09
B35: Дисконтированный поток | C35: KZT | D35: =D21/(1+$C$47)^D4 -> 59441492 | E35: =E21/(1+$C$47)^E4 -> 59053027 | F35: =F21/(1+$C$47)^F4 -> 58660342 | G35: =G21/(1+$C$47)^G4 -> 3841295.9 | H35: =H21/(1+$C$47)^H4 -> -17328451 | I35: =I21/(1+$C$47)^I4 -> 14547259 | J35: =J21/(1+$C$47)^J4 -> 14878264 | K35: =K21/(1+$C$47)^K4 -> -65509861 | ... KQ35: =KQ21/(1+$C$47)^KQ4 -> 0
B36: Накопительный денежный поток | C36: KZT | D36: =D35 -> 59441492 | E36: =E35 -> 59053027 | F36: =F35 -> 58660342 | G36: =G35 -> 3841295.9 | H36: =H35 -> -17328451 | I36: =I35 -> 14547259 | J36: =J35 -> 14878264 | K36: =K35 -> -65509861 | ... KQ36: =KQ35 -> 0
B37: Индекс окупаемости, мес | C37: {=MATCH(TRUE,D34:JX34>=C23,0)} -> 1 | D37: =IF(D36<0,1,0) -> 0 | E37: =IF(E36<0,1,0) -> 0 | F37: =IF(F36<0,1,0) -> 0 | G37: =IF(G36<0,1,0) -> 0 | H37: =IF(H36<0,1,0) -> 1 | I37: =IF(I36<0,1,0) -> 0 | J37: =IF(J36<0,1,0) -> 0 | K37: =IF(K36<0,1,0) -> 1 | ... KQ37: =IF(KQ36<0,1,0) -> 0
B40: Equity discount rate | C40: =18%/12 -> 0.015
B41: IRR FCFF | C41: =IRR(D51:D52) -> 15.142248
B42: NPV FCFF | C42: =NPV(C40,E21:FA21)+D21 -> 1.8777444e+09
B44: ROE | C44: =IFERROR(C21/C23, 0) -> 0
B45: ROI | C45: =IFERROR(C21/SUM(C22:C24),0) -> 3.8019591
B46: DPP | C46: =C37 -> 1
B47: WACC месячный | C47: =21%/12 -> 0.0175
B48: ROI | C48: =IFERROR(C21/SUM(C22:C24),0) -> 3.8019591
C51: 2026 | D51: =SUM(D21:P21) -> -1.6948094e+08
C52: 2027 | D52: =SUM(Q21:AB21) -> 2.7358033e+09
C53: 2028 | D53: =SUM(AC21:AN21) -> 0
C54: 2029
C55: 2030

Sheet Цена
A1: № | B1: Площадь | C1: Офис | D1: 1057000 | E1: 0.012 | F1: Сумма | H1: Коммерция | J1: 1287500
A2: 603 | B2: 143.9 | C2: 11 | D2: =D1+D1*$E$1 -> 1069684 | E2: 0.0115 | F2: =B2*D2 -> 1.5392753e+08 | H2: C101 | I2: 138.79 | J2: =J1+J1*K2 -> 1301662.5 | K2: 0.011 | L2: =I2*J2 -> 1.8065774e+08
A3: 703 | B3: 143.9 | C3: 15 | D3: =D2+D2*$E$1 -> 1082520.2 | E3: 0.011 | F3: =B3*D3 -> 1.5577466e+08 | H3: C102 | I3: 268.95 | J3: =J1+J1*K3 -> 1301018.8 | K3: 0.0105 | L3: =I3*J3 -> 3.4990899e+08
A4: 803 | B4: 143.9 | C4: 19 | D4: =D3+D3*$E$1 -> 1095510.5 | F4: =B4*D4 -> 1.5764395e+08 | J4: =AVERAGE(J2:J3) -> 1301340.6 | L4: =SUM(L2:L3) -> 5.3056673e+08
A5: 602 | B5: 143.96 | C5: 10 | D5: =D4+D4*$E$1 -> 1108656.6 | F5: =B5*D5 -> 1.596022e+08
A6: 702 | B6: 143.96 | C6: 14 | D6: =D5+D5*$E$1 -> 1121960.5 | F6: =B6*D6 -> 1.6151743e+08
A7: 802 | B7: 143.96 | C7: 18 | D7: =D6+D6*$E$1 -> 1135424 | F7: =B7*D7 -> 1.6345564e+08
A8: 202 | B8: 206.76 | C8: 2 | D8: =D1+$D$1*$E$2 -> 1069155.5 | F8: =B8*D8 -> 2.2105859e+08
A9: 601 | B9: 218.81 | C9: 9 | D9: =D8+D8*$E$2 -> 1081450.8 | F9: =B9*D9 -> 2.3663225e+08
A10: 701 | B10: 218.81 | C10: 13 | D10: =D9+D9*$E$2 -> 1093887.5 | F10: =B10*D10 -> 2.3935352e+08
A11: 801 | B11: 218.81 | C11: 17 | D11: =D10+D10*$E$2 -> 1106467.2 | F11: =B11*D11 -> 2.4210608e+08
A12: 604 | B12: 221.38 | C12: 12 | D12: =D11+D11*$E$2 -> 1119191.6 | F12: =B12*D12 -> 2.4776663e+08
A13: 704 | B13: 221.38 | C13: 16 | D13: =D12+D12*$E$2 -> 1132062.3 | F13: =B13*D13 -> 2.5061594e+08
A14: 804 | B14: 221.38 | C14: 20 | D14: =D13+D13*$E$2 -> 1145081 | F14: =B14*D14 -> 2.5349803e+08
A15: 201 | B15: 345.9 | C15: 1 | D15: =D1 -> 1057000 | F15: =B15*D15 -> 365616300
A16: 301 | B16: 363.47 | C16: 3 | D16: =D15+D15*$E$3 -> 1068627 | F16: =B16*D16 -> 3.8841386e+08
A17: 401 | B17: 363.87 | C17: 5 | D17: =D16+D16*$E$3 -> 1080381.9 | F17: =B17*D17 -> 3.9311856e+08
A18: 501 | B18: 366.11 | C18: 7 | D18: =D17+D17*$E$3 -> 1092266.1 | F18: =B18*D18 -> 3.9988954e+08
A19: 302 | B19: 366.28 | C19: 4 | D19: =D18+D18*$E$3 -> 1104281 | F19: =B19*D19 -> 4.0447605e+08
A20: 402 | B20: 366.28 | C20: 6 | D20: =D19+D19*$E$3 -> 1116428.1 | F20: =B20*D20 -> 4.0892529e+08
A21: 502 | B21: 369.09 | C21: 8 | D21: =D20+D20*$E$3 -> 1128708.8 | F21: =B21*D21 -> 4.1659514e+08
A22: 1001 | B22: 560.69 | C22: 22 | D22: =D1+D21*$E$3 -> 1069415.8 | F22: =B22*D22 -> 5.9961074e+08
A23: 901 | B23: 700.45 | C23: 21 | D23: =D1 -> 1057000 | F23: =B23*D23 -> 740375650
B24: =SUM(B2:B23) -> 6193.05 | D24: =AVERAGE(D2:D23) -> 1097052.7 | F24: =SUM(F2:F23) -> 6.7599736e+09

Sheet Sensitivity
B2: Изменение Цены реализации м2 | E2: Сред. Цена, тг | F2: =F5/F4 -> 1552427.2
B3: Изменение Себестоимости | E3: Себес-ть, млн.тг | F3: ='PnL все'!B39+'PnL все'!B73 -> 8.1469776e+09
B4: Изменение м2 | E4: Объем, м2 | F4: ='PnL все'!B7 -> 6901
E5: Выручка, млн.тг | F5: ='PnL все'!B34 -> 10713300000
E6: ЧП, млн.тг | F6: ='PnL все'!B74 -> 2.5663224e+09
B8: Анализ чувствительности
B10: Изменение ЧП | E10: Изменение стоимости проекта м2
E11: =F11*(1+E12) -> 1009370.5 | F11: =G11*(1+F12) -> 1121522.8 | G11: =F3/F4 -> 1180550.3 | H11: =G11*(1+H12) -> 1239577.8 | I11: =G11*(1+I12) -> 1298605.3
E12: =D13 -> -0.1 | F12: =D14 -> -0.05 | G12: =D15 -> 0 | H12: =D16 -> 0.05 | I12: =D17 -> 0.1
B13: Изменение Цены реализации м2 | C13: =C15*(1+D13) -> 1397184.5 | D13: -0.1 | E13: =$C13*$F$4-E$11*$F$4 -> 2.6763041e+09 | F13: =$C13*$F$4-F$11*$F$4 -> 1.9023413e+09 | G13: =$C13*$F$4-G$11*$F$4 -> 1.4949924e+09 | H13: =$C13*$F$4-H$11*$F$4 -> 1.0876435e+09 | I13: =$C13*$F$4-I$11*$F$4 -> 6.8029463e+08
C14: =C15*(1+D14) -> 1474805.8 | D14: -0.05 | E14: =$C14*$F$4-E$11*$F$4 -> 3.2119691e+09 | F14: =$C14*$F$4-F$11*$F$4 -> 2.4380063e+09 | G14: =$C14*$F$4-G$11*$F$4 -> 2.0306574e+09 | H14: =$C14*$F$4-H$11*$F$4 -> 1.6233085e+09 | I14: =$C14*$F$4-I$11*$F$4 -> 1.2159596e+09
C15: =VLOOKUP(B13,B2:F4,5,FALSE) -> 1552427.2 | D15: 0 | E15: =$C15*$F$4-E$11*$F$4 -> 3.7476341e+09 | F15: =$C15*$F$4-F$11*$F$4 -> 2.9736713e+09 | G15: =$C15*$F$4-G$11*$F$4 -> 2.5663224e+09 | H15: =$C15*$F$4-H$11*$F$4 -> 2.1589735e+09 | I15: =$C15*$F$4-I$11*$F$4 -> 1.7516246e+09
C16: =C15*(1+D16) -> 1630048.5 | D16: =-D14 -> 0.05 | E16: =$C16*$F$4-E$11*$F$4 -> 4.2832991e+09 | F16: =$C16*$F$4-F$11*$F$4 -> 3.5093363e+09 | G16: =$C16*$F$4-G$11*$F$4 -> 3.1019874e+09 | H16: =$C16*$F$4-H$11*$F$4 -> 2.6946385e+09 | I16: =$C16*$F$4-I$11*$F$4 -> 2.2872896e+09
C17: =C15*(1+D17) -> 1707669.9 | D17: =-D13 -> 0.1 | E17: =$C17*$F$4-E$11*$F$4 -> 4.8189641e+09 | F17: =$C17*$F$4-F$11*$F$4 -> 4.0450013e+09 | G17: =$C17*$F$4-G$11*$F$4 -> 3.6376524e+09 | H17: =$C17*$F$4-H$11*$F$4 -> 3.2303035e+09 | I17: =$C17*$F$4-I$11*$F$4 -> 2.8229546e+09
B19: Изменение Рентабельности | E19: Изменение стоимости проекта м2
E20: =E11 -> 1009370.5 | F20: =F11 -> 1121522.8 | G20: =G11 -> 1180550.3 | H20: =H11 -> 1239577.8 | I20: =I11 -> 1298605.3
E21: =E12 -> -0.1 | F21: =F12 -> -0.05 | G21: =G12 -> 0 | H21: =H12 -> 0.05 | I21: =I12 -> 0.1
B22: Изменение средней цены за м2 | C22: =C13 -> 1397184.5 | D22: =C22/$C$23 -> 0.94736842 | E22: =E13/$F$5 -> 0.24981137 | F22: =F13/$F$5 -> 0.17756819 | G22: =G13/$F$5 -> 0.13954546 | H22: =H13/$F$5 -> 0.10152273 | I22: =I13/$F$5 -> 0.063500008
C23: =C14 -> 1474805.8 | D23: =C23/$C$23 -> 1 | E23: =E14/$F$5 -> 0.29981137 | F23: =F14/$F$5 -> 0.22756819 | G23: =G14/$F$5 -> 0.18954546 | H23: =H14/$F$5 -> 0.15152273 | I23: =I14/$F$5 -> 0.11350001
C24: =C15 -> 1552427.2 | D24: =C24/$C$23 -> 1.0526316 | E24: =E15/$F$5 -> 0.34981137 | F24: =F15/$F$5 -> 0.27756819 | G24: =G15/$F$5 -> 0.23954546 | H24: =H15/$F$5 -> 0.20152273 | I24: =I15/$F$5 -> 0.16350001
C25: =C16 -> 1630048.5 | D25: =C25/$C$23 -> 1.1052632 | E25: =E16/$F$5 -> 0.39981137 | F25: =F16/$F$5 -> 0.32756819 | G25: =G16/$F$5 -> 0.28954546 | H25: =H16/$F$5 -> 0.25152273 | I25: =I16/$F$5 -> 0.21350001
C26: =C17 -> 1707669.9 | D26: =C26/$C$23 -> 1.1578947 | E26: =E17/$F$5 -> 0.44981137 | F26: =F17/$F$5 -> 0.37756819 | G26: =G17/$F$5 -> 0.33954546 | H26: =H17/$F$5 -> 0.30152273 | I26: =I17/$F$5 -> 0.26350001

Sheet Dashboard (с перегор)
B3: Итоговые показатели
B4: Net Profit | C4: ='PnL (с перегор)'!B74 -> #REF!
B5: ROS, % | C5: ='PnL все'!B75 -> 0.23954546
B6: ROE (Отдача на капитал) | C6: =DCF!C44 -> 0
B7: WACC (Годовой) | C7: =DCF!C47*12 -> 0.21
B8: IRR (Минимальная ставка доходности) | C8: =DCF!C41*12 -> 181.70697
B9: NPV | C9: =DCF!C42 -> 1.8777444e+09
B10: PP | C10: =DCF!C37 -> 1
B11: DPP | C11: =DCF!C46 -> 1
B14: Основные вводные
B15: LAND | E15: SALES | H15: COSTS | K15: Sellable Area, sq.m | L15: =SUM(L16:L19) -> 12968.198
B16: Площадь ЗУ, га | C16: 1.1062 | E16: Цена за м2 квартиры | F16: 650000 | H16: Себестоимость за м2 | I16: 285417.25 | K16: Квартиры | L16: =11801.735625-720 -> 11081.736
B17: Курс ЗУ | C17: 470.46 | E17: Цена за м2 офиса | F17: 0 | H17: Накладные расходы | I17: 22701.345 | K17: Офисы | L17: 0
B18: Стоимость за сотку, USD | C18: 25000 | E18: Цена за м2 кладовки | F18: 150000 | H18: Расходы на реализацию | I18: 0.0455 | K18: Кладовые | L18: 841.46211
B19: Стоимость участка итого, KZT | C19: =C16*100*C18*C17 -> 1301057130 | E19: Цена за 1 м/м | F19: 6000000 | H19: Расходы офиса | I19: 0.024 | K19: Паркинг | L19: =L26*13.75 -> 1045
H20: ПИРы | I20: 7902.8232
B22: CONSTRUCTION | E22: CASH FLOW | H22: TAXES | K22: Sellable Units, pcs | L22: =SUM(L23:L26) -> 469
B23: Этажность | C23: 9 | E23: Собственный капитал | H23: НДС | I23: ='PnL все'!B70 -> 6.8771146e+08 | K23: Квартиры | L23: 240
B24: Застраиваемая площадь | E24: Кредит | F24: 200000000 | H24: КПН | I24: ='PnL все'!B73 -> 6.415806e+08 | K24: Офисы | L24: 0
B25: Продаваемая площадь | C25: ='PnL все'!B7 -> 6901 | E25: Срок займа, мес | F25: 18 | K25: Кладовые | L25: 153
B26: Прод площ 1 очереди | C26: =C25 -> 6901 | E26: Дивиденды | F26: ='PnL все'!B74 -> 2.5663224e+09 | K26: Паркинг | L26: 76
E27: Дата займа | F27: 46327
B28: ЖЦП, мес | C28: 16 | E28: Ставка, % | F28: 21
B29: Дата старта | C29: 46174 | E29: Льготный период, мес | F29: 6
B34: Собственный капитал | C34: 0
B35: Ставка займа (годовая) | C35: 0.21
B36: Стоимость акционерских денег | C36: 0.25

Sheet PnL (с перегор)
A2: Показатель | B2: KZT | C2: USD
A3: Цена за сотку (Общая), USD | B3: =B48/B5/100/B4 -> 90000
A4: Курс $ | B4: ='Dashboard все'!C17 -> 500
A5: Земельный участок га | B5: ='Dashboard все'!C16 -> 0.15
A6: Этажность | B6: ='Dashboard все'!C23 -> 10
A7: Реализуемая площадь, м2 | B7: =SUM(B8:B11) -> 17982.736 | C7: =B7 -> 17982.736
A8: Квартиры (себес м2 * площадь) | B8: ='Dashboard (с перегор)'!L16 -> 11081.736 | C8: =B8 -> 11081.736
A9: Коммерческие помещения | B9: ='Dashboard все'!L17 -> 6232 | C9: =B9 -> 6232
A10: Кладовые помещения | B10: ='Dashboard все'!L18 -> 253 | C10: =B10 -> 253
A11: Паркинги | B11: ='Dashboard все'!L19 -> 416 | C11: =B11 -> 416
A12: Реализуемое количество, шт | B12: =SUM(B13:B16) -> 50 | C12: =B12 -> 50
A13: Квартиры (себес м2 * площадь) | B13: ='Dashboard все'!L23 -> 0 | C13: =B13 -> 0
A14: Коммерческие помещения | B14: ='Dashboard все'!L24 -> 22 | C14: =B14 -> 22
A15: Кладовые помещения | B15: ='Dashboard все'!L25 -> 2 | C15: =B15 -> 2
A16: Паркинги | B16: ='Dashboard все'!L26 -> 26 | C16: =B16 -> 26
A17: Средние цены реализации: | B17: =B34/B7 -> 411343.32 | C17: =C34/C7 -> 822.68664
A18: Квартиры (себес м2 * площадь) | B18: ='Dashboard (с перегор)'!F16 -> 650000 | C18: =B18/$B$4 -> 1300
A19: Коммерческие помещения | B19: ='Dashboard (с перегор)'!F17 -> 0 | C19: =B19/$B$4 -> 0
A20: Кладовые помещения | B20: ='Dashboard (с перегор)'!F18 -> 150000 | C20: =B20/$B$4 -> 300
A21: Паркинги | B21: ='Dashboard (с перегор)'!F19 -> 6000000 | C21: =B21/$B$4 -> 12000
A22: Cебестоимость СМР за м2: | B22: =(B41+B42+B43+B44)/(B8+B9+B10+B11) -> 692590.51 | C22: =B22/$B$4 -> 1385.181
A23: Квартиры (себес м2 * площадь) | B23: ='Dashboard все'!I16 -> 665927.82 | C23: =B23/$B$4 -> 1331.8556
A24: Коммерческие помещения | B24: 0 | C24: =B24/$B$4 -> 0
A25: Кладовые помещения | B25: 0 | C25: =B25/$B$4 -> 0
A26: Паркинги | C26: =B26/$B$4 -> 0
A27: Средняя себестоимость (СМР+ПСД+опер.+накл.) | B27: =SUM(B28:B33) -> 862752.55 | C27: =B27/$B$4 -> 1725.5051
A28: Строительно-монтажные работы | B28: =B40/(B8+B9+B10+B11) -> 692590.51 | C28: =B28/$B$4 -> 1385.181
A29: Земельный участок | B29: =B48/B7 -> 37536.002 | C29: =B29/$B$4 -> 75.072004
A30: Расходы заказчика | B30: =B50/B7 -> 29712.567 | C30: =B30/$B$4 -> 59.425133
A31: Накладные расходы | B31: =B52/B7 -> 102913.48 | C31: =B31/$B$4 -> 205.82696
A32: Социальная нагрузка | B32: 0 | C32: =B32/$B$4 -> 0
A33: % по кредиту | B33: 0 | C33: =B33/$B$4 -> 0
A34: Выручка итого в т.ч. | B34: =SUM(B35:B38) -> 7.3970782e+09 | C34: =B34/B4 -> 14794156
A35: Квартиры (себес м2 * площадь) | B35: =(B8*B18) -> 7.2031282e+09 | C35: =B35/$B$4 -> 14406256
A36: Коммерческие помещения | B36: =(B9*B19) -> 0 | C36: =B36/$B$4 -> 0
A37: Кладовые помещения | B37: =(B10*B20) -> 37950000 | C37: =B37/$B$4 -> 75900
A38: Паркинги | B38: =(B16*B21) -> 156000000 | C38: =B38/$B$4 -> 312000
A39: Расходы итого: | B39: =B40+B48+B50+B52+B62+B66+B68+B70 -> #REF! | C39: =B39/$B$4 -> #REF!
A40: СМР в т.ч.: | B40: =SUM(B41:B47) -> 1.2454672e+10 | C40: =B40/$B$4 -> 24909344
A41: СМР(себес м2 * площадь) | B41: =(B7+720)*'Dashboard все'!I16 -> 1.2454672e+10
A42: Коммерческие помещения (себес м2 * площадь) | B42: =B25*B7 -> 0 | C42: =B42/$B$4 -> 0
A43: Кладовки (себес м2 * площадь)
A44: Паркинги (себес м2 * площадь)
A45: Снос строении
A46: Изменение целевого назначения
A47: Подключение к сетям
A48: ЗУ в т.ч.: | B48: =B49 -> 675000000 | C48: =B48/$B$4 -> 1350000
A49: Земельный участок | B49: ='Dashboard все'!C19 -> 675000000 | C49: =B49/$B$4 -> 1350000
A50: ПИР в т.ч.: | B50: =SUM(B51:B51) -> 5.3431323e+08 | C50: =B50/$B$4 -> 1068626.5
A51: ПИР, тг | B51: =(B7+720)*'Dashboard все'!I20 -> 5.3431323e+08 | C51: =C42*0.016 -> 0
A52: Накладные расходы вт.ч. | B52: =SUM(B53:B61) -> 1.8506659e+09 | C52: =B52/$B$4 -> 3701331.7
A53: Накладные расходы, тг | B53: ='Dashboard все'!I17*('PnL (с перегор)'!B7+720) -> 1.2120222e+09 | C53: =B53/$B$4 -> 2424044.4
A54: Административные расходы проекта, 1% | B54: =B40*1% -> 1.2454672e+08 | C54: =B54/$B$4 -> 249093.44
A55: Подготовительные работы 1% | B55: 0 | C55: =B55/$B$4 -> 0
A56: Управление проектом | B56: 0 | C56: =B56/$B$4 -> 0
A57: Представительские расходы, тг 1% | B57: 0 | C57: =B57/$B$4 -> 0
A58: Содержание HCG (11+6 этаж), 2,4% | B58: =B34*'Dashboard все'!I19 -> 1.7752988e+08 | C58: =B58/$B$4 -> 355059.75
A59: Гарантийный Резерв, 0,8% | B59: 0 | C59: =B59/$B$4 -> 0
A60: Ипотека 5% на 30% квартир | B60: =B35*5%*30%*0 -> 0 | C60: =B60/$B$4 -> 0
A61: Расходы на реализацию, тг 4,55% | B61: =B34*'Dashboard все'!I18 -> 3.3656706e+08 | C61: =B61/$B$4 -> 673134.11
A62: Соц. Инфраструктура в т.ч.: | B62: =SUM(B63:B65) -> 0 | C62: =B62/$B$4 -> 0
A63: Школа | B63: 0 | C63: =B63/$B$4 -> 0
A64: Дет. Сад | B64: 0 | C64: =B64/$B$4 -> 0
A65: Парк | B65: 0 | C65: =B65/$B$4 -> 0
A66: % по кредиту | B66: =SUM(B67:B67) -> 112218750 | C66: =B66/$B$4 -> 224437.5
A67: % по кредиту | B67: =Credit!D8 -> 112218750 | C67: =B67/$B$4 -> 224437.5
A68: НДС не разрешенный в зачет | B68: =SUM(B69:B69) -> 0 | C68: =B68/$B$4 -> 0
A69: НДС не разрешенный в зачет
A70: НДС | B70: =SUM(B71:B71) -> #REF! | C70: =B70/$B$4 -> #REF!
A71: НДС | B71: ='НДС расчет'!#REF! -> #REF! | C71: =B71/$B$4 -> #REF!
A72: Прибыль до налогообложения | B72: =B34-B39 -> #REF! | C72: =B72/$B$4 -> #REF!
A73: КПН, 20% | B73: =IF((B72)>0,(B72)*20%,0) -> #REF! | C73: =B73/$B$4 -> #REF!
A74: Чистая прибыль | B74: =B72-B73 -> #REF! | C74: =C72-C73 -> #REF!
A75: Рентабельность | B75: =B74/B34 -> #REF! | C75: =C74/C34 -> #REF!

Sheet Credit
A1: РАВНЫМИ ДОЛЯМИ | H1: не удалять
A2: Сумма | D2: ='Dashboard все'!F24 -> 675000000 | H2: АННУИТЕТ | I2: 46027
A3: Срок (мес) | D3: ='Dashboard (с перегор)'!F25 -> 18 | H3: РАВНЫМИ ДОЛЯМИ | I3: 47092
A4: % годовые | D4: ='Dashboard все'!F28 -> 21 | H4: ло | I4: =I3-I2 -> 1065
A5: Льготный период | D5: ='Dashboard все'!F29 -> 0 | H5: TRUE | I5: =I4/30 -> 35.5
A6: Дата первого взноса | D6: ='Dashboard все'!F27 -> 46204
A7: =IF(A1="АННУИТЕТ","Ежемесячный платеж","Ежемесячный платеж от") -> Ежемесячный платеж от | D7: =IF(H5=TRUE,IF($A$1="АННУИТЕТ",-PMT($D$4/(12*100),$D$3-$D$5,$D$2),$D$2/($D$3-$D$5)+$D$2*$D$4/(12*100)),IF($A$1="АННУИТЕТ",-PMT($D$4/(12*100),$D$3,$D$2),$D$2/($D$3)+$D$2*$D$4/(12*100))) -> 49312500
A8: % к выплате | D8: =SUM(D12:D251) -> 112218750
A9: Сумма к выплате | D9: =SUM(E12:E251) -> 787218750
A10: Дата взноса | B10: Взнос | C10: Выплаты по ОД | D10: Выплата процентов | E10: Сумма к выплате | F10: Сальдо капитала
F11: =D2 -> 675000000
A12: =IF($D$3>=B12,DATE(YEAR($D$6),MONTH($D$6)+B12-1,DAY($D$6)),0) -> 46204 | B12: 1 | C12: =IF(F11<0.01,0,IF($H$5=TRUE,IF(B12<=$D$5,0,IF($A$1="АННУИТЕТ",$D$7-D12,$D$2/($D$3-$D$5))),IF($A$1="АННУИТЕТ",$D$7-D12,$D$2/$D$3))) -> 37500000 | D12: =F11*($D$4/12)/100 -> 11812500 | E12: =IF($A$1="АННУИТЕТ",IF(F11>0,C12+D12,0),C12+D12) -> 49312500 | F12: =F11-C12 -> 637500000
A13: =IF($D$3>=B13,DATE(YEAR($D$6),MONTH($D$6)+B13-1,DAY($D$6)),0) -> 46235 | B13: 2 | C13: =IF(F12<0.01,0,IF($H$5=TRUE,IF(B13<=$D$5,0,IF($A$1="АННУИТЕТ",$D$7-D13,$D$2/($D$3-$D$5))),IF($A$1="АННУИТЕТ",$D$7-D13,$D$2/$D$3))) -> 37500000 | D13: =F12*($D$4/12)/100 -> 11156250 | E13: =IF($A$1="АННУИТЕТ",IF(F12>0,C13+D13,0),C13+D13) -> 48656250 | F13: =F12-C13 -> 600000000
A14: =IF($D$3>=B14,DATE(YEAR($D$6),MONTH($D$6)+B14-1,DAY($D$6)),0) -> 46266 | B14: 3 | C14: =IF(F13<0.01,0,IF($H$5=TRUE,IF(B14<=$D$5,0,IF($A$1="АННУИТЕТ",$D$7-D14,$D$2/($D$3-$D$5))),IF($A$1="АННУИТЕТ",$D$7-D14,$D$2/$D$3))) -> 37500000 | D14: =F13*($D$4/12)/100 -> 10500000 | E14: =IF($A$1="АННУИТЕТ",IF(F13>0,C14+D14,0),C14+D14) -> 48000000 | F14: =F13-C14 -> 562500000
A15: =IF($D$3>=B15,DATE(YEAR($D$6),MONTH($D$6)+B15-1,DAY($D$6)),0) -> 46296 | B15: 4 | C15: =IF(F14<0.01,0,IF($H$5=TRUE,IF(B15<=$D$5,0,IF($A$1="АННУИТЕТ",$D$7-D15,$D$2/($D$3-$D$5))),IF($A$1="АННУИТЕТ",$D$7-D15,$D$2/$D$3))) -> 37500000 | D15: =F14*($D$4/12)/100 -> 9843750 | E15: =IF($A$1="АННУИТЕТ",IF(F14>0,C15+D15,0),C15+D15) -> 47343750 | F15: =F14-C15 -> 525000000
A16: =IF($D$3>=B16,DATE(YEAR($D$6),MONTH($D$6)+B16-1,DAY($D$6)),0) -> 46327 | B16: 5 | C16: =IF(F15<0.01,0,IF($H$5=TRUE,IF(B16<=$D$5,0,IF($A$1="АННУИТЕТ",$D$7-D16,$D$2/($D$3-$D$5))),IF($A$1="АННУИТЕТ",$D$7-D16,$D$2/$D$3))) -> 37500000 | D16: =F15*($D$4/12)/100 -> 9187500 | E16: =IF($A$1="АННУИТЕТ",IF(F15>0,C16+D16,0),C16+D16) -> 46687500 | F16: =F15-C16 -> 487500000
A17: =IF($D$3>=B17,DATE(YEAR($D$6),MONTH($D$6)+B17-1,DAY($D$6)),0) -> 46357 | B17: 6 | C17: =IF(F16<0.01,0,IF($H$5=TRUE,IF(B17<=$D$5,0,IF($A$1="АННУИТЕТ",$D$7-D17,$D$2/($D$3-$D$5))),IF($A$1="АННУИТЕТ",$D$7-D17,$D$2/$D$3))) -> 37500000 | D17: =F16*($D$4/12)/100 -> 8531250 | E17: =IF($A$1="АННУИТЕТ",IF(F16>0,C17+D17,0),C17+D17) -> 46031250 | F17: =F16-C17 -> 450000000
A18: =IF($D$3>=B18,DATE(YEAR($D$6),MONTH($D$6)+B18-1,DAY($D$6)),0) -> 46388 | B18: 7 | C18: =IF(F17<0.01,0,IF($H$5=TRUE,IF(B18<=$D$5,0,IF($A$1="АННУИТЕТ",$D$7-D18,$D$2/($D$3-$D$5))),IF($A$1="АННУИТЕТ",$D$7-D18,$D$2/$D$3))) -> 37500000 | D18: =F17*($D$4/12)/100 -> 7875000 | E18: =IF($A$1="АННУИТЕТ",IF(F17>0,C18+D18,0),C18+D18) -> 45375000 | F18: =F17-C18 -> 412500000
A19: =IF($D$3>=B19,DATE(YEAR($D$6),MONTH($D$6)+B19-1,DAY($D$6)),0) -> 46419 | B19: 8 | C19: =IF(F18<0.01,0,IF($H$5=TRUE,IF(B19<=$D$5,0,IF($A$1="АННУИТЕТ",$D$7-D19,$D$2/($D$3-$D$5))),IF($A$1="АННУИТЕТ",$D$7-D19,$D$2/$D$3))) -> 37500000 | D19: =F18*($D$4/12)/100 -> 7218750 | E19: =IF($A$1="АННУИТЕТ",IF(F18>0,C19+D19,0),C19+D19) -> 44718750 | F19: =F18-C19 -> 375000000
A20: =IF($D$3>=B20,DATE(YEAR($D$6),MONTH($D$6)+B20-1,DAY($D$6)),0) -> 46447 | B20: 9 | C20: =IF(F19<0.01,0,IF($H$5=TRUE,IF(B20<=$D$5,0,IF($A$1="АННУИТЕТ",$D$7-D20,$D$2/($D$3-$D$5))),IF($A$1="АННУИТЕТ",$D$7-D20,$D$2/$D$3))) -> 37500000 | D20: =F19*($D$4/12)/100 -> 6562500 | E20: =IF($A$1="АННУИТЕТ",IF(F19>0,C20+D20,0),C20+D20) -> 44062500 | F20: =F19-C20 -> 337500000
A21: =IF($D$3>=B21,DATE(YEAR($D$6),MONTH($D$6)+B21-1,DAY($D$6)),0) -> 46478 | B21: 10 | C21: =IF(F20<0.01,0,IF($H$5=TRUE,IF(B21<=$D$5,0,IF($A$1="АННУИТЕТ",$D$7-D21,$D$2/($D$3-$D$5))),IF($A$1="АННУИТЕТ",$D$7-D21,$D$2/$D$3))) -> 37500000 | D21: =F20*($D$4/12)/100 -> 5906250 | E21: =IF($A$1="АННУИТЕТ",IF(F20>0,C21+D21,0),C21+D21) -> 43406250 | F21: =F20-C21 -> 300000000
A22: =IF($D$3>=B22,DATE(YEAR($D$6),MONTH($D$6)+B22-1,DAY($D$6)),0) -> 46508 | B22: 11 | C22: =IF(F21<0.01,0,IF($H$5=TRUE,IF(B22<=$D$5,0,IF($A$1="АННУИТЕТ",$D$7-D22,$D$2/($D$3-$D$5))),IF($A$1="АННУИТЕТ",$D$7-D22,$D$2/$D$3))) -> 37500000 | D22: =F21*($D$4/12)/100 -> 5250000 | E22: =IF($A$1="АННУИТЕТ",IF(F21>0,C22+D22,0),C22+D22) -> 42750000 | F22: =F21-C22 -> 262500000
A23: =IF($D$3>=B23,DATE(YEAR($D$6),MONTH($D$6)+B23-1,DAY($D$6)),0) -> 46539 | B23: 12 | C23: =IF(F22<0.01,0,IF($H$5=TRUE,IF(B23<=$D$5,0,IF($A$1="АННУИТЕТ",$D$7-D23,$D$2/($D$3-$D$5))),IF($A$1="АННУИТЕТ",$D$7-D23,$D$2/$D$3))) -> 37500000 | D23: =F22*($D$4/12)/100 -> 4593750 | E23: =IF($A$1="АННУИТЕТ",IF(F22>0,C23+D23,0),C23+D23) -> 42093750 | F23: =F22-C23 -> 225000000
... A371: =IF($D$3>=B371,DATE(YEAR($D$6),MONTH($D$6)+B371-1,DAY($D$6)),0) -> 0 | B371: 360 | C371: =IF(F370<0.01,0,IF($H$5=TRUE,IF(B371<=$D$5,0,IF($A$1="АННУИТЕТ",$D$7-D371,$D$2/($D$3-$D$5))),IF($A$1="АННУИТЕТ",$D$7-D371,$D$2/$D$3))) -> 0 | D371: =F370*($D$4/12)/100 -> 0 | E371: =IF($A$1="АННУИТЕТ",IF(F370>0,C371+D371,0),C371+D371) -> 0 | F371: =F370-C371 -> 0

Sheet Графики
H1: =H3-H2 -> 0
F2: =SUBTOTAL(9,F7:F306) -> 197152741 | G2: =SUBTOTAL(9,G7:G306) -> 0 | H2: =SUBTOTAL(9,H7:H306) -> 6.415806e+08 | I2: =SUBTOTAL(9,I7:I306) -> 6.8771146e+08 | J2: =SUBTOTAL(9,J7:J306) -> 112218750 | K2: =SUBTOTAL(9,K7:K306) -> 675000000
E3: ='PnL все'!B48 -> 675000000 | F3: ='PnL все'!B50 -> 197152741 | G3: ='PnL все'!B62 -> 0 | H3: ='PnL все'!B73 -> 6.415806e+08 | I3: ='PnL все'!B70 -> 6.8771146e+08 | J3: ='PnL все'!B66 -> 112218750 | K3: =Credit!D2 -> 675000000
E6: Приобретение ЗУ | F6: Проектирование | G6: Соц нагрузка | H6: КПН | I6: НДС к уплате | J6: Вознаграждение по займам | K6: Оттоки по фин.деят (ОД)
B7: 1 | C7: =MONTH(D7) -> 7 | D7: =DCF!D6 -> 46204 | F7: =$F$3*8% -> 15772219 | J7: =SUMIF(Credit!$A$12:$A$371,Графики!D7,Credit!$D$12:$D$371) -> 11812500 | K7: =SUMIF(Credit!$A$12:$A$371,Графики!D7,Credit!$C$12:$C$371) -> 37500000
B8: =B7+1 -> 2 | C8: =MONTH(D8) -> 8 | D8: =EDATE(D7,1) -> 46235 | F8: =$F$3*8% -> 15772219 | J8: =SUMIF(Credit!$A$12:$A$371,Графики!D8,Credit!$D$12:$D$371) -> 11156250 | K8: =SUMIF(Credit!$A$12:$A$371,Графики!D8,Credit!$C$12:$C$371) -> 37500000
B9: =B8+1 -> 3 | C9: =MONTH(D9) -> 9 | D9: =EDATE(D8,1) -> 46266 | F9: =$F$3*8% -> 15772219 | J9: =SUMIF(Credit!$A$12:$A$371,Графики!D9,Credit!$D$12:$D$371) -> 10500000 | K9: =SUMIF(Credit!$A$12:$A$371,Графики!D9,Credit!$C$12:$C$371) -> 37500000
B10: =B9+1 -> 4 | C10: =MONTH(D10) -> 10 | D10: =EDATE(D9,1) -> 46296 | F10: =$F$3*8% -> 15772219 | J10: =SUMIF(Credit!$A$12:$A$371,Графики!D10,Credit!$D$12:$D$371) -> 9843750 | K10: =SUMIF(Credit!$A$12:$A$371,Графики!D10,Credit!$C$12:$C$371) -> 37500000
B11: =B10+1 -> 5 | C11: =MONTH(D11) -> 11 | D11: =EDATE(D10,1) -> 46327 | F11: =$F$3*8% -> 15772219 | I11: =$I$3*5% -> 34385573 | J11: =SUMIF(Credit!$A$12:$A$371,Графики!D11,Credit!$D$12:$D$371) -> 9187500 | K11: =SUMIF(Credit!$A$12:$A$371,Графики!D11,Credit!$C$12:$C$371) -> 37500000
B12: =B11+1 -> 6 | C12: =MONTH(D12) -> 12 | D12: =EDATE(D11,1) -> 46357 | F12: =$F$3*8% -> 15772219 | J12: =SUMIF(Credit!$A$12:$A$371,Графики!D12,Credit!$D$12:$D$371) -> 8531250 | K12: =SUMIF(Credit!$A$12:$A$371,Графики!D12,Credit!$C$12:$C$371) -> 37500000
B13: =B12+1 -> 7 | C13: =MONTH(D13) -> 1 | D13: =EDATE(D12,1) -> 46388 | F13: =$F$3*8% -> 15772219 | J13: =SUMIF(Credit!$A$12:$A$371,Графики!D13,Credit!$D$12:$D$371) -> 7875000 | K13: =SUMIF(Credit!$A$12:$A$371,Графики!D13,Credit!$C$12:$C$371) -> 37500000
B14: =B13+1 -> 8 | C14: =MONTH(D14) -> 2 | D14: =EDATE(D13,1) -> 46419 | F14: =$F$3*8% -> 15772219 | I14: =$I$3*5% -> 34385573 | J14: =SUMIF(Credit!$A$12:$A$371,Графики!D14,Credit!$D$12:$D$371) -> 7218750 | K14: =SUMIF(Credit!$A$12:$A$371,Графики!D14,Credit!$C$12:$C$371) -> 37500000
B15: =B14+1 -> 9 | C15: =MONTH(D15) -> 3 | D15: =EDATE(D14,1) -> 46447 | F15: =$F$3*8% -> 15772219 | J15: =SUMIF(Credit!$A$12:$A$371,Графики!D15,Credit!$D$12:$D$371) -> 6562500 | K15: =SUMIF(Credit!$A$12:$A$371,Графики!D15,Credit!$C$12:$C$371) -> 37500000 | M15: =100/12 -> 8.3333333
B16: =B15+1 -> 10 | C16: =MONTH(D16) -> 4 | D16: =EDATE(D15,1) -> 46478 | F16: =$F$3*8% -> 15772219 | J16: =SUMIF(Credit!$A$12:$A$371,Графики!D16,Credit!$D$12:$D$371) -> 5906250 | K16: =SUMIF(Credit!$A$12:$A$371,Графики!D16,Credit!$C$12:$C$371) -> 37500000
B17: =B16+1 -> 11 | C17: =MONTH(D17) -> 5 | D17: =EDATE(D16,1) -> 46508 | F17: =$F$3*8% -> 15772219 | H17: =$H$3*20% -> 1.2831612e+08 | I17: =$I$3*5% -> 34385573 | J17: =SUMIF(Credit!$A$12:$A$371,Графики!D17,Credit!$D$12:$D$371) -> 5250000 | K17: =SUMIF(Credit!$A$12:$A$371,Графики!D17,Credit!$C$12:$C$371) -> 37500000 | M17: =8*11 -> 88
B18: =B17+1 -> 12 | C18: =MONTH(D18) -> 6 | D18: =EDATE(D17,1) -> 46539 | F18: =$F$3*12% -> 23658329 | J18: =SUMIF(Credit!$A$12:$A$371,Графики!D18,Credit!$D$12:$D$371) -> 4593750 | K18: =SUMIF(Credit!$A$12:$A$371,Графики!D18,Credit!$C$12:$C$371) -> 37500000
B19: =B18+1 -> 13 | C19: =MONTH(D19) -> 7 | D19: =EDATE(D18,1) -> 46569 | J19: =SUMIF(Credit!$A$12:$A$371,Графики!D19,Credit!$D$12:$D$371) -> 3937500 | K19: =SUMIF(Credit!$A$12:$A$371,Графики!D19,Credit!$C$12:$C$371) -> 37500000
B20: =B19+1 -> 14 | C20: =MONTH(D20) -> 8 | D20: =EDATE(D19,1) -> 46600 | I20: =$I$3*5% -> 34385573 | J20: =SUMIF(Credit!$A$12:$A$371,Графики!D20,Credit!$D$12:$D$371) -> 3281250 | K20: =SUMIF(Credit!$A$12:$A$371,Графики!D20,Credit!$C$12:$C$371) -> 37500000
B21: =B20+1 -> 15 | C21: =MONTH(D21) -> 9 | D21: =EDATE(D20,1) -> 46631 | J21: =SUMIF(Credit!$A$12:$A$371,Графики!D21,Credit!$D$12:$D$371) -> 2625000 | K21: =SUMIF(Credit!$A$12:$A$371,Графики!D21,Credit!$C$12:$C$371) -> 37500000
B22: =B21+1 -> 16 | C22: =MONTH(D22) -> 10 | D22: =EDATE(D21,1) -> 46661 | J22: =SUMIF(Credit!$A$12:$A$371,Графики!D22,Credit!$D$12:$D$371) -> 1968750 | K22: =SUMIF(Credit!$A$12:$A$371,Графики!D22,Credit!$C$12:$C$371) -> 37500000
B23: =B22+1 -> 17 | C23: =MONTH(D23) -> 11 | D23: =EDATE(D22,1) -> 46692 | I23: =$I$3*5% -> 34385573 | J23: =SUMIF(Credit!$A$12:$A$371,Графики!D23,Credit!$D$12:$D$371) -> 1312500 | K23: =SUMIF(Credit!$A$12:$A$371,Графики!D23,Credit!$C$12:$C$371) -> 37500000
B24: =B23+1 -> 18 | C24: =MONTH(D24) -> 12 | D24: =EDATE(D23,1) -> 46722 | J24: =SUMIF(Credit!$A$12:$A$371,Графики!D24,Credit!$D$12:$D$371) -> 656250 | K24: =SUMIF(Credit!$A$12:$A$371,Графики!D24,Credit!$C$12:$C$371) -> 37500000
B25: =B24+1 -> 19 | C25: =MONTH(D25) -> 1 | D25: =EDATE(D24,1) -> 46753 | J25: =SUMIF(Credit!$A$12:$A$371,Графики!D25,Credit!$D$12:$D$371) -> 0 | K25: =SUMIF(Credit!$A$12:$A$371,Графики!D25,Credit!$C$12:$C$371) -> 0
B26: =B25+1 -> 20 | C26: =MONTH(D26) -> 2 | D26: =EDATE(D25,1) -> 46784 | E26: =$E$3*100% -> 675000000 | I26: =$I$3*75% -> 5.1578359e+08 | J26: =SUMIF(Credit!$A$12:$A$371,Графики!D26,Credit!$D$12:$D$371) -> 0 | K26: =SUMIF(Credit!$A$12:$A$371,Графики!D26,Credit!$C$12:$C$371) -> 0
B27: =B26+1 -> 21 | C27: =MONTH(D27) -> 3 | D27: =EDATE(D26,1) -> 46813 | J27: =SUMIF(Credit!$A$12:$A$371,Графики!D27,Credit!$D$12:$D$371) -> 0 | K27: =SUMIF(Credit!$A$12:$A$371,Графики!D27,Credit!$C$12:$C$371) -> 0
B28: =B27+1 -> 22 | C28: =MONTH(D28) -> 4 | D28: =EDATE(D27,1) -> 46844 | J28: =SUMIF(Credit!$A$12:$A$371,Графики!D28,Credit!$D$12:$D$371) -> 0 | K28: =SUMIF(Credit!$A$12:$A$371,Графики!D28,Credit!$C$12:$C$371) -> 0
B29: =B28+1 -> 23 | C29: =MONTH(D29) -> 5 | D29: =EDATE(D28,1) -> 46874 | H29: =$H$3*80% -> 5.1326448e+08 | J29: =SUMIF(Credit!$A$12:$A$371,Графики!D29,Credit!$D$12:$D$371) -> 0 | K29: =SUMIF(Credit!$A$12:$A$371,Графики!D29,Credit!$C$12:$C$371) -> 0
B30: =B29+1 -> 24 | C30: =MONTH(D30) -> 6 | D30: =EDATE(D29,1) -> 46905 | G30: =$G$3/24 -> 0 | J30: =SUMIF(Credit!$A$12:$A$371,Графики!D30,Credit!$D$12:$D$371) -> 0 | K30: =SUMIF(Credit!$A$12:$A$371,Графики!D30,Credit!$C$12:$C$371) -> 0
B31: =B30+1 -> 25 | C31: =MONTH(D31) -> 7 | D31: =EDATE(D30,1) -> 46935 | G31: =$G$3/24 -> 0 | J31: =SUMIF(Credit!$A$12:$A$371,Графики!D31,Credit!$D$12:$D$371) -> 0 | K31: =SUMIF(Credit!$A$12:$A$371,Графики!D31,Credit!$C$12:$C$371) -> 0
B32: =B31+1 -> 26 | C32: =MONTH(D32) -> 8 | D32: =EDATE(D31,1) -> 46966 | G32: =$G$3/24 -> 0 | J32: =SUMIF(Credit!$A$12:$A$371,Графики!D32,Credit!$D$12:$D$371) -> 0 | K32: =SUMIF(Credit!$A$12:$A$371,Графики!D32,Credit!$C$12:$C$371) -> 0
B33: =B32+1 -> 27 | C33: =MONTH(D33) -> 9 | D33: =EDATE(D32,1) -> 46997 | G33: =$G$3/24 -> 0 | J33: =SUMIF(Credit!$A$12:$A$371,Графики!D33,Credit!$D$12:$D$371) -> 0 | K33: =SUMIF(Credit!$A$12:$A$371,Графики!D33,Credit!$C$12:$C$371) -> 0
B34: =B33+1 -> 28 | C34: =MONTH(D34) -> 10 | D34: =EDATE(D33,1) -> 47027 | G34: =$G$3/24 -> 0 | J34: =SUMIF(Credit!$A$12:$A$371,Графики!D34,Credit!$D$12:$D$371) -> 0 | K34: =SUMIF(Credit!$A$12:$A$371,Графики!D34,Credit!$C$12:$C$371) -> 0
B35: =B34+1 -> 29 | C35: =MONTH(D35) -> 11 | D35: =EDATE(D34,1) -> 47058 | G35: =$G$3/24 -> 0 | J35: =SUMIF(Credit!$A$12:$A$371,Графики!D35,Credit!$D$12:$D$371) -> 0 | K35: =SUMIF(Credit!$A$12:$A$371,Графики!D35,Credit!$C$12:$C$371) -> 0
B36: =B35+1 -> 30 | C36: =MONTH(D36) -> 12 | D36: =EDATE(D35,1) -> 47088 | G36: =$G$3/24 -> 0 | J36: =SUMIF(Credit!$A$12:$A$371,Графики!D36,Credit!$D$12:$D$371) -> 0 | K36: =SUMIF(Credit!$A$12:$A$371,Графики!D36,Credit!$C$12:$C$371) -> 0 | M36: =100/6 -> 16.666667
B37: =B36+1 -> 31 | C37: =MONTH(D37) -> 1 | D37: =EDATE(D36,1) -> 47119 | G37: =$G$3/24 -> 0 | J37: =SUMIF(Credit!$A$12:$A$371,Графики!D37,Credit!$D$12:$D$371) -> 0 | K37: =SUMIF(Credit!$A$12:$A$371,Графики!D37,Credit!$C$12:$C$371) -> 0 | M37: 16.666667
B38: =B37+1 -> 32 | C38: =MONTH(D38) -> 2 | D38: =EDATE(D37,1) -> 47150 | G38: =$G$3/24 -> 0 | J38: =SUMIF(Credit!$A$12:$A$371,Графики!D38,Credit!$D$12:$D$371) -> 0 | K38: =SUMIF(Credit!$A$12:$A$371,Графики!D38,Credit!$C$12:$C$371) -> 0
B39: =B38+1 -> 33 | C39: =MONTH(D39) -> 3 | D39: =EDATE(D38,1) -> 47178 | G39: =$G$3/24 -> 0 | J39: =SUMIF(Credit!$A$12:$A$371,Графики!D39,Credit!$D$12:$D$371) -> 0 | K39: =SUMIF(Credit!$A$12:$A$371,Графики!D39,Credit!$C$12:$C$371) -> 0
B40: =B39+1 -> 34 | C40: =MONTH(D40) -> 4 | D40: =EDATE(D39,1) -> 47209 | G40: =$G$3/24 -> 0 | J40: =SUMIF(Credit!$A$12:$A$371,Графики!D40,Credit!$D$12:$D$371) -> 0 | K40: =SUMIF(Credit!$A$12:$A$371,Графики!D40,Credit!$C$12:$C$371) -> 0 | M40: =16*5 -> 80
B41: =B40+1 -> 35 | C41: =MONTH(D41) -> 5 | D41: =EDATE(D40,1) -> 47239 | G41: =$G$3/24 -> 0 | J41: =SUMIF(Credit!$A$12:$A$371,Графики!D41,Credit!$D$12:$D$371) -> 0 | K41: =SUMIF(Credit!$A$12:$A$371,Графики!D41,Credit!$C$12:$C$371) -> 0
B42: =B41+1 -> 36 | C42: =MONTH(D42) -> 6 | D42: =EDATE(D41,1) -> 47270 | G42: =$G$3/24 -> 0 | J42: =SUMIF(Credit!$A$12:$A$371,Графики!D42,Credit!$D$12:$D$371) -> 0 | K42: =SUMIF(Credit!$A$12:$A$371,Графики!D42,Credit!$C$12:$C$371) -> 0
B43: =B42+1 -> 37 | C43: =MONTH(D43) -> 7 | D43: =EDATE(D42,1) -> 47300 | G43: =$G$3/24 -> 0 | J43: =SUMIF(Credit!$A$12:$A$371,Графики!D43,Credit!$D$12:$D$371) -> 0 | K43: =SUMIF(Credit!$A$12:$A$371,Графики!D43,Credit!$C$12:$C$371) -> 0 | M43: 1.94757e+08 | O43: 1.8266701e+08
B44: =B43+1 -> 38 | C44: =MONTH(D44) -> 8 | D44: =EDATE(D43,1) -> 47331 | G44: =$G$3/24 -> 0 | J44: =SUMIF(Credit!$A$12:$A$371,Графики!D44,Credit!$D$12:$D$371) -> 0 | K44: =SUMIF(Credit!$A$12:$A$371,Графики!D44,Credit!$C$12:$C$371) -> 0
B45: =B44+1 -> 39 | C45: =MONTH(D45) -> 9 | D45: =EDATE(D44,1) -> 47362 | G45: =$G$3/24 -> 0 | J45: =SUMIF(Credit!$A$12:$A$371,Графики!D45,Credit!$D$12:$D$371) -> 0 | K45: =SUMIF(Credit!$A$12:$A$371,Графики!D45,Credit!$C$12:$C$371) -> 0 | O45: =O43/2 -> 91333505
B46: =B45+1 -> 40 | C46: =MONTH(D46) -> 10 | D46: =EDATE(D45,1) -> 47392 | G46: =$G$3/24 -> 0 | J46: =SUMIF(Credit!$A$12:$A$371,Графики!D46,Credit!$D$12:$D$371) -> 0 | K46: =SUMIF(Credit!$A$12:$A$371,Графики!D46,Credit!$C$12:$C$371) -> 0
B47: =B46+1 -> 41 | C47: =MONTH(D47) -> 11 | D47: =EDATE(D46,1) -> 47423 | G47: =$G$3/24 -> 0 | J47: =SUMIF(Credit!$A$12:$A$371,Графики!D47,Credit!$D$12:$D$371) -> 0 | K47: =SUMIF(Credit!$A$12:$A$371,Графики!D47,Credit!$C$12:$C$371) -> 0
B48: =B47+1 -> 42 | C48: =MONTH(D48) -> 12 | D48: =EDATE(D47,1) -> 47453 | G48: =$G$3/24 -> 0 | J48: =SUMIF(Credit!$A$12:$A$371,Графики!D48,Credit!$D$12:$D$371) -> 0 | K48: =SUMIF(Credit!$A$12:$A$371,Графики!D48,Credit!$C$12:$C$371) -> 0 | M48: =I48*3 -> 0
B49: =B48+1 -> 43 | C49: =MONTH(D49) -> 1 | D49: =EDATE(D48,1) -> 47484 | G49: =$G$3/24 -> 0 | J49: =SUMIF(Credit!$A$12:$A$371,Графики!D49,Credit!$D$12:$D$371) -> 0 | K49: =SUMIF(Credit!$A$12:$A$371,Графики!D49,Credit!$C$12:$C$371) -> 0
B50: =B49+1 -> 44 | C50: =MONTH(D50) -> 2 | D50: =EDATE(D49,1) -> 47515 | G50: =$G$3/24 -> 0 | J50: =SUMIF(Credit!$A$12:$A$371,Графики!D50,Credit!$D$12:$D$371) -> 0 | K50: =SUMIF(Credit!$A$12:$A$371,Графики!D50,Credit!$C$12:$C$371) -> 0
B51: =B50+1 -> 45 | C51: =MONTH(D51) -> 3 | D51: =EDATE(D50,1) -> 47543 | G51: =$G$3/24 -> 0 | J51: =SUMIF(Credit!$A$12:$A$371,Графики!D51,Credit!$D$12:$D$371) -> 0 | K51: =SUMIF(Credit!$A$12:$A$371,Графики!D51,Credit!$C$12:$C$371) -> 0
B52: =B51+1 -> 46 | C52: =MONTH(D52) -> 4 | D52: =EDATE(D51,1) -> 47574 | G52: =$G$3/24 -> 0 | J52: =SUMIF(Credit!$A$12:$A$371,Графики!D52,Credit!$D$12:$D$371) -> 0 | K52: =SUMIF(Credit!$A$12:$A$371,Графики!D52,Credit!$C$12:$C$371) -> 0
B53: =B52+1 -> 47 | C53: =MONTH(D53) -> 5 | D53: =EDATE(D52,1) -> 47604 | G53: =$G$3/24 -> 0 | J53: =SUMIF(Credit!$A$12:$A$371,Графики!D53,Credit!$D$12:$D$371) -> 0 | K53: =SUMIF(Credit!$A$12:$A$371,Графики!D53,Credit!$C$12:$C$371) -> 0
B54: =B53+1 -> 48 | C54: =MONTH(D54) -> 6 | D54: =EDATE(D53,1) -> 47635 | J54: =SUMIF(Credit!$A$12:$A$371,Графики!D54,Credit!$D$12:$D$371) -> 0 | K54: =SUMIF(Credit!$A$12:$A$371,Графики!D54,Credit!$C$12:$C$371) -> 0
B55: =B54+1 -> 49 | C55: =MONTH(D55) -> 7 | D55: =EDATE(D54,1) -> 47665 | J55: =SUMIF(Credit!$A$12:$A$371,Графики!D55,Credit!$D$12:$D$371) -> 0 | K55: =SUMIF(Credit!$A$12:$A$371,Графики!D55,Credit!$C$12:$C$371) -> 0
B56: =B55+1 -> 50 | C56: =MONTH(D56) -> 8 | D56: =EDATE(D55,1) -> 47696 | J56: =SUMIF(Credit!$A$12:$A$371,Графики!D56,Credit!$D$12:$D$371) -> 0 | K56: =SUMIF(Credit!$A$12:$A$371,Графики!D56,Credit!$C$12:$C$371) -> 0
B57: =B56+1 -> 51 | C57: =MONTH(D57) -> 9 | D57: =EDATE(D56,1) -> 47727 | J57: =SUMIF(Credit!$A$12:$A$371,Графики!D57,Credit!$D$12:$D$371) -> 0 | K57: =SUMIF(Credit!$A$12:$A$371,Графики!D57,Credit!$C$12:$C$371) -> 0
B58: =B57+1 -> 52 | C58: =MONTH(D58) -> 10 | D58: =EDATE(D57,1) -> 47757 | J58: =SUMIF(Credit!$A$12:$A$371,Графики!D58,Credit!$D$12:$D$371) -> 0 | K58: =SUMIF(Credit!$A$12:$A$371,Графики!D58,Credit!$C$12:$C$371) -> 0
B59: =B58+1 -> 53 | C59: =MONTH(D59) -> 11 | D59: =EDATE(D58,1) -> 47788 | J59: =SUMIF(Credit!$A$12:$A$371,Графики!D59,Credit!$D$12:$D$371) -> 0 | K59: =SUMIF(Credit!$A$12:$A$371,Графики!D59,Credit!$C$12:$C$371) -> 0
B60: =B59+1 -> 54 | C60: =MONTH(D60) -> 12 | D60: =EDATE(D59,1) -> 47818 | J60: =SUMIF(Credit!$A$12:$A$371,Графики!D60,Credit!$D$12:$D$371) -> 0 | K60: =SUMIF(Credit!$A$12:$A$371,Графики!D60,Credit!$C$12:$C$371) -> 0
B61: =B60+1 -> 55 | C61: =MONTH(D61) -> 1 | D61: =EDATE(D60,1) -> 47849 | J61: =SUMIF(Credit!$A$12:$A$371,Графики!D61,Credit!$D$12:$D$371) -> 0 | K61: =SUMIF(Credit!$A$12:$A$371,Графики!D61,Credit!$C$12:$C$371) -> 0
B62: =B61+1 -> 56 | C62: =MONTH(D62) -> 2 | D62: =EDATE(D61,1) -> 47880 | J62: =SUMIF(Credit!$A$12:$A$371,Графики!D62,Credit!$D$12:$D$371) -> 0 | K62: =SUMIF(Credit!$A$12:$A$371,Графики!D62,Credit!$C$12:$C$371) -> 0
B63: =B62+1 -> 57 | C63: =MONTH(D63) -> 3 | D63: =EDATE(D62,1) -> 47908 | J63: =SUMIF(Credit!$A$12:$A$371,Графики!D63,Credit!$D$12:$D$371) -> 0 | K63: =SUMIF(Credit!$A$12:$A$371,Графики!D63,Credit!$C$12:$C$371) -> 0
B64: =B63+1 -> 58 | C64: =MONTH(D64) -> 4 | D64: =EDATE(D63,1) -> 47939 | J64: =SUMIF(Credit!$A$12:$A$371,Графики!D64,Credit!$D$12:$D$371) -> 0 | K64: =SUMIF(Credit!$A$12:$A$371,Графики!D64,Credit!$C$12:$C$371) -> 0
B65: =B64+1 -> 59 | C65: =MONTH(D65) -> 5 | D65: =EDATE(D64,1) -> 47969 | J65: =SUMIF(Credit!$A$12:$A$371,Графики!D65,Credit!$D$12:$D$371) -> 0 | K65: =SUMIF(Credit!$A$12:$A$371,Графики!D65,Credit!$C$12:$C$371) -> 0
... B306: =B305+1 -> 300 | C306: =MONTH(D306) -> 6 | D306: =EDATE(D305,1) -> 55305 | J306: =SUMIF(Credit!$A$12:$A$371,Графики!D306,Credit!$D$12:$D$371) -> 0 | K306: =SUMIF(Credit!$A$12:$A$371,Графики!D306,Credit!$C$12:$C$371) -> 0

Sheet НДС расчет
B2: Себестоимость без НДС | C2: =C3/1.16 -> 4.9374068e+09
B3: Себестоимость с НДС | C3: ='PnL все'!B40+'PnL все'!B50+'PnL все'!B53+'PnL все'!B61 -> 5727391923
B4: НДС к зачету входящий | C4: =C3-C2 -> 7.8998509e+08
B5: Выручка без НДС | C5: ='PnL все'!B34/1.16 -> 9.2356034e+09
B6: Выручка с НДС | C6: ='PnL все'!B34 -> 10713300000
B7: Исходящий НДС (начисленный) | C7: =C6-C5 -> 1.4776966e+09
B8: НДС к уплате в бюджет | C8: =C7-C4 -> 6.8771146e+08

Sheet Sales
I1: Months
C2: Реализуемая площадь | D2: ='Dashboard все'!C25 -> 6901 | I2: 1-4 | J2: 0.03 | K2: 4 | L2: =J2*K2 -> 0.12
C3: Площадь одной очереди | D3: ='Dashboard все'!C26 -> 6901 | I3: 5-8 | J3: 0.031 | K3: =8-5+1 -> 4 | L3: =J3*K3 -> 0.124
C4: Количество очередей | D4: 1 | I4: 9-13 | J4: 0.032 | K4: =13-9+1 -> 5 | L4: =J4*K4 -> 0.16
C5: Итого продажи | D5: ='PnL все'!B34 -> 10713300000 | I5: 14-18 | J5: 0.033 | K5: =18-14+1 -> 5 | L5: =J5*K5 -> 0.165
C6: Продажи на 1 очередь | D6: =D5/D4 -> 10713300000 | I6: 19-24 | J6: =L6/K6 -> 0.071833333 | K6: =24-19+1 -> 6 | L6: =L10-L2-L3-L4-L5 -> 0.431
I7: 25-29 | J7: 0.036 | K7: =29-25+1 -> 5
I8: 30-33 | K8: =33-30+1 -> 4
D9: =D6-B14 -> 0
I10: Total | J10: 0.01 | K10: =SUM(K2:K9) -> 33 | L10: 1
E13: =DCF!D6 -> 46204 | F13: =EDATE(E13,1) -> 46235 | G13: =EDATE(F13,1) -> 46266 | H13: =EDATE(G13,1) -> 46296 | I13: =EDATE(H13,1) -> 46327 | J13: =EDATE(I13,1) -> 46357 | K13: =EDATE(J13,1) -> 46388 | L13: =EDATE(K13,1) -> 46419 | M13: =EDATE(L13,1) -> 46447 | ... EQ13: =EDATE(EP13,1) -> 50526
B14: =SUM(B15:B34) -> 10713300000 | D14: Очередь | E14: 1 | F14: =E14+1 -> 2 | G14: =F14+1 -> 3 | H14: =G14+1 -> 4 | I14: =H14+1 -> 5 | J14: =I14+1 -> 6 | K14: =J14+1 -> 7 | L14: =K14+1 -> 8 | M14: =L14+1 -> 9 | ... EQ14: =EP14+1 -> 143
B15: =SUM(E15:EQ15) -> 10713300000 | C15: =IF(D15<=$D$4,1,0) -> 1 | D15: 1 | E15: =$J$2*$D$6 -> 321399000 | F15: =$J$2*$D$6 -> 321399000 | G15: =$J$2*$D$6 -> 321399000 | H15: =$J$2*$D$6 -> 321399000 | I15: =$J$3*$D$6 -> 332112300 | J15: =$J$3*$D$6 -> 332112300 | K15: =$J$3*$D$6 -> 332112300 | L15: =$J$3*$D$6 -> 332112300 | M15: =$J$4*$D$6 -> 342825600 | N15: =$J$4*$D$6 -> 342825600 | O15: =$J$4*$D$6 -> 342825600 | P15: =$J$4*$D$6 -> 342825600 | Q15: =$J$4*$D$6 -> 342825600 | R15: =$J$5*$D$6 -> 353538900 | S15: =$J$5*$D$6 -> 353538900 | T15: =$J$5*$D$6 -> 353538900 | U15: =$J$5*$D$6 -> 353538900 | V15: =$J$5*$D$6 -> 353538900 | W15: =$J$6*$D$6 -> 7.6957205e+08 | X15: =$J$6*$D$6 -> 7.6957205e+08 | Y15: =$J$6*$D$6 -> 7.6957205e+08 | Z15: =$J$6*$D$6 -> 7.6957205e+08 | AA15: =$J$6*$D$6 -> 7.6957205e+08 | AB15: =$J$6*$D$6 -> 7.6957205e+08 | AC15: 0 | AD15: 0 | AE15: 0 | AF15: 0 | AG15: 0 | AH15: =$J$8*$D$6 -> 0 | AI15: =$J$8*$D$6 -> 0 | AJ15: =$J$8*$D$6 -> 0 | AK15: =$J$8*$D$6 -> 0
B16: =SUM(E16:EQ16) -> 0 | C16: =IF(D16<=$D$4,1,0) -> 0 | D16: =D15+C15 -> 2 | K16: =IF($C16=1,E$15,0) -> 0 | L16: =IF($C$16=1,F15,0) -> 0 | M16: =IF($C$16=1,G15,0) -> 0 | N16: =IF($C$16=1,H15,0) -> 0 | O16: =IF($C$16=1,I15,0) -> 0 | P16: =IF($C$16=1,J15,0) -> 0 | Q16: =IF($C$16=1,K15,0) -> 0 | R16: =IF($C$16=1,L15,0) -> 0 | S16: =IF($C$16=1,M15,0) -> 0 | ... CY16: =IF($C$16=1,CS15,0) -> 0
B17: =SUM(E17:EQ17) -> 0 | C17: =IF(D17<=$D$4,1,0) -> 0 | D17: 3 | Q17: =IF($C17=1,E$15,0) -> 0 | R17: =IF($C17=1,F$15,0) -> 0 | S17: =IF($C17=1,G$15,0) -> 0 | T17: =IF($C17=1,H$15,0) -> 0 | U17: =IF($C17=1,I$15,0) -> 0 | V17: =IF($C17=1,J$15,0) -> 0 | W17: =IF($C17=1,K$15,0) -> 0 | X17: =IF($C17=1,L$15,0) -> 0 | ... CZ17: =IF($C17=1,CN$15,0) -> 0
B18: =SUM(E18:EQ18) -> 0 | C18: =IF(D18<=$D$4,1,0) -> 0 | D18: 4 | W18: =IF($C18=1,E$15,0) -> 0 | X18: =IF($C18=1,F$15,0) -> 0 | Y18: =IF($C18=1,G$15,0) -> 0 | Z18: =IF($C18=1,H$15,0) -> 0 | AA18: =IF($C18=1,I$15,0) -> 0 | AB18: =IF($C18=1,J$15,0) -> 0 | AC18: =IF($C18=1,K$15,0) -> 0 | AD18: =IF($C18=1,L$15,0) -> 0 | ... AT18: =IF($C18=1,AB$15,0) -> 0
B19: =SUM(E19:EQ19) -> 0 | C19: =IF(D19<=$D$4,1,0) -> 0 | D19: 5 | AC19: =IF($C19=1,E$15,0) -> 0 | AD19: =IF($C19=1,F$15,0) -> 0 | AE19: =IF($C19=1,G$15,0) -> 0 | AF19: =IF($C19=1,H$15,0) -> 0 | AG19: =IF($C19=1,I$15,0) -> 0 | AH19: =IF($C19=1,J$15,0) -> 0 | AI19: =IF($C19=1,K$15,0) -> 0 | AJ19: =IF($C19=1,L$15,0) -> 0 | ... AZ19: =IF($C19=1,AB$15,0) -> 0
B20: =SUM(E20:EQ20) -> 0 | C20: =IF(D20<=$D$4,1,0) -> 0 | D20: 6 | AI20: =IF($C20=1,E$15,0) -> 0 | AJ20: =IF($C20=1,F$15,0) -> 0 | AK20: =IF($C20=1,G$15,0) -> 0 | AL20: =IF($C20=1,H$15,0) -> 0 | AM20: =IF($C20=1,I$15,0) -> 0 | AN20: =IF($C20=1,J$15,0) -> 0 | AO20: =IF($C20=1,K$15,0) -> 0 | AP20: =IF($C20=1,L$15,0) -> 0 | ... BF20: =IF($C20=1,AB$15,0) -> 0
B21: =SUM(E21:EQ21) -> 0 | C21: =IF(D21<=$D$4,1,0) -> 0 | D21: 7 | AO21: =IF($C21=1,E$15,0) -> 0 | AP21: =IF($C21=1,F$15,0) -> 0 | AQ21: =IF($C21=1,G$15,0) -> 0 | AR21: =IF($C21=1,H$15,0) -> 0 | AS21: =IF($C21=1,I$15,0) -> 0 | AT21: =IF($C21=1,J$15,0) -> 0 | AU21: =IF($C21=1,K$15,0) -> 0 | AV21: =IF($C21=1,L$15,0) -> 0 | ... BL21: =IF($C21=1,AB$15,0) -> 0
B22: =SUM(E22:EQ22) -> 0 | C22: =IF(D22<=$D$4,1,0) -> 0 | D22: 8 | AU22: =IF($C22=1,E$15,0) -> 0 | AV22: =IF($C22=1,F$15,0) -> 0 | AW22: =IF($C22=1,G$15,0) -> 0 | AX22: =IF($C22=1,H$15,0) -> 0 | AY22: =IF($C22=1,I$15,0) -> 0 | AZ22: =IF($C22=1,J$15,0) -> 0 | BA22: =IF($C22=1,K$15,0) -> 0 | BB22: =IF($C22=1,L$15,0) -> 0 | ... BR22: =IF($C22=1,AB$15,0) -> 0
B23: =SUM(AC23:EQ23) -> 0 | C23: =IF(D23<=$D$4,1,0) -> 0 | D23: 9 | BA23: =IF($C23=1,E$15,0) -> 0 | BB23: =IF($C23=1,F$15,0) -> 0 | BC23: =IF($C23=1,G$15,0) -> 0 | BD23: =IF($C23=1,H$15,0) -> 0 | BE23: =IF($C23=1,I$15,0) -> 0 | BF23: =IF($C23=1,J$15,0) -> 0 | BG23: =IF($C23=1,K$15,0) -> 0 | BH23: =IF($C23=1,L$15,0) -> 0 | ... BX23: =IF($C23=1,AB$15,0) -> 0
B24: =SUM(AC24:EQ24) -> 0 | C24: =IF(D24<=$D$4,1,0) -> 0 | D24: 10 | BG24: =IF($C24=1,E$15,0) -> 0 | BH24: =IF($C24=1,F$15,0) -> 0 | BI24: =IF($C24=1,G$15,0) -> 0 | BJ24: =IF($C24=1,H$15,0) -> 0 | BK24: =IF($C24=1,I$15,0) -> 0 | BL24: =IF($C24=1,J$15,0) -> 0 | BM24: =IF($C24=1,K$15,0) -> 0 | BN24: =IF($C24=1,L$15,0) -> 0 | ... CD24: =IF($C24=1,AB$15,0) -> 0
B25: =SUM(AC25:EQ25) -> 0 | C25: =IF(D25<=$D$4,1,0) -> 0 | D25: 11 | BM25: =IF($C25=1,E$15,0) -> 0 | BN25: =IF($C25=1,F$15,0) -> 0 | BO25: =IF($C25=1,G$15,0) -> 0 | BP25: =IF($C25=1,H$15,0) -> 0 | BQ25: =IF($C25=1,I$15,0) -> 0 | BR25: =IF($C25=1,J$15,0) -> 0 | BS25: =IF($C25=1,K$15,0) -> 0 | BT25: =IF($C25=1,L$15,0) -> 0 | ... CJ25: =IF($C25=1,AB$15,0) -> 0
B26: =SUM(E26:EQ26) -> 0 | C26: =IF(D26<=$D$4,1,0) -> 0 | D26: 12 | BS26: =IF($C26=1,K$15,0) -> 0 | BT26: =IF($C26=1,L$15,0) -> 0 | BU26: =IF($C26=1,M$15,0) -> 0 | BV26: =IF($C26=1,N$15,0) -> 0 | BW26: =IF($C26=1,O$15,0) -> 0 | BX26: =IF($C26=1,P$15,0) -> 0 | BY26: =IF($C26=1,Q$15,0) -> 0 | BZ26: =IF($C26=1,R$15,0) -> 0 | ... CP26: =IF($C26=1,AH$15,0) -> 0
B27: =SUM(E27:EQ27) -> 0 | C27: =IF(D27<=$D$4,1,0) -> 0 | D27: 13 | BY27: =IF($C27=1,Q$15,0) -> 0 | BZ27: =IF($C27=1,R$15,0) -> 0 | CA27: =IF($C27=1,S$15,0) -> 0 | CB27: =IF($C27=1,T$15,0) -> 0 | CC27: =IF($C27=1,U$15,0) -> 0 | CD27: =IF($C27=1,V$15,0) -> 0 | CE27: =IF($C27=1,W$15,0) -> 0 | CF27: =IF($C27=1,X$15,0) -> 0 | ... CV27: =IF($C27=1,AN$15,0) -> 0
B28: =SUM(E28:EQ28) -> 0 | C28: =IF(D28<=$D$4,1,0) -> 0 | D28: 14 | CE28: =IF($C28=1,W$15,0) -> 0 | CF28: =IF($C28=1,X$15,0) -> 0 | CG28: =IF($C28=1,Y$15,0) -> 0 | CH28: =IF($C28=1,Z$15,0) -> 0 | CI28: =IF($C28=1,AA$15,0) -> 0 | CJ28: =IF($C28=1,AB$15,0) -> 0 | CK28: =IF($C28=1,AC$15,0) -> 0 | CL28: =IF($C28=1,AD$15,0) -> 0 | ... DB28: =IF($C28=1,AT$15,0) -> 0
B29: =SUM(E29:EQ29) -> 0 | C29: =IF(D29<=$D$4,1,0) -> 0 | D29: 15 | CK29: =IF($C29=1,AC$15,0) -> 0 | CL29: =IF($C29=1,AD$15,0) -> 0 | CM29: =IF($C29=1,AE$15,0) -> 0 | CN29: =IF($C29=1,AF$15,0) -> 0 | CO29: =IF($C29=1,AG$15,0) -> 0 | CP29: =IF($C29=1,AH$15,0) -> 0 | CQ29: =IF($C29=1,AI$15,0) -> 0 | CR29: =IF($C29=1,AJ$15,0) -> 0 | ... DH29: =IF($C29=1,AZ$15,0) -> 0
B30: =SUM(E30:EQ30) -> 0 | C30: =IF(D30<=$D$4,1,0) -> 0 | D30: 16 | CQ30: =IF($C30=1,AI$15,0) -> 0 | CR30: =IF($C30=1,AJ$15,0) -> 0 | CS30: =IF($C30=1,AK$15,0) -> 0 | CT30: =IF($C30=1,AL$15,0) -> 0 | CU30: =IF($C30=1,AM$15,0) -> 0 | CV30: =IF($C30=1,AN$15,0) -> 0 | CW30: =IF($C30=1,AO$15,0) -> 0 | CX30: =IF($C30=1,AP$15,0) -> 0 | ... DN30: =IF($C30=1,BF$15,0) -> 0
B31: =SUM(E31:EQ31) -> 0 | C31: =IF(D31<=$D$4,1,0) -> 0 | D31: 17 | CW31: =IF($C31=1,AO$15,0) -> 0 | CX31: =IF($C31=1,AP$15,0) -> 0 | CY31: =IF($C31=1,AQ$15,0) -> 0 | CZ31: =IF($C31=1,AR$15,0) -> 0 | DA31: =IF($C31=1,AS$15,0) -> 0 | DB31: =IF($C31=1,AT$15,0) -> 0 | DC31: =IF($C31=1,AU$15,0) -> 0 | DD31: =IF($C31=1,AV$15,0) -> 0 | ... DT31: =IF($C31=1,BL$15,0) -> 0
B32: =SUM(E32:EQ32) -> 0 | C32: =IF(D32<=$D$4,1,0) -> 0 | D32: 18 | DC32: =IF($C32=1,AU$15,0) -> 0 | DD32: =IF($C32=1,AV$15,0) -> 0 | DE32: =IF($C32=1,AW$15,0) -> 0 | DF32: =IF($C32=1,AX$15,0) -> 0 | DG32: =IF($C32=1,AY$15,0) -> 0 | DH32: =IF($C32=1,AZ$15,0) -> 0 | DI32: =IF($C32=1,BA$15,0) -> 0 | DJ32: =IF($C32=1,BB$15,0) -> 0 | ... DZ32: =IF($C32=1,BR$15,0) -> 0
B33: =SUM(E33:EQ33) -> 0 | C33: =IF(D33<=$D$4,1,0) -> 0 | D33: 19 | DI33: =IF($C33=1,BA$15,0) -> 0 | DJ33: =IF($C33=1,BB$15,0) -> 0 | DK33: =IF($C33=1,BC$15,0) -> 0 | DL33: =IF($C33=1,BD$15,0) -> 0 | DM33: =IF($C33=1,BE$15,0) -> 0 | DN33: =IF($C33=1,BF$15,0) -> 0 | DO33: =IF($C33=1,BG$15,0) -> 0 | DP33: =IF($C33=1,BH$15,0) -> 0 | ... EF33: =IF($C33=1,BX$15,0) -> 0
B34: =SUM(E34:EQ34) -> 0 | C34: =IF(D34<=$D$4,1,0) -> 0 | D34: 20 | DO34: =IF($C34=1,BG$15,0) -> 0 | DP34: =IF($C34=1,BH$15,0) -> 0 | DQ34: =IF($C34=1,BI$15,0) -> 0 | DR34: =IF($C34=1,BJ$15,0) -> 0 | DS34: =IF($C34=1,BK$15,0) -> 0 | DT34: =IF($C34=1,BL$15,0) -> 0 | DU34: =IF($C34=1,BM$15,0) -> 0 | DV34: =IF($C34=1,BN$15,0) -> 0 | ... EL34: =IF($C34=1,CD$15,0) -> 0
D36: Total | E36: =SUM(E15:E34) -> 321399000 | F36: =SUM(F15:F34) -> 321399000 | G36: =SUM(G15:G34) -> 321399000 | H36: =SUM(H15:H34) -> 321399000 | I36: =SUM(I15:I34) -> 332112300 | J36: =SUM(J15:J34) -> 332112300 | K36: =SUM(K15:K34) -> 332112300 | L36: =SUM(L15:L34) -> 332112300 | ... EQ36: =SUM(EQ15:EQ34) -> 0

Sheet Costs
L1: Months
C2: Реализуемая площадь | D2: ='Dashboard все'!C25 -> 6901 | L2: 1 - 3 | M2: 0.04 | N2: 3 | O2: =M2*N2 -> 0.12
C3: Площадь одной очереди | D3: ='Dashboard все'!C26 -> 6901 | L3: 4 - 7 | M3: 0.05 | N3: =7-4+1 -> 4 | O3: =M3*N3 -> 0.2
C4: Количество очередей | D4: 1 | L4: 8 - 14 | M4: 0.06 | N4: =14-8+1 -> 7 | O4: =M4*N4 -> 0.42
C5: СМР + Накладные | D5: ='PnL все'!B40+'PnL все'!B52 -> 5.8333141e+09 | L5: 15 - 19 | M5: =O5/N5 -> 0.052 | N5: =19-15+1 -> 5 | O5: =O8-O2-O3-O4 -> 0.26
C6: Расходы на 1 очередь | D6: =D5/D4 -> 5.8333141e+09 | L6: 22 -24 | N6: =15-14+1 -> 2 | O6: =M6*N6 -> 0
L7: 16 -17 | M7: =O7/N7 -> 0 | N7: =17-16+1 -> 2 | O7: =O8-O2-O3-O4-O5-O6 -> 0
L8: Total | M8: 0.01 | N8: =SUM(N2:N7) -> 23 | O8: 1
C11: =D6-B15 -> 0
C13: =C12/D6 -> 0
E14: =DCF!D6 -> 46204 | F14: =DCF!E6 -> 46235 | G14: =DCF!F6 -> 46266 | H14: =DCF!G6 -> 46296 | I14: =DCF!H6 -> 46327 | J14: =DCF!I6 -> 46357 | K14: =DCF!J6 -> 46388 | L14: =DCF!K6 -> 46419 | ... ET14: =DCF!ES6 -> 50618
B15: =SUM(B16:B35) -> 5.8333141e+09 | D15: Очередь | E15: 1 | F15: =E15+1 -> 2 | G15: =F15+1 -> 3 | H15: =G15+1 -> 4 | I15: =H15+1 -> 5 | J15: =I15+1 -> 6 | K15: =J15+1 -> 7 | L15: =K15+1 -> 8 | M15: =L15+1 -> 9 | ... ET15: =ES15+1 -> 146
B16: =SUM(E16:ET16) -> 5.8333141e+09 | C16: =IF(D16<=$D$4,1,0) -> 1 | D16: 1 | E16: =$M$2*$D$6 -> 2.3333256e+08 | F16: =$M$2*$D$6 -> 2.3333256e+08 | G16: =$M$2*$D$6 -> 2.3333256e+08 | H16: =$M$3*$D$6 -> 2.916657e+08 | I16: =$M$3*$D$6 -> 2.916657e+08 | J16: =$M$3*$D$6 -> 2.916657e+08 | K16: =$M$3*$D$6 -> 2.916657e+08 | L16: =$M$4*$D$6 -> 3.4999884e+08 | M16: =$M$4*$D$6 -> 3.4999884e+08 | N16: =$M$4*$D$6 -> 3.4999884e+08 | O16: =$M$4*$D$6 -> 3.4999884e+08 | P16: =$M$4*$D$6 -> 3.4999884e+08 | Q16: =$M$4*$D$6 -> 3.4999884e+08 | R16: =$M$4*$D$6 -> 3.4999884e+08 | S16: =$M$5*$D$6 -> 3.0333233e+08 | T16: =$M$5*$D$6 -> 3.0333233e+08 | U16: =$M$5*$D$6 -> 3.0333233e+08 | V16: =$M$5*$D$6 -> 3.0333233e+08 | W16: =$M$5*$D$6 -> 3.0333233e+08 | X16: 0 | Z16: 0
B17: =SUM(H17:ET17) -> 0 | C17: =IF(D17<=$D$4,1,0) -> 0 | D17: =D16+C16 -> 2 | N17: =IF($C17=1,H$16,0) -> 0 | O17: =IF($C$17=1,I16,0) -> 0 | P17: =IF($C$17=1,J16,0) -> 0 | Q17: =IF($C$17=1,K16,0) -> 0 | R17: =IF($C$17=1,L16,0) -> 0 | S17: =IF($C$17=1,M16,0) -> 0 | T17: =IF($C$17=1,N16,0) -> 0 | U17: =IF($C$17=1,O16,0) -> 0 | V17: =IF($C$17=1,P16,0) -> 0 | ... AK17: =IF($C$17=1,AE16,0) -> 0
B18: =SUM(H18:ET18) -> 0 | C18: =IF(D18<=$D$4,1,0) -> 0 | D18: 3 | T18: =IF($C18=1,H$16,0) -> 0 | U18: =IF($C18=1,I$16,0) -> 0 | V18: =IF($C18=1,J$16,0) -> 0 | W18: =IF($C18=1,K$16,0) -> 0 | X18: =IF($C18=1,L$16,0) -> 0 | Y18: =IF($C18=1,M$16,0) -> 0 | Z18: =IF($C18=1,N$16,0) -> 0 | AA18: =IF($C18=1,O$16,0) -> 0 | ... AQ18: =IF($C18=1,AE$16,0) -> 0
B19: =SUM(H19:ET19) -> 0 | C19: =IF(D19<=$D$4,1,0) -> 0 | D19: 4 | Z19: =IF($C19=1,H$16,0) -> 0 | AA19: =IF($C19=1,I$16,0) -> 0 | AB19: =IF($C19=1,J$16,0) -> 0 | AC19: =IF($C19=1,K$16,0) -> 0 | AD19: =IF($C19=1,L$16,0) -> 0 | AE19: =IF($C19=1,M$16,0) -> 0 | AF19: =IF($C19=1,N$16,0) -> 0 | AG19: =IF($C19=1,O$16,0) -> 0 | ... AW19: =IF($C19=1,AE$16,0) -> 0
B20: =SUM(H20:ET20) -> 0 | C20: =IF(D20<=$D$4,1,0) -> 0 | D20: 5 | AF20: =IF($C20=1,H$16,0) -> 0 | AG20: =IF($C20=1,I$16,0) -> 0 | AH20: =IF($C20=1,J$16,0) -> 0 | AI20: =IF($C20=1,K$16,0) -> 0 | AJ20: =IF($C20=1,L$16,0) -> 0 | AK20: =IF($C20=1,M$16,0) -> 0 | AL20: =IF($C20=1,N$16,0) -> 0 | AM20: =IF($C20=1,O$16,0) -> 0 | ... BC20: =IF($C20=1,AE$16,0) -> 0
B21: =SUM(H21:ET21) -> 0 | C21: =IF(D21<=$D$4,1,0) -> 0 | D21: 6 | AL21: =IF($C21=1,H$16,0) -> 0 | AM21: =IF($C21=1,I$16,0) -> 0 | AN21: =IF($C21=1,J$16,0) -> 0 | AO21: =IF($C21=1,K$16,0) -> 0 | AP21: =IF($C21=1,L$16,0) -> 0 | AQ21: =IF($C21=1,M$16,0) -> 0 | AR21: =IF($C21=1,N$16,0) -> 0 | AS21: =IF($C21=1,O$16,0) -> 0 | ... BI21: =IF($C21=1,AE$16,0) -> 0
B22: =SUM(H22:ET22) -> 0 | C22: =IF(D22<=$D$4,1,0) -> 0 | D22: 7 | AR22: =IF($C22=1,H$16,0) -> 0 | AS22: =IF($C22=1,I$16,0) -> 0 | AT22: =IF($C22=1,J$16,0) -> 0 | AU22: =IF($C22=1,K$16,0) -> 0 | AV22: =IF($C22=1,L$16,0) -> 0 | AW22: =IF($C22=1,M$16,0) -> 0 | AX22: =IF($C22=1,N$16,0) -> 0 | AY22: =IF($C22=1,O$16,0) -> 0 | ... BO22: =IF($C22=1,AE$16,0) -> 0
B23: =SUM(H23:ET23) -> 0 | C23: =IF(D23<=$D$4,1,0) -> 0 | D23: 8 | AX23: =IF($C23=1,H$16,0) -> 0 | AY23: =IF($C23=1,I$16,0) -> 0 | AZ23: =IF($C23=1,J$16,0) -> 0 | BA23: =IF($C23=1,K$16,0) -> 0 | BB23: =IF($C23=1,L$16,0) -> 0 | BC23: =IF($C23=1,M$16,0) -> 0 | BD23: =IF($C23=1,N$16,0) -> 0 | BE23: =IF($C23=1,O$16,0) -> 0 | ... BU23: =IF($C23=1,AE$16,0) -> 0
B24: =SUM(AF24:ET24) -> 0 | C24: =IF(D24<=$D$4,1,0) -> 0 | D24: 9 | BD24: =IF($C24=1,H$16,0) -> 0 | BE24: =IF($C24=1,I$16,0) -> 0 | BF24: =IF($C24=1,J$16,0) -> 0 | BG24: =IF($C24=1,K$16,0) -> 0 | BH24: =IF($C24=1,L$16,0) -> 0 | BI24: =IF($C24=1,M$16,0) -> 0 | BJ24: =IF($C24=1,N$16,0) -> 0 | BK24: =IF($C24=1,O$16,0) -> 0 | ... CA24: =IF($C24=1,AE$16,0) -> 0
B25: =SUM(AF25:ET25) -> 0 | C25: =IF(D25<=$D$4,1,0) -> 0 | D25: 10 | BJ25: =IF($C25=1,H$16,0) -> 0 | BK25: =IF($C25=1,I$16,0) -> 0 | BL25: =IF($C25=1,J$16,0) -> 0 | BM25: =IF($C25=1,K$16,0) -> 0 | BN25: =IF($C25=1,L$16,0) -> 0 | BO25: =IF($C25=1,M$16,0) -> 0 | BP25: =IF($C25=1,N$16,0) -> 0 | BQ25: =IF($C25=1,O$16,0) -> 0 | ... CG25: =IF($C25=1,AE$16,0) -> 0
B26: =SUM(AF26:ET26) -> 0 | C26: =IF(D26<=$D$4,1,0) -> 0 | D26: 11 | BP26: =IF($C26=1,H$16,0) -> 0 | BQ26: =IF($C26=1,I$16,0) -> 0 | BR26: =IF($C26=1,J$16,0) -> 0 | BS26: =IF($C26=1,K$16,0) -> 0 | BT26: =IF($C26=1,L$16,0) -> 0 | BU26: =IF($C26=1,M$16,0) -> 0 | BV26: =IF($C26=1,N$16,0) -> 0 | BW26: =IF($C26=1,O$16,0) -> 0 | ... CM26: =IF($C26=1,AE$16,0) -> 0
B27: =SUM(H27:ET27) -> 0 | C27: =IF(D27<=$D$4,1,0) -> 0 | D27: 12 | BV27: =IF($C27=1,N$16,0) -> 0 | BW27: =IF($C27=1,O$16,0) -> 0 | BX27: =IF($C27=1,P$16,0) -> 0 | BY27: =IF($C27=1,Q$16,0) -> 0 | BZ27: =IF($C27=1,R$16,0) -> 0 | CA27: =IF($C27=1,S$16,0) -> 0 | CB27: =IF($C27=1,T$16,0) -> 0 | CC27: =IF($C27=1,U$16,0) -> 0 | ... CS27: =IF($C27=1,AK$16,0) -> 0
B28: =SUM(H28:ET28) -> 0 | C28: =IF(D28<=$D$4,1,0) -> 0 | D28: 13 | CB28: =IF($C28=1,T$16,0) -> 0 | CC28: =IF($C28=1,U$16,0) -> 0 | CD28: =IF($C28=1,V$16,0) -> 0 | CE28: =IF($C28=1,W$16,0) -> 0 | CF28: =IF($C28=1,X$16,0) -> 0 | CG28: =IF($C28=1,Y$16,0) -> 0 | CH28: =IF($C28=1,Z$16,0) -> 0 | CI28: =IF($C28=1,AA$16,0) -> 0 | ... CY28: =IF($C28=1,AQ$16,0) -> 0
B29: =SUM(H29:ET29) -> 0 | C29: =IF(D29<=$D$4,1,0) -> 0 | D29: 14 | CH29: =IF($C29=1,Z$16,0) -> 0 | CI29: =IF($C29=1,AA$16,0) -> 0 | CJ29: =IF($C29=1,AB$16,0) -> 0 | CK29: =IF($C29=1,AC$16,0) -> 0 | CL29: =IF($C29=1,AD$16,0) -> 0 | CM29: =IF($C29=1,AE$16,0) -> 0 | CN29: =IF($C29=1,AF$16,0) -> 0 | CO29: =IF($C29=1,AG$16,0) -> 0 | ... DE29: =IF($C29=1,AW$16,0) -> 0
B30: =SUM(H30:ET30) -> 0 | C30: =IF(D30<=$D$4,1,0) -> 0 | D30: 15 | CN30: =IF($C30=1,AF$16,0) -> 0 | CO30: =IF($C30=1,AG$16,0) -> 0 | CP30: =IF($C30=1,AH$16,0) -> 0 | CQ30: =IF($C30=1,AI$16,0) -> 0 | CR30: =IF($C30=1,AJ$16,0) -> 0 | CS30: =IF($C30=1,AK$16,0) -> 0 | CT30: =IF($C30=1,AL$16,0) -> 0 | CU30: =IF($C30=1,AM$16,0) -> 0 | ... DK30: =IF($C30=1,BC$16,0) -> 0
B31: =SUM(H31:ET31) -> 0 | C31: =IF(D31<=$D$4,1,0) -> 0 | D31: 16 | CT31: =IF($C31=1,AL$16,0) -> 0 | CU31: =IF($C31=1,AM$16,0) -> 0 | CV31: =IF($C31=1,AN$16,0) -> 0 | CW31: =IF($C31=1,AO$16,0) -> 0 | CX31: =IF($C31=1,AP$16,0) -> 0 | CY31: =IF($C31=1,AQ$16,0) -> 0 | CZ31: =IF($C31=1,AR$16,0) -> 0 | DA31: =IF($C31=1,AS$16,0) -> 0 | ... DQ31: =IF($C31=1,BI$16,0) -> 0
B32: =SUM(H32:ET32) -> 0 | C32: =IF(D32<=$D$4,1,0) -> 0 | D32: 17 | CZ32: =IF($C32=1,AR$16,0) -> 0 | DA32: =IF($C32=1,AS$16,0) -> 0 | DB32: =IF($C32=1,AT$16,0) -> 0 | DC32: =IF($C32=1,AU$16,0) -> 0 | DD32: =IF($C32=1,AV$16,0) -> 0 | DE32: =IF($C32=1,AW$16,0) -> 0 | DF32: =IF($C32=1,AX$16,0) -> 0 | DG32: =IF($C32=1,AY$16,0) -> 0 | ... DW32: =IF($C32=1,BO$16,0) -> 0
B33: =SUM(H33:ET33) -> 0 | C33: =IF(D33<=$D$4,1,0) -> 0 | D33: 18 | DF33: =IF($C33=1,AX$16,0) -> 0 | DG33: =IF($C33=1,AY$16,0) -> 0 | DH33: =IF($C33=1,AZ$16,0) -> 0 | DI33: =IF($C33=1,BA$16,0) -> 0 | DJ33: =IF($C33=1,BB$16,0) -> 0 | DK33: =IF($C33=1,BC$16,0) -> 0 | DL33: =IF($C33=1,BD$16,0) -> 0 | DM33: =IF($C33=1,BE$16,0) -> 0 | ... EC33: =IF($C33=1,BU$16,0) -> 0
B34: =SUM(H34:ET34) -> 0 | C34: =IF(D34<=$D$4,1,0) -> 0 | D34: 19 | DL34: =IF($C34=1,BD$16,0) -> 0 | DM34: =IF($C34=1,BE$16,0) -> 0 | DN34: =IF($C34=1,BF$16,0) -> 0 | DO34: =IF($C34=1,BG$16,0) -> 0 | DP34: =IF($C34=1,BH$16,0) -> 0 | DQ34: =IF($C34=1,BI$16,0) -> 0 | DR34: =IF($C34=1,BJ$16,0) -> 0 | DS34: =IF($C34=1,BK$16,0) -> 0 | ... EI34: =IF($C34=1,CA$16,0) -> 0
B35: =SUM(H35:ET35) -> 0 | C35: =IF(D35<=$D$4,1,0) -> 0 | D35: 20 | DR35: =IF($C35=1,BJ$16,0) -> 0 | DS35: =IF($C35=1,BK$16,0) -> 0 | DT35: =IF($C35=1,BL$16,0) -> 0 | DU35: =IF($C35=1,BM$16,0) -> 0 | DV35: =IF($C35=1,BN$16,0) -> 0 | DW35: =IF($C35=1,BO$16,0) -> 0 | DX35: =IF($C35=1,BP$16,0) -> 0 | DY35: =IF($C35=1,BQ$16,0) -> 0 | ... EO35: =IF($C35=1,CG$16,0) -> 0
D37: Total | F37: =SUM(F16:F35) -> 2.3333256e+08 | G37: =SUM(G16:G35) -> 2.3333256e+08 | H37: =SUM(H16:H35) -> 2.916657e+08 | I37: =SUM(I16:I35) -> 2.916657e+08 | J37: =SUM(J16:J35) -> 2.916657e+08 | K37: =SUM(K16:K35) -> 2.916657e+08 | L37: =SUM(L16:L35) -> 3.4999884e+08 | M37: =SUM(M16:M35) -> 3.4999884e+08 | ... ET37: =SUM(ET16:ET35) -> 0

Sheet шахматка
A1: Block No | B1: Enterance Code | C1: Door Number | D1: Flat Number | E1: Flat Code | F1: Group of Blocks | G1: Block Type | H1: Этаж | I1: Quantity of Rooms | J1: Net area (m2) | K1: Net area (m2) Rounded UP | L1: Вид | M1: Ликвидность | N1: Type | O1: Status | P1: Цена
A2: 01 | B2: A | C2: C101 | D2: 01A-203 | E2: 09-HAR-01-01-203 | F2: 01-Group | G2: Bk | H2: 1 | I2: 1 | J2: 252.62 | K2: 252.62 | L2: Двор | M2: Высокая ликвидность | N2: Commercial | O2: Not-listed | P2: =K2*'база коммерция'!$B$2*(1+IFERROR(VLOOKUP(шахматка!H2,коэф!$A$1:$B$10,2,FALSE),0)+IFERROR(VLOOKUP(K2,коэф!$G$1:$H$6,2,TRUE),0)+IFERROR(VLOOKUP(шахматка!M2,коэф!$J$1:$K$3,2,FALSE),0)+IFERROR(VLOOKUP(шахматка!L2,коэф!$D$1:$E$2,2,FALSE),0))*'база коммерция'!$B$3*'база офис'!$B$6 -> 3.4927586e+08
A3: 01 | B3: A | C3: C102 | D3: 01A-204 | E3: 09-HAR-01-01-204 | F3: 01-Group | G3: Bk | H3: 2 | I3: 1 | J3: 338.32 | K3: 338.32 | L3: Улица | M3: Средняя ликвидность | N3: Office | O3: Not-listed | P3: =K3*'база офис'!$B$2*(1+IFERROR(VLOOKUP(шахматка!H3,коэф!$A$1:$B$10,2,FALSE),0)+IFERROR(VLOOKUP(K3,коэф!$G$1:$H$9,2,TRUE),0)+IFERROR(VLOOKUP(шахматка!M3,коэф!$J$1:$K$3,2,FALSE),0)+IFERROR(VLOOKUP(шахматка!L3,коэф!$D$1:$E$2,2,FALSE),0))*'база офис'!$B$3*'база офис'!$B$6 -> 4.7002244e+08 | Q3: =P3/K3 -> 1389283.6 | R3: =LEN(L4) -> 4
A4: 01 | B4: A | C4: 201 | D4: 01A-205 | E4: 09-HAR-01-01-205 | F4: 01-Group | G4: Bk | H4: 2 | I4: 1 | J4: 203.2 | K4: 203.2 | L4: Двор | M4: Средняя ликвидность | N4: Office | O4: Not-listed | P4: =K4*'база офис'!$B$2*(1+IFERROR(VLOOKUP(шахматка!H4,коэф!$A$1:$B$10,2,FALSE),0)+IFERROR(VLOOKUP(K4,коэф!$G$1:$H$9,2,TRUE),0)+IFERROR(VLOOKUP(шахматка!M4,коэф!$J$1:$K$3,2,FALSE),0)+IFERROR(VLOOKUP(шахматка!L4,коэф!$D$1:$E$2,2,FALSE),0))*'база офис'!$B$3*'база офис'!$B$6 -> 2.8480069e+08 | Q4: =P4/K4 -> 1401578.2 | R4: =LEN(коэф!D2) -> 5
A5: 01 | B5: A | C5: 202 | D5: 01A-206 | E5: 09-HAR-01-01-206 | F5: 01-Group | G5: Bk | H5: 3 | I5: 1 | J5: 355.75 | K5: 355.75 | L5: Улица | M5: Средняя ликвидность | N5: Office | O5: Not-listed | P5: =K5*'база офис'!$B$2*(1+IFERROR(VLOOKUP(шахматка!H5,коэф!$A$1:$B$10,2,FALSE),0)+IFERROR(VLOOKUP(K5,коэф!$G$1:$H$9,2,TRUE),0)+IFERROR(VLOOKUP(шахматка!M5,коэф!$J$1:$K$3,2,FALSE),0)+IFERROR(VLOOKUP(шахматка!L5,коэф!$D$1:$E$2,2,FALSE),0))*'база офис'!$B$3*'база офис'!$B$6 -> 4.9423765e+08 | Q5: =P5/K5 -> 1389283.6
A6: 01 | B6: A | C6: 301 | D6: 01A-301 | E6: 09-HAR-01-01-301 | F6: 01-Group | G6: Bk | H6: 3 | I6: 1 | J6: 357.79 | K6: 357.79 | L6: Двор | M6: Средняя ликвидность | N6: Office | O6: Not-listed | P6: =K6*'база офис'!$B$2*(1+IFERROR(VLOOKUP(шахматка!H6,коэф!$A$1:$B$10,2,FALSE),0)+IFERROR(VLOOKUP(K6,коэф!$G$1:$H$9,2,TRUE),0)+IFERROR(VLOOKUP(шахматка!M6,коэф!$J$1:$K$3,2,FALSE),0)+IFERROR(VLOOKUP(шахматка!L6,коэф!$D$1:$E$2,2,FALSE),0))*'база офис'!$B$3*'база офис'!$B$6 -> 4.838752e+08 | Q6: =P6/K6 -> 1352400
A7: 01 | B7: A | C7: 302 | D7: 01A-302 | E7: 09-HAR-01-01-302 | F7: 01-Group | G7: Bk | H7: 4 | I7: 1 | J7: 358.5 | K7: 358.5 | L7: Улица | M7: Средняя ликвидность | N7: Office | O7: Not-listed | P7: =K7*'база офис'!$B$2*(1+IFERROR(VLOOKUP(шахматка!H7,коэф!$A$1:$B$10,2,FALSE),0)+IFERROR(VLOOKUP(K7,коэф!$G$1:$H$9,2,TRUE),0)+IFERROR(VLOOKUP(шахматка!M7,коэф!$J$1:$K$3,2,FALSE),0)+IFERROR(VLOOKUP(шахматка!L7,коэф!$D$1:$E$2,2,FALSE),0))*'база офис'!$B$3*'база офис'!$B$6 -> 4.9365059e+08 | Q7: =P7/K7 -> 1376989.1
A8: 01 | B8: A | C8: 401 | D8: 01A-303 | E8: 09-HAR-01-01-303 | F8: 01-Group | G8: Bk | H8: 4 | I8: 1 | J8: 361.18 | K8: 361.18 | L8: Двор | M8: Средняя ликвидность | N8: Office | O8: Not-listed | P8: =K8*'база офис'!$B$2*(1+IFERROR(VLOOKUP(шахматка!H8,коэф!$A$1:$B$10,2,FALSE),0)+IFERROR(VLOOKUP(K8,коэф!$G$1:$H$9,2,TRUE),0)+IFERROR(VLOOKUP(шахматка!M8,коэф!$J$1:$K$3,2,FALSE),0)+IFERROR(VLOOKUP(шахматка!L8,коэф!$D$1:$E$2,2,FALSE),0))*'база офис'!$B$3*'база офис'!$B$6 -> 4.8401929e+08 | Q8: =P8/K8 -> 1340105.5
A9: 01 | B9: A | C9: 402 | D9: 01A-304 | E9: 09-HAR-01-01-304 | F9: 01-Group | G9: Bk | H9: 5 | I9: 1 | J9: 358.5 | K9: 358.5 | L9: Улица | M9: Средняя ликвидность | N9: Office | O9: Not-listed | P9: =K9*'база офис'!$B$2*(1+IFERROR(VLOOKUP(шахматка!H9,коэф!$A$1:$B$10,2,FALSE),0)+IFERROR(VLOOKUP(K9,коэф!$G$1:$H$9,2,TRUE),0)+IFERROR(VLOOKUP(шахматка!M9,коэф!$J$1:$K$3,2,FALSE),0)+IFERROR(VLOOKUP(шахматка!L9,коэф!$D$1:$E$2,2,FALSE),0))*'база офис'!$B$3*'база офис'!$B$6 -> 4.9365059e+08 | Q9: =P9/K9 -> 1376989.1
A10: 01 | B10: A | C10: 501 | D10: 01A-305 | E10: 09-HAR-01-01-305 | F10: 01-Group | G10: Bk | H10: 5 | I10: 1 | J10: 361.18 | K10: 361.18 | L10: Двор | M10: Средняя ликвидность | N10: Office | O10: Not-listed | P10: =K10*'база офис'!$B$2*(1+IFERROR(VLOOKUP(шахматка!H10,коэф!$A$1:$B$10,2,FALSE),0)+IFERROR(VLOOKUP(K10,коэф!$G$1:$H$9,2,TRUE),0)+IFERROR(VLOOKUP(шахматка!M10,коэф!$J$1:$K$3,2,FALSE),0)+IFERROR(VLOOKUP(шахматка!L10,коэф!$D$1:$E$2,2,FALSE),0))*'база офис'!$B$3*'база офис'!$B$6 -> 4.8401929e+08 | Q10: =P10/K10 -> 1340105.5
A11: 01 | B11: A | C11: 502 | D11: 01A-306 | E11: 09-HAR-01-01-306 | F11: 01-Group | G11: Bk | H11: 6 | I11: 1 | J11: 212.49 | K11: 212.49 | L11: Улица | M11: Средняя ликвидность | N11: Office | O11: Not-listed | P11: =K11*'база офис'!$B$2*(1+IFERROR(VLOOKUP(шахматка!H11,коэф!$A$1:$B$10,2,FALSE),0)+IFERROR(VLOOKUP(K11,коэф!$G$1:$H$9,2,TRUE),0)+IFERROR(VLOOKUP(шахматка!M11,коэф!$J$1:$K$3,2,FALSE),0)+IFERROR(VLOOKUP(шахматка!L11,коэф!$D$1:$E$2,2,FALSE),0))*'база офис'!$B$3*'база офис'!$B$6 -> 3.0174005e+08 | Q11: =P11/K11 -> 1420020
A12: 01 | B12: A | C12: 601 | D12: 01A-401 | E12: 09-HAR-01-01-401 | F12: 01-Group | G12: Bk | H12: 6 | I12: 1 | J12: 140.08 | K12: 140.08 | L12: Двор | M12: Средняя ликвидность | N12: Office | O12: Not-listed | P12: =K12*'база офис'!$B$2*(1+IFERROR(VLOOKUP(шахматка!H12,коэф!$A$1:$B$10,2,FALSE),0)+IFERROR(VLOOKUP(K12,коэф!$G$1:$H$9,2,TRUE),0)+IFERROR(VLOOKUP(шахматка!M12,коэф!$J$1:$K$3,2,FALSE),0)+IFERROR(VLOOKUP(шахматка!L12,коэф!$D$1:$E$2,2,FALSE),0))*'база офис'!$B$3*'база офис'!$B$6 -> 2.0236084e+08 | Q12: =P12/K12 -> 1444609.1
A13: 01 | B13: A | C13: 602 | D13: 01A-402 | E13: 09-HAR-01-01-402 | F13: 01-Group | G13: Bk | H13: 6 | I13: 1 | J13: 142.13 | K13: 142.13 | L13: Улица | M13: Средняя ликвидность | N13: Office | O13: Not-listed | P13: =K13*'база офис'!$B$2*(1+IFERROR(VLOOKUP(шахматка!H13,коэф!$A$1:$B$10,2,FALSE),0)+IFERROR(VLOOKUP(K13,коэф!$G$1:$H$9,2,TRUE),0)+IFERROR(VLOOKUP(шахматка!M13,коэф!$J$1:$K$3,2,FALSE),0)+IFERROR(VLOOKUP(шахматка!L13,коэф!$D$1:$E$2,2,FALSE),0))*'база офис'!$B$3*'база офис'!$B$6 -> 2.1056456e+08 | Q13: =P13/K13 -> 1481492.7
A14: 01 | B14: A | C14: 603 | D14: 01A-403 | E14: 09-HAR-01-01-403 | F14: 01-Group | G14: Bk | H14: 6 | I14: 1 | J14: 219.09 | K14: 219.09 | L14: Двор | M14: Средняя ликвидность | N14: Office | O14: Not-listed | P14: =K14*'база офис'!$B$2*(1+IFERROR(VLOOKUP(шахматка!H14,коэф!$A$1:$B$10,2,FALSE),0)+IFERROR(VLOOKUP(K14,коэф!$G$1:$H$9,2,TRUE),0)+IFERROR(VLOOKUP(шахматка!M14,коэф!$J$1:$K$3,2,FALSE),0)+IFERROR(VLOOKUP(шахматка!L14,коэф!$D$1:$E$2,2,FALSE),0))*'база офис'!$B$3*'база офис'!$B$6 -> 3.0303135e+08 | Q14: =P14/K14 -> 1383136.4
A15: 01 | B15: A | C15: 604 | D15: 01A-404 | E15: 09-HAR-01-01-404 | F15: 01-Group | G15: Bk | H15: 7 | I15: 1 | J15: 212.49 | K15: 212.49 | L15: Улица | M15: Средняя ликвидность | N15: Office | O15: Not-listed | P15: =K15*'база офис'!$B$2*(1+IFERROR(VLOOKUP(шахматка!H15,коэф!$A$1:$B$10,2,FALSE),0)+IFERROR(VLOOKUP(K15,коэф!$G$1:$H$9,2,TRUE),0)+IFERROR(VLOOKUP(шахматка!M15,коэф!$J$1:$K$3,2,FALSE),0)+IFERROR(VLOOKUP(шахматка!L15,коэф!$D$1:$E$2,2,FALSE),0))*'база офис'!$B$3*'база офис'!$B$6 -> 3.0043382e+08 | Q15: =P15/K15 -> 1413872.7
A16: 01 | B16: A | C16: 701 | D16: 01A-405 | E16: 09-HAR-01-01-405 | F16: 01-Group | G16: Bk | H16: 7 | I16: 1 | J16: 140.08 | K16: 140.08 | L16: Двор | M16: Средняя ликвидность | N16: Office | O16: Not-listed | P16: =K16*'база офис'!$B$2*(1+IFERROR(VLOOKUP(шахматка!H16,коэф!$A$1:$B$10,2,FALSE),0)+IFERROR(VLOOKUP(K16,коэф!$G$1:$H$9,2,TRUE),0)+IFERROR(VLOOKUP(шахматка!M16,коэф!$J$1:$K$3,2,FALSE),0)+IFERROR(VLOOKUP(шахматка!L16,коэф!$D$1:$E$2,2,FALSE),0))*'база офис'!$B$3*'база офис'!$B$6 -> 2.0149973e+08 | Q16: =P16/K16 -> 1438461.8
... A23: 01 | B23: A | C23: 804 | D23: 01A-506 | E23: 09-HAR-01-01-506 | F23: 01-Group | G23: Bk | H23: 9 | I23: 1 | J23: 704.02 | K23: 704.02 | L23: Улица | M23: Средняя ликвидность | N23: Office | O23: Not-listed | P23: =K23*'база офис'!$B$2*(1+IFERROR(VLOOKUP(шахматка!H23,коэф!$A$1:$B$10,2,FALSE),0)+IFERROR(VLOOKUP(K23,коэф!$G$1:$H$9,2,TRUE),0)+IFERROR(VLOOKUP(шахматка!M23,коэф!$J$1:$K$3,2,FALSE),0)+IFERROR(VLOOKUP(шахматка!L23,коэф!$D$1:$E$2,2,FALSE),0))*'база офис'!$B$3*'база офис'!$B$6 -> 7.2707089e+08 | Q23: =P23/K23 -> 1032741.8
A24: 01 | B24: A | C24: 901 | D24: 01A-601 | E24: 09-HAR-01-01-601 | F24: 01-Group | G24: Bk | H24: 10 | I24: 1 | J24: =558.89+133.38 -> 692.27 | K24: 692.27 | L24: Двор | M24: Средняя ликвидность | N24: Office | O24: Not-listed | P24: =K24*'база офис'!$B$2*(1+IFERROR(VLOOKUP(шахматка!H24,коэф!$A$1:$B$10,2,FALSE),0)+IFERROR(VLOOKUP(K24,коэф!$G$1:$H$9,2,TRUE),0)+IFERROR(VLOOKUP(шахматка!M24,коэф!$J$1:$K$3,2,FALSE),0)+IFERROR(VLOOKUP(шахматка!L24,коэф!$D$1:$E$2,2,FALSE),0))*'база офис'!$B$3*'база офис'!$B$6 -> 7.2344732e+08 | Q24: =P24/K24 -> 1045036.4
A25: 01 | B25: A | C25: 1001 | D25: 01A-602 | E25: 09-HAR-01-01-602 | F25: 01-Group | G25: Bk | H25: 1 | I25: 1 | J25: 0 | K25: 0 | L25: Улица | M25: Средняя ликвидность | N25: Office | O25: Not-listed | P25: =K25*'база офис'!$B$2*(1+IFERROR(VLOOKUP(шахматка!H25,коэф!$A$1:$B$10,2,FALSE),0)+IFERROR(VLOOKUP(K25,коэф!$G$1:$H$9,2,TRUE),0)+IFERROR(VLOOKUP(шахматка!M25,коэф!$J$1:$K$3,2,FALSE),0)+IFERROR(VLOOKUP(шахматка!L25,коэф!$D$1:$E$2,2,FALSE),0))*'база офис'!$B$3*'база офис'!$B$6 -> 0
A26: 01 | B26: A | C26: P101 | D26: 01A-603 | E26: 09-HAR-01-01-603 | F26: 01-Group | G26: Bk | H26: 1 | I26: 1 | J26: 0 | K26: 0 | L26: Двор | M26: Средняя ликвидность | N26: Parking | O26: Not-listed | P26: =K26*[3]база!$B$1*(1+IFERROR(VLOOKUP(шахматка!H26,[3]коэф!$A$1:$B$9,2,FALSE),0)+IFERROR(VLOOKUP(шахматка!I26,коэф!$G:$H,2,FALSE),0)+IFERROR(VLOOKUP(шахматка!M26,[3]коэф!$J$1:$K$3,2,FALSE),0)+IFERROR(VLOOKUP(шахматка!L26,[3]коэф!$D$1:$E$3,2,FALSE),0))*[3]база!$B$2*[3]база!$B$5 -> 0
A27: 01 | B27: A | C27: P102 | D27: 01A-604 | E27: 09-HAR-01-01-604 | F27: 01-Group | G27: Bk | H27: 1 | I27: 1 | J27: 0 | K27: 0 | L27: Горы | M27: Средняя ликвидность | N27: Parking | O27: Not-listed | P27: =K27*[3]база!$B$1*(1+IFERROR(VLOOKUP(шахматка!H27,[3]коэф!$A$1:$B$9,2,FALSE),0)+IFERROR(VLOOKUP(шахматка!I27,коэф!$G:$H,2,FALSE),0)+IFERROR(VLOOKUP(шахматка!M27,[3]коэф!$J$1:$K$3,2,FALSE),0)+IFERROR(VLOOKUP(шахматка!L27,[3]коэф!$D$1:$E$3,2,FALSE),0))*[3]база!$B$2*[3]база!$B$5 -> 0
A28: 01 | B28: A | C28: P103 | D28: 01A-605 | E28: 09-HAR-01-01-605 | F28: 01-Group | G28: Bk | H28: 1 | I28: 1 | J28: 0 | K28: 0 | L28: Улица | M28: Средняя ликвидность | N28: Parking | O28: Not-listed | P28: =K28*[3]база!$B$1*(1+IFERROR(VLOOKUP(шахматка!H28,[3]коэф!$A$1:$B$9,2,FALSE),0)+IFERROR(VLOOKUP(шахматка!I28,коэф!$G:$H,2,FALSE),0)+IFERROR(VLOOKUP(шахматка!M28,[3]коэф!$J$1:$K$3,2,FALSE),0)+IFERROR(VLOOKUP(шахматка!L28,[3]коэф!$D$1:$E$3,2,FALSE),0))*[3]база!$B$2*[3]база!$B$5 -> 0
A29: 01 | B29: A | C29: P104 | D29: 01A-606 | E29: 09-HAR-01-01-606 | F29: 01-Group | G29: Bk | H29: 1 | I29: 1 | J29: 0 | K29: 0 | L29: Двор | M29: Средняя ликвидность | N29: Parking | O29: Not-listed | P29: =K29*[3]база!$B$1*(1+IFERROR(VLOOKUP(шахматка!H29,[3]коэф!$A$1:$B$9,2,FALSE),0)+IFERROR(VLOOKUP(шахматка!I29,коэф!$G:$H,2,FALSE),0)+IFERROR(VLOOKUP(шахматка!M29,[3]коэф!$J$1:$K$3,2,FALSE),0)+IFERROR(VLOOKUP(шахматка!L29,[3]коэф!$D$1:$E$3,2,FALSE),0))*[3]база!$B$2*[3]база!$B$5 -> 0
A30: 01 | B30: A | C30: P105 | D30: 01A-701 | E30: 09-HAR-01-01-701 | F30: 01-Group | G30: Bk | H30: 1 | I30: 1 | J30: 0 | K30: 0 | L30: Горы | M30: Средняя ликвидность | N30: Parking | O30: Not-listed | P30: =K30*[3]база!$B$1*(1+IFERROR(VLOOKUP(шахматка!H30,[3]коэф!$A$1:$B$9,2,FALSE),0)+IFERROR(VLOOKUP(шахматка!I30,коэф!$G:$H,2,FALSE),0)+IFERROR(VLOOKUP(шахматка!M30,[3]коэф!$J$1:$K$3,2,FALSE),0)+IFERROR(VLOOKUP(шахматка!L30,[3]коэф!$D$1:$E$3,2,FALSE),0))*[3]база!$B$2*[3]база!$B$5 -> 0
A31: 01 | B31: A | C31: P106 | D31: 01A-702 | E31: 09-HAR-01-01-702 | F31: 01-Group | G31: Bk | H31: 1 | I31: 1 | J31: 0 | K31: 0 | L31: Улица | M31: Средняя ликвидность | N31: Parking | O31: Not-listed | P31: =K31*[3]база!$B$1*(1+IFERROR(VLOOKUP(шахматка!H31,[3]коэф!$A$1:$B$9,2,FALSE),0)+IFERROR(VLOOKUP(шахматка!I31,коэф!$G:$H,2,FALSE),0)+IFERROR(VLOOKUP(шахматка!M31,[3]коэф!$J$1:$K$3,2,FALSE),0)+IFERROR(VLOOKUP(шахматка!L31,[3]коэф!$D$1:$E$3,2,FALSE),0))*[3]база!$B$2*[3]база!$B$5 -> 0
A32: 01 | B32: A | C32: P107 | D32: 01A-703 | E32: 09-HAR-01-01-703 | F32: 01-Group | G32: Bk | H32: 1 | I32: 1 | J32: 0 | K32: 0 | L32: Двор | M32: Средняя ликвидность | N32: Parking | O32: Not-listed | P32: =K32*[3]база!$B$1*(1+IFERROR(VLOOKUP(шахматка!H32,[3]коэф!$A$1:$B$9,2,FALSE),0)+IFERROR(VLOOKUP(шахматка!I32,коэф!$G:$H,2,FALSE),0)+IFERROR(VLOOKUP(шахматка!M32,[3]коэф!$J$1:$K$3,2,FALSE),0)+IFERROR(VLOOKUP(шахматка!L32,[3]коэф!$D$1:$E$3,2,FALSE),0))*[3]база!$B$2*[3]база!$B$5 -> 0
A33: 01 | B33: A | C33: P108 | D33: 01A-704 | E33: 09-HAR-01-01-704 | F33: 01-Group | G33: Bk | H33: 1 | I33: 1 | J33: 0 | K33: 0 | L33: Горы | M33: Средняя ликвидность | N33: Parking | O33: Not-listed | P33: =K33*[3]база!$B$1*(1+IFERROR(VLOOKUP(шахматка!H33,[3]коэф!$A$1:$B$9,2,FALSE),0)+IFERROR(VLOOKUP(шахматка!I33,коэф!$G:$H,2,FALSE),0)+IFERROR(VLOOKUP(шахматка!M33,[3]коэф!$J$1:$K$3,2,FALSE),0)+IFERROR(VLOOKUP(шахматка!L33,[3]коэф!$D$1:$E$3,2,FALSE),0))*[3]база!$B$2*[3]база!$B$5 -> 0
A34: 01 | B34: A | C34: P109 | D34: 01A-705 | E34: 09-HAR-01-01-705 | F34: 01-Group | G34: Bk | H34: 1 | I34: 1 | J34: 0 | K34: 0 | L34: Улица | M34: Средняя ликвидность | N34: Parking | O34: Not-listed | P34: =K34*[3]база!$B$1*(1+IFERROR(VLOOKUP(шахматка!H34,[3]коэф!$A$1:$B$9,2,FALSE),0)+IFERROR(VLOOKUP(шахматка!I34,коэф!$G:$H,2,FALSE),0)+IFERROR(VLOOKUP(шахматка!M34,[3]коэф!$J$1:$K$3,2,FALSE),0)+IFERROR(VLOOKUP(шахматка!L34,[3]коэф!$D$1:$E$3,2,FALSE),0))*[3]база!$B$2*[3]база!$B$5 -> 0
A35: 01 | B35: A | C35: P110 | D35: 01A-706 | E35: 09-HAR-01-01-706 | F35: 01-Group | G35: Bk | H35: 1 | I35: 1 | J35: 0 | K35: 0 | L35: Двор | M35: Средняя ликвидность | N35: Parking | O35: Not-listed | P35: =K35*[3]база!$B$1*(1+IFERROR(VLOOKUP(шахматка!H35,[3]коэф!$A$1:$B$9,2,FALSE),0)+IFERROR(VLOOKUP(шахматка!I35,коэф!$G:$H,2,FALSE),0)+IFERROR(VLOOKUP(шахматка!M35,[3]коэф!$J$1:$K$3,2,FALSE),0)+IFERROR(VLOOKUP(шахматка!L35,[3]коэф!$D$1:$E$3,2,FALSE),0))*[3]база!$B$2*[3]база!$B$5 -> 0
A36: 01 | B36: A | C36: P111 | D36: 01A-801 | E36: 09-HAR-01-01-801 | F36: 01-Group | G36: Bk | H36: 1 | I36: 1 | J36: 0 | K36: 0 | L36: Горы | M36: Средняя ликвидность | N36: Parking | O36: Not-listed | P36: =K36*[3]база!$B$1*(1+IFERROR(VLOOKUP(шахматка!H36,[3]коэф!$A$1:$B$9,2,FALSE),0)+IFERROR(VLOOKUP(шахматка!I36,коэф!$G:$H,2,FALSE),0)+IFERROR(VLOOKUP(шахматка!M36,[3]коэф!$J$1:$K$3,2,FALSE),0)+IFERROR(VLOOKUP(шахматка!L36,[3]коэф!$D$1:$E$3,2,FALSE),0))*[3]база!$B$2*[3]база!$B$5 -> 0
A37: 01 | B37: A | C37: P112 | D37: 01A-802 | E37: 09-HAR-01-01-802 | F37: 01-Group | G37: Bk | H37: 1 | I37: 1 | J37: 0 | K37: 0 | L37: Улица | M37: Средняя ликвидность | N37: Parking | O37: Not-listed | P37: =K37*[3]база!$B$1*(1+IFERROR(VLOOKUP(шахматка!H37,[3]коэф!$A$1:$B$9,2,FALSE),0)+IFERROR(VLOOKUP(шахматка!I37,коэф!$G:$H,2,FALSE),0)+IFERROR(VLOOKUP(шахматка!M37,[3]коэф!$J$1:$K$3,2,FALSE),0)+IFERROR(VLOOKUP(шахматка!L37,[3]коэф!$D$1:$E$3,2,FALSE),0))*[3]база!$B$2*[3]база!$B$5 -> 0
... A51: 02 | B51: A | C51: P214 | D51: 02A-104 | E51: 09-HAR-01-02-104 | F51: 01-Group | G51: F | H51: 1 | I51: 1 | J51: 0 | K51: 0 | L51: Горы | M51: Средняя ликвидность | N51: Parking | O51: Not-listed | P51: =K51*[3]база!$B$1*(1+IFERROR(VLOOKUP(шахматка!H51,[3]коэф!$A$1:$B$9,2,FALSE),0)+IFERROR(VLOOKUP(шахматка!I51,коэф!$G:$H,2,FALSE),0)+IFERROR(VLOOKUP(шахматка!M51,[3]коэф!$J$1:$K$3,2,FALSE),0)+IFERROR(VLOOKUP(шахматка!L51,[3]коэф!$D$1:$E$3,2,FALSE),0))*[3]база!$B$2*[3]база!$B$5 -> 0
J52: =SUM(J2:J51) -> 6484.7 | K52: =SUM(K2:K51) -> 6484.7
P53: =SUBTOTAL(9,P2:P52) -> 8.4885059e+09
A54: =AVERAGEIF(N:N,'база офис'!B1,Q:Q) -> 1360782.6 | B54: Средняя цена реализации офисы
A55: =AVERAGEIF(N:N,'база коммерция'!B1,Q:Q) -> #DIV/0! | B55: Средняя цена реализации коммерция
A57: =SUM(P4:P25) -> 7.6692076e+09 | B57: Офисы
A58: =SUM(P2:P3) -> 8.192983e+08 | B58: Коммерция
A60: Офисы
A61: =SUM(P3:P25) -> 8.13923e+09
A62: =SUM(K3:K25) -> 6232.08
A63: =A61/A62 -> 1306021.4
A64: Коммерция

Sheet коэф
A1: 1 | B1: 0.05 | D1: Двор | E1: 0 | G1: 0 | H1: 0.2 | J1: Неликвид | K1: -0.05
A2: 2 | B2: 0.04 | D2: Улица | E2: 0.03 | G2: 50 | H2: 0.1 | J2: Высокая ликвидность | K2: 0.06
A3: 3 | B3: 0.04 | G3: 100 | H3: 0.15 | J3: Средняя ликвидность | K3: 0
A4: 4 | B4: 0.03 | G4: 200 | H4: 0.1 | J4: Низкая ликвидность
A5: 5 | B5: 0.03 | G5: 300 | H5: 0.06
A6: 6 | B6: 0.025 | G6: 400 | H6: 0.05
A7: 7 | B7: 0.02 | G7: 500 | H7: 0
A8: 8 | B8: -0.03 | G8: 600 | H8: -0.1
A9: 9 | B9: -0.04 | G9: 700 | H9: -0.15
A10: 10 | B10: -0.05
E14: ликвидность
E15: ПВ
E16: экспозиция | F16: частота распроданности

Sheet база офис
B1: Office | D1: старт | E1: 1
A2: Бавзовая цена за кв м | B2: 1120000 | D2: котлован | E2: 1.01
A3: Коэф стадии | B3: 1.05 | D3: каркас | E3: 1.03
A4: Всего офисов | B4: =COUNTA(шахматка!N4:N25) -> 22 | D4: фасад | E4: 1.05
A5: Продано | B5: 10 | D5: сдача | E5: 1.08
A6: Коэф спроса | B6: =1+(B5/B4)*0.1 -> 1.0454545

Sheet база коммерция
B1: Commercial | D1: старт | E1: 1
A2: Бавзовая цена за кв м | B2: 1150000 | D2: котлован | E2: 1.01
A3: Коэф стадии | B3: 1 | D3: каркас | E3: 1.03
A4: Всего коммерция | B4: 1 | D4: фасад | E4: 1.05
A5: Продано | B5: 0 | D5: сдача | E5: 1.08
A6: Коэф спроса | B6: =1+(B5/B4)*0.1 -> 1

Sheet Лист3
B2: 📄 Лист Шахматка
B4: A | C4: B | D4: C | E4: D | F4: E | G4: F | H4: G | I4: H
B5: ID | C5: Этаж | D5: № | E5: Тип | F5: Площадь | G5: Вид | H5: Ликвидность | I5: Цена
H8: 31164000000
H9: 13076057000
H10: =H8+H9 -> 44240057000
H11: =H10/55961 -> 790551.58

Sheet DCF year
B6: Дисконтированные денежные потоки | C6: Total | D6: =DCF!D3 -> 2026 | E6: =D6+1 -> 2027 | F6: =E6+1 -> 2028 | G6: =F6+1 -> 2029 | H6: =G6+1 -> 2030 | I6: =H6+1 -> 2031 | J6: =I6+1 -> 2032 | K6: =J6+1 -> 2033 | L6: =K6+1 -> 2034 | ... AC6: =AB6+1 -> 2051
B7: Поступления по операционной деятельности | C7: =SUM(D7:KO7) -> 10713300000 | D7: =SUM(D8:D8) -> 1949820600 | E7: =SUM(E8:E8) -> 4146047100 | F7: =SUM(F8:F8) -> 4.6174323e+09 | G7: =SUM(G8:G8) -> 0 | H7: =SUM(H8:H8) -> 0 | I7: =SUM(I8:I8) -> 0 | J7: =SUM(J8:J8) -> 0 | K7: =SUM(K8:K8) -> 0 | ... AC7: =SUM(AC8:AC8) -> 0
B8: Релизация помещений | C8: =SUM(D8:KO8) -> 10713300000 | D8: =SUMIF(DCF!$D$3:$KQ$3,'DCF year'!D$6,DCF!D8:KQ8) -> 1949820600 | E8: =SUMIF(DCF!E3:KR3,'DCF year'!E$6,DCF!E8:KR8) -> 4146047100 | F8: =SUMIF(DCF!F3:KS3,'DCF year'!F$6,DCF!F8:KS8) -> 4.6174323e+09 | G8: =SUMIF(DCF!G3:KT3,'DCF year'!G$6,DCF!G8:KT8) -> 0 | H8: =SUMIF(DCF!H3:KU3,'DCF year'!H$6,DCF!H8:KU8) -> 0 | I8: =SUMIF(DCF!I3:KV3,'DCF year'!I$6,DCF!I8:KV8) -> 0 | J8: =SUMIF(DCF!J3:KW3,'DCF year'!J$6,DCF!J8:KW8) -> 0 | K8: =SUMIF(DCF!K3:KX3,'DCF year'!K$6,DCF!K8:KX8) -> 0 | L8: =SUMIF(DCF!L3:KY3,'DCF year'!L$6,DCF!L8:KY8) -> 0 | ... AC8: =SUMIF(DCF!AC3:LP3,'DCF year'!AC$6,DCF!AC8:LP8) -> 0
B9: Выбытие по операционной деятельности | C9: =SUM(D9:KO9) -> 5.8333141e+09 | D9: =SUM(D10:D10) -> 1.5749948e+09 | E9: =SUM(E10:E10) -> 3.9549869e+09 | F9: =SUM(F10:F10) -> 3.0333233e+08 | G9: =SUM(G10:G10) -> 0 | H9: =SUM(H10:H10) -> 0 | I9: =SUM(I10:I10) -> 0 | J9: =SUM(J10:J10) -> 0 | K9: =SUM(K10:K10) -> 0 | ... AC9: =SUM(AC10:AC10) -> 0
B10: Расходы проекта | C10: =SUM(D10:KO10) -> 5.8333141e+09 | D10: =SUMIF(DCF!D$3:KQ$3,'DCF year'!D$6,DCF!D10:KQ10) -> 1.5749948e+09 | E10: =SUMIF(DCF!E$3:KR$3,'DCF year'!E$6,DCF!E10:KR10) -> 3.9549869e+09 | F10: =SUMIF(DCF!F$3:KS$3,'DCF year'!F$6,DCF!F10:KS10) -> 3.0333233e+08 | G10: =SUMIF(DCF!G$3:KT$3,'DCF year'!G$6,DCF!G10:KT10) -> 0 | H10: =SUMIF(DCF!H$3:KU$3,'DCF year'!H$6,DCF!H10:KU10) -> 0 | I10: =SUMIF(DCF!I$3:KV$3,'DCF year'!I$6,DCF!I10:KV10) -> 0 | J10: =SUMIF(DCF!J$3:KW$3,'DCF year'!J$6,DCF!J10:KW10) -> 0 | K10: =SUMIF(DCF!K$3:KX$3,'DCF year'!K$6,DCF!K10:KX10) -> 0 | ... AC10: =SUMIF(DCF!AC$3:LP$3,'DCF year'!AC$6,DCF!AC10:LP10) -> 0
B11: Операционная прибыль EBITDA | C11: =SUM(D11:KO11) -> 4.8799859e+09 | D11: =D7-D9 -> 3.748258e+08 | E11: =E7-E9 -> 1.9106017e+08 | F11: =F7-F9 -> 4.3141e+09 | G11: =G7-G9 -> 0 | H11: =H7-H9 -> 0 | I11: =I7-I9 -> 0 | J11: =J7-J9 -> 0 | K11: =K7-K9 -> 0 | ... AC11: =AC7-AC9 -> 0
B12: НДС к уплате | C12: =SUM(D12:KO12) -> 6.8771146e+08 | D12: =SUMIF(DCF!D$3:KQ$3,'DCF year'!D$6,DCF!D12:KQ12) -> 34385573 | E12: =SUMIF(DCF!E$3:KR$3,'DCF year'!E$6,DCF!E12:KR12) -> 1.3754229e+08 | F12: =SUMIF(DCF!F$3:KS$3,'DCF year'!F$6,DCF!F12:KS12) -> 5.1578359e+08 | G12: =SUMIF(DCF!G$3:KT$3,'DCF year'!G$6,DCF!G12:KT12) -> 0 | H12: =SUMIF(DCF!H$3:KU$3,'DCF year'!H$6,DCF!H12:KU12) -> 0 | I12: =SUMIF(DCF!I$3:KV$3,'DCF year'!I$6,DCF!I12:KV12) -> 0 | J12: =SUMIF(DCF!J$3:KW$3,'DCF year'!J$6,DCF!J12:KW12) -> 0 | K12: =SUMIF(DCF!K$3:KX$3,'DCF year'!K$6,DCF!K12:KX12) -> 0 | ... AC12: =SUMIF(DCF!AC$3:LP$3,'DCF year'!AC$6,DCF!AC12:LP12) -> 0
B13: КПН | C13: =SUM(D13:KO13) -> 6.415806e+08 | D13: =SUMIF(DCF!D$3:KQ$3,'DCF year'!D$6,DCF!D13:KQ13) -> 0 | E13: =SUMIF(DCF!E$3:KR$3,'DCF year'!E$6,DCF!E13:KR13) -> 1.2831612e+08 | F13: =SUMIF(DCF!F$3:KS$3,'DCF year'!F$6,DCF!F13:KS13) -> 5.1326448e+08 | G13: =SUMIF(DCF!G$3:KT$3,'DCF year'!G$6,DCF!G13:KT13) -> 0 | H13: =SUMIF(DCF!H$3:KU$3,'DCF year'!H$6,DCF!H13:KU13) -> 0 | I13: =SUMIF(DCF!I$3:KV$3,'DCF year'!I$6,DCF!I13:KV13) -> 0 | J13: =SUMIF(DCF!J$3:KW$3,'DCF year'!J$6,DCF!J13:KW13) -> 0 | K13: =SUMIF(DCF!K$3:KX$3,'DCF year'!K$6,DCF!K13:KX13) -> 0 | ... AC13: =SUMIF(DCF!AC$3:LP$3,'DCF year'!AC$6,DCF!AC13:LP13) -> 0
B14: Вознаграждение по займам | C14: =SUM(D14:KO14) -> 112218750 | D14: =SUMIF(DCF!D$3:KQ$3,'DCF year'!D$6,DCF!D14:KQ14) -> 61031250 | E14: =SUMIF(DCF!E$3:KR$3,'DCF year'!E$6,DCF!E14:KR14) -> 51187500 | F14: =SUMIF(DCF!F$3:KS$3,'DCF year'!F$6,DCF!F14:KS14) -> 0 | G14: =SUMIF(DCF!G$3:KT$3,'DCF year'!G$6,DCF!G14:KT14) -> 0 | H14: =SUMIF(DCF!H$3:KU$3,'DCF year'!H$6,DCF!H14:KU14) -> 0 | I14: =SUMIF(DCF!I$3:KV$3,'DCF year'!I$6,DCF!I14:KV14) -> 0 | J14: =SUMIF(DCF!J$3:KW$3,'DCF year'!J$6,DCF!J14:KW14) -> 0 | K14: =SUMIF(DCF!K$3:KX$3,'DCF year'!K$6,DCF!K14:KX14) -> 0 | ... AC14: =SUMIF(DCF!AC$3:LP$3,'DCF year'!AC$6,DCF!AC14:LP14) -> 0
B15: Свободный денежный поток по опер. деятельности | C15: =SUM(D15:KO15) -> 3.4384751e+09 | D15: =D11-SUM(D12:D14) -> 2.7940898e+08 | E15: =E11-SUM(E12:E14) -> -1.2598574e+08 | F15: =F11-SUM(F12:F14) -> 3.2850519e+09 | G15: =G11-SUM(G12:G14) -> 0 | H15: =H11-SUM(H12:H14) -> 0 | I15: =I11-SUM(I12:I14) -> 0 | J15: =J11-SUM(J12:J14) -> 0 | K15: =K11-SUM(K12:K14) -> 0 | ... AC15: =AC11-SUM(AC12:AC14) -> 0
B17: Приобретение ЗУ | C17: =SUM(D17:KO17) -> 675000000 | D17: =SUMIF(DCF!D$3:KQ$3,'DCF year'!D$6,DCF!D16:KQ16) -> 0 | E17: =SUMIF(DCF!E$3:KR$3,'DCF year'!E$6,DCF!E16:KR16) -> 0 | F17: =SUMIF(DCF!F$3:KS$3,'DCF year'!F$6,DCF!F16:KS16) -> 675000000 | G17: =SUMIF(DCF!G$3:KT$3,'DCF year'!G$6,DCF!G16:KT16) -> 0 | H17: =SUMIF(DCF!H$3:KU$3,'DCF year'!H$6,DCF!H16:KU16) -> 0 | I17: =SUMIF(DCF!I$3:KV$3,'DCF year'!I$6,DCF!I16:KV16) -> 0 | J17: =SUMIF(DCF!J$3:KW$3,'DCF year'!J$6,DCF!J16:KW16) -> 0 | K17: =SUMIF(DCF!K$3:KX$3,'DCF year'!K$6,DCF!K16:KX16) -> 0 | ... AC17: =SUMIF(DCF!AC$3:LP$3,'DCF year'!AC$6,DCF!AC16:LP16) -> 0
B18: Соц нагрузка | C18: =SUM(D18:KO18) -> 0 | D18: =SUMIF(DCF!D$3:KQ$3,'DCF year'!D$6,DCF!D17:KQ17) -> 0 | E18: =SUMIF(DCF!E$3:KR$3,'DCF year'!E$6,DCF!E17:KR17) -> 0 | F18: =SUMIF(DCF!F$3:KS$3,'DCF year'!F$6,DCF!F17:KS17) -> 0 | G18: =SUMIF(DCF!G$3:KT$3,'DCF year'!G$6,DCF!G17:KT17) -> 0 | H18: =SUMIF(DCF!H$3:KU$3,'DCF year'!H$6,DCF!H17:KU17) -> 0 | I18: =SUMIF(DCF!I$3:KV$3,'DCF year'!I$6,DCF!I17:KV17) -> 0 | J18: =SUMIF(DCF!J$3:KW$3,'DCF year'!J$6,DCF!J17:KW17) -> 0 | K18: =SUMIF(DCF!K$3:KX$3,'DCF year'!K$6,DCF!K17:KX17) -> 0 | ... AC18: =SUMIF(DCF!AC$3:LP$3,'DCF year'!AC$6,DCF!AC17:LP17) -> 0
B19: Проектирование | C19: =SUM(D19:KO19) -> 197152741 | D19: =SUMIF(DCF!D$3:KQ$3,'DCF year'!D$6,DCF!D18:KQ18) -> 94633316 | E19: =SUMIF(DCF!E$3:KR$3,'DCF year'!E$6,DCF!E18:KR18) -> 1.0251943e+08 | F19: =SUMIF(DCF!F$3:KS$3,'DCF year'!F$6,DCF!F18:KS18) -> 0 | G19: =SUMIF(DCF!G$3:KT$3,'DCF year'!G$6,DCF!G18:KT18) -> 0 | H19: =SUMIF(DCF!H$3:KU$3,'DCF year'!H$6,DCF!H18:KU18) -> 0 | I19: =SUMIF(DCF!I$3:KV$3,'DCF year'!I$6,DCF!I18:KV18) -> 0 | J19: =SUMIF(DCF!J$3:KW$3,'DCF year'!J$6,DCF!J18:KW18) -> 0 | K19: =SUMIF(DCF!K$3:KX$3,'DCF year'!K$6,DCF!K18:KX18) -> 0 | ... AC19: =SUMIF(DCF!AC$3:LP$3,'DCF year'!AC$6,DCF!AC18:LP18) -> 0
B20: Свободный денежный поток от инвестиционной деятельности | C20: =SUM(D20:KO20) -> -872152741 | D20: =-SUM(D17:D19) -> -94633316 | E20: =-SUM(E17:E19) -> -1.0251943e+08 | F20: =-SUM(F17:F19) -> -675000000 | G20: =-SUM(G17:G19) -> 0 | H20: =-SUM(H17:H19) -> 0 | I20: =-SUM(I17:I19) -> 0 | J20: =-SUM(J17:J19) -> 0 | K20: =-SUM(K17:K19) -> 0 | ... AC20: =-SUM(AC17:AC19) -> 0
B22: FCFF | C22: =SUM(D22:KO22) -> 2.5663224e+09 | D22: =D15+D20 -> 1.8477566e+08 | E22: =E15+E20 -> -2.2850517e+08 | F22: =F15+F20 -> 2.6100519e+09 | G22: =G15+G20 -> 0 | H22: =H15+H20 -> 0 | I22: =I15+I20 -> 0 | J22: =J15+J20 -> 0 | K22: =K15+K20 -> 0 | ... AC22: =AC15+AC20 -> 0
B24: Поступление по фин.деят (ОД) | C24: =SUM(D24:KO24) -> 675000000 | D24: =SUMIF(DCF!D$3:KQ$3,'DCF year'!D$6,DCF!D22:KQ22) -> 675000000 | E24: =SUMIF(DCF!E$3:KR$3,'DCF year'!E$6,DCF!E22:KR22) -> 0 | F24: =SUMIF(DCF!F$3:KS$3,'DCF year'!F$6,DCF!F22:KS22) -> 0 | G24: =SUMIF(DCF!G$3:KT$3,'DCF year'!G$6,DCF!G22:KT22) -> 0 | H24: =SUMIF(DCF!H$3:KU$3,'DCF year'!H$6,DCF!H22:KU22) -> 0 | I24: =SUMIF(DCF!I$3:KV$3,'DCF year'!I$6,DCF!I22:KV22) -> 0 | J24: =SUMIF(DCF!J$3:KW$3,'DCF year'!J$6,DCF!J22:KW22) -> 0 | K24: =SUMIF(DCF!K$3:KX$3,'DCF year'!K$6,DCF!K22:KX22) -> 0 | ... AC24: =SUMIF(DCF!AC$3:LP$3,'DCF year'!AC$6,DCF!AC22:LP22) -> 0
B25: Equity | C25: =SUM(D25:KO25) -> 0 | D25: =SUMIF(DCF!D$3:KQ$3,'DCF year'!D$6,DCF!D23:KQ23) -> 0 | E25: =SUMIF(DCF!E$3:KR$3,'DCF year'!E$6,DCF!E23:KR23) -> 0 | F25: =SUMIF(DCF!F$3:KS$3,'DCF year'!F$6,DCF!F23:KS23) -> 0 | G25: =SUMIF(DCF!G$3:KT$3,'DCF year'!G$6,DCF!G23:KT23) -> 0 | H25: =SUMIF(DCF!H$3:KU$3,'DCF year'!H$6,DCF!H23:KU23) -> 0 | I25: =SUMIF(DCF!I$3:KV$3,'DCF year'!I$6,DCF!I23:KV23) -> 0 | J25: =SUMIF(DCF!J$3:KW$3,'DCF year'!J$6,DCF!J23:KW23) -> 0 | K25: =SUMIF(DCF!K$3:KX$3,'DCF year'!K$6,DCF!K23:KX23) -> 0 | ... AC25: =SUMIF(DCF!AC$3:LP$3,'DCF year'!AC$6,DCF!AC23:LP23) -> 0
B26: Партнеры/рассрочка | C26: =SUM(D26:KO26) -> 0 | D26: =SUMIF(DCF!D$3:KQ$3,'DCF year'!D$6,DCF!D24:KQ24) -> 0 | E26: =SUMIF(DCF!E$3:KR$3,'DCF year'!E$6,DCF!E24:KR24) -> 0 | F26: =SUMIF(DCF!F$3:KS$3,'DCF year'!F$6,DCF!F24:KS24) -> 0 | G26: =SUMIF(DCF!G$3:KT$3,'DCF year'!G$6,DCF!G24:KT24) -> 0 | H26: =SUMIF(DCF!H$3:KU$3,'DCF year'!H$6,DCF!H24:KU24) -> 0 | I26: =SUMIF(DCF!I$3:KV$3,'DCF year'!I$6,DCF!I24:KV24) -> 0 | J26: =SUMIF(DCF!J$3:KW$3,'DCF year'!J$6,DCF!J24:KW24) -> 0 | K26: =SUMIF(DCF!K$3:KX$3,'DCF year'!K$6,DCF!K24:KX24) -> 0 | ... AC26: =SUMIF(DCF!AC$3:LP$3,'DCF year'!AC$6,DCF!AC24:LP24) -> 0
B27: Оттоки по фин.деят (ОД) | C27: =SUM(D27:KO27) -> 675000000 | D27: =SUMIF(DCF!D$3:KQ$3,'DCF year'!D$6,DCF!D25:KQ25) -> 225000000 | E27: =SUMIF(DCF!E$3:KR$3,'DCF year'!E$6,DCF!E25:KR25) -> 450000000 | F27: =SUMIF(DCF!F$3:KS$3,'DCF year'!F$6,DCF!F25:KS25) -> 0 | G27: =SUMIF(DCF!G$3:KT$3,'DCF year'!G$6,DCF!G25:KT25) -> 0 | H27: =SUMIF(DCF!H$3:KU$3,'DCF year'!H$6,DCF!H25:KU25) -> 0 | I27: =SUMIF(DCF!I$3:KV$3,'DCF year'!I$6,DCF!I25:KV25) -> 0 | J27: =SUMIF(DCF!J$3:KW$3,'DCF year'!J$6,DCF!J25:KW25) -> 0 | K27: =SUMIF(DCF!K$3:KX$3,'DCF year'!K$6,DCF!K25:KX25) -> 0 | ... AC27: =SUMIF(DCF!AC$3:LP$3,'DCF year'!AC$6,DCF!AC25:LP25) -> 0
B28: Возврат Equity | C28: =SUM(D28:KO28) -> 0 | D28: =SUMIF(DCF!D$3:KQ$3,'DCF year'!D$6,DCF!D26:KQ26) -> 0 | E28: =SUMIF(DCF!E$3:KR$3,'DCF year'!E$6,DCF!E26:KR26) -> 0 | F28: =SUMIF(DCF!F$3:KS$3,'DCF year'!F$6,DCF!F26:KS26) -> 0 | G28: =SUMIF(DCF!G$3:KT$3,'DCF year'!G$6,DCF!G26:KT26) -> 0 | H28: =SUMIF(DCF!H$3:KU$3,'DCF year'!H$6,DCF!H26:KU26) -> 0 | I28: =SUMIF(DCF!I$3:KV$3,'DCF year'!I$6,DCF!I26:KV26) -> 0 | J28: =SUMIF(DCF!J$3:KW$3,'DCF year'!J$6,DCF!J26:KW26) -> 0 | K28: =SUMIF(DCF!K$3:KX$3,'DCF year'!K$6,DCF!K26:KX26) -> 0 | ... AC28: =SUMIF(DCF!AC$3:LP$3,'DCF year'!AC$6,DCF!AC26:LP26) -> 0
B29: Возврат партнеры/рассрочка | C29: =SUM(D29:KO29) -> 0 | D29: =SUMIF(DCF!D$3:KQ$3,'DCF year'!D$6,DCF!D27:KQ27) -> 0 | E29: =SUMIF(DCF!E$3:KR$3,'DCF year'!E$6,DCF!E27:KR27) -> 0 | F29: =SUMIF(DCF!F$3:KS$3,'DCF year'!F$6,DCF!F27:KS27) -> 0 | G29: =SUMIF(DCF!G$3:KT$3,'DCF year'!G$6,DCF!G27:KT27) -> 0 | H29: =SUMIF(DCF!H$3:KU$3,'DCF year'!H$6,DCF!H27:KU27) -> 0 | I29: =SUMIF(DCF!I$3:KV$3,'DCF year'!I$6,DCF!I27:KV27) -> 0 | J29: =SUMIF(DCF!J$3:KW$3,'DCF year'!J$6,DCF!J27:KW27) -> 0 | K29: =SUMIF(DCF!K$3:KX$3,'DCF year'!K$6,DCF!K27:KX27) -> 0 | ... AC29: =SUMIF(DCF!AC$3:LP$3,'DCF year'!AC$6,DCF!AC27:LP27) -> 0
B30: Выплата ДВД | C30: =SUM(D30:KO30) -> 0 | D30: =SUMIF(DCF!D$3:KQ$3,'DCF year'!D$6,DCF!D28:KQ28) -> 0 | E30: =SUMIF(DCF!E$3:KR$3,'DCF year'!E$6,DCF!E28:KR28) -> 0 | F30: =SUMIF(DCF!F$3:KS$3,'DCF year'!F$6,DCF!F28:KS28) -> 0 | G30: =SUMIF(DCF!G$3:KT$3,'DCF year'!G$6,DCF!G28:KT28) -> 0 | H30: =SUMIF(DCF!H$3:KU$3,'DCF year'!H$6,DCF!H28:KU28) -> 0 | I30: =SUMIF(DCF!I$3:KV$3,'DCF year'!I$6,DCF!I28:KV28) -> 0 | J30: =SUMIF(DCF!J$3:KW$3,'DCF year'!J$6,DCF!J28:KW28) -> 0 | K30: =SUMIF(DCF!K$3:KX$3,'DCF year'!K$6,DCF!K28:KX28) -> 0 | ... AC30: =SUMIF(DCF!AC$3:LP$3,'DCF year'!AC$6,DCF!AC28:LP28) -> 0
B31: Свободный денежный поток от ФИН деятельности | C31: =SUM(D31:KO31) -> 0 | D31: =D24+D25+D26-D27-D28-D30-D29 -> 450000000 | E31: =E24+E25+E26-E27-E28-E30-E29 -> -450000000 | F31: =F24+F25+F26-F27-F28-F30-F29 -> 0 | G31: =G24+G25+G26-G27-G28-G30-G29 -> 0 | H31: =H24+H25+H26-H27-H28-H30-H29 -> 0 | I31: =I24+I25+I26-I27-I28-I30-I29 -> 0 | J31: =J24+J25+J26-J27-J28-J30-J29 -> 0 | K31: =K24+K25+K26-K27-K28-K30-K29 -> 0 | ... AC31: =AC24+AC25+AC26-AC27-AC28-AC30-AC29 -> 0
B33: FCFE | C33: =SUM(D33:KO33) -> 2.5663224e+09 | D33: =D22+D31 -> 6.3477566e+08 | E33: =E22+E31 -> -6.7850517e+08 | F33: =F22+F31 -> 2.6100519e+09 | G33: =G22+G31 -> 0 | H33: =H22+H31 -> 0 | I33: =I22+I31 -> 0 | J33: =J22+J31 -> 0 | K33: =K22+K31 -> 0 | ... AC33: =AC22+AC31 -> 0
B36: Накопительный денежный поток | D36: =D33 -> 6.3477566e+08 | E36: =D36+E33 -> -43729505 | F36: =E36+F33 -> 2.5663224e+09 | G36: =F36+G33 -> 2.5663224e+09 | H36: =G36+H33 -> 2.5663224e+09 | I36: =H36+I33 -> 2.5663224e+09 | J36: =I36+J33 -> 2.5663224e+09 | K36: =J36+K33 -> 2.5663224e+09 | L36: =K36+L33 -> 2.5663224e+09 | ... AC36: =AB36+AC33 -> 2.5663224e+09
B37: Индекс окупаемости | C37: =SUM(D37:AN37) -> 1 | D37: =IF(D36<0,1,0) -> 0 | E37: =IF(E36<0,1,0) -> 1 | F37: =IF(F36<0,1,0) -> 0 | G37: =IF(G36<0,1,0) -> 0 | H37: =IF(H36<0,1,0) -> 0 | I37: =IF(I36<0,1,0) -> 0 | J37: =IF(J36<0,1,0) -> 0 | K37: =IF(K36<0,1,0) -> 0 | ... AC37: =IF(AC36<0,1,0) -> 0
B39: Дисконтированный поток | D39: =SUMIF(DCF!D$3:KQ$3,'DCF year'!D$6,DCF!D35:KQ35) -> 1.7821497e+08 | E39: =SUMIF(DCF!E$3:KR$3,'DCF year'!E$6,DCF!E35:KR35) -> -2.0197748e+08 | F39: =SUMIF(DCF!F$3:KS$3,'DCF year'!F$6,DCF!F35:KS35) -> 1.7770554e+09 | G39: =SUMIF(DCF!G$3:KT$3,'DCF year'!G$6,DCF!G35:KT35) -> 0 | H39: =SUMIF(DCF!H$3:KU$3,'DCF year'!H$6,DCF!H35:KU35) -> 0 | I39: =SUMIF(DCF!I$3:KV$3,'DCF year'!I$6,DCF!I35:KV35) -> 0 | J39: =SUMIF(DCF!J$3:KW$3,'DCF year'!J$6,DCF!J35:KW35) -> 0 | K39: =SUMIF(DCF!K$3:KX$3,'DCF year'!K$6,DCF!K35:KX35) -> 0 | ... AC39: =SUMIF(DCF!AC$3:LP$3,'DCF year'!AC$6,DCF!AC35:LP35) -> 0
B40: Накопительный денежный поток | D40: =D39 -> 1.7821497e+08 | E40: =E39 -> -2.0197748e+08 | F40: =F39 -> 1.7770554e+09 | G40: =G39 -> 0 | H40: =H39 -> 0 | I40: =I39 -> 0 | J40: =J39 -> 0 | K40: =K39 -> 0 | ... AC40: =AC39 -> 0
B41: Индекс окупаемости | C41: =DCF!C37 -> 1
B43: Equity discount rate | C43: 0.18
B44: IRR FCFF | C44: =DCF!C41*12 -> 181.70697
B45: NPV FCFF | C45: =DCF!C42 -> 1.8777444e+09
B47: ROE | C47: =DCF!C44 -> 0
B48: ROI | C48: =DCF!C45 -> 3.8019591
B49: DPP | C49: =DCF!C46 -> 1
B50: WACC месячный | C50: =DCF!C47*12 -> 0.21
B51: ROI | C51: =DCF!C48 -> 3.8019591

Sheet Dashboard (2)
B3: Итоговые показатели
B4: Net Profit | C4: ='PnL (2)'!B74 -> 1.358886e+10
B5: ROS, % | C5: ='PnL (2)'!B75 -> 0.15281573
B6: ROE (Отдача на капитал) | C6: ='DCF (2)'!C46 -> -6.3982158
B7: WACC (Годовой) | C7: ='DCF (2)'!C49*12 -> 0.21
B8: IRR (Минимальная ставка доходности) | C8: ='DCF (2)'!C43 -> #NUM!
B9: NPV | C9: ='DCF (2)'!C44 -> -3.1318888e+10
B10: PP | C10: ='DCF (2)'!C39 -> #N/A
B11: DPP | C11: ='DCF (2)'!C48 -> #N/A
B14: Основные вводные
B15: LAND | E15: SALES | H15: COSTS
B16: Площадь ЗУ, га | C16: 10.0131 | E16: Цена за м2 квартиры | F16: 635000 | H16: Себестоимость за м2 | I16: 334817
B17: Курс ЗУ | C17: 500 | E17: Цена за м2 офиса | F17: 700000 | H17: Накладные расходы | I17: 24412.178
B18: Стоимость за сотку, USD | C18: 20000 | E18: Цена за м2 кладовки | F18: 150000 | H18: Расходы на реализацию | I18: 0.0455
B19: Стоимость участка итого, KZT | C19: =C16*100*C18*C17 -> 10013100000 | E19: Цена за 1 м/м | F19: 6000000 | H19: Расходы офиса | I19: 0.024
H20: Гарантийный Резерв
B22: CONSTRUCTION | E22: CASH FLOW | H22: TAXES
B23: Этажность | C23: 9 | E23: Собственный капитал | H23: ПИРы | I23: ='PnL все'!B50 -> 197152741
B24: Застраиваемая площадь | E24: Кредит | F24: 0 | H24: НДС | I24: ='PnL все'!B70 -> 6.8771146e+08
B25: Продаваемая площадь | C25: ='PnL все'!B7 -> 6901 | E25: Срок займа, мес | F25: 36 | H25: КПН | I25: ='PnL все'!B73 -> 6.415806e+08
B26: Прод площ 1 очереди | C26: =C25 -> 6901 | E26: Дивиденды | F26: ='PnL все'!B74 -> 2.5663224e+09
E27: Дата займа | F27: 46157
B28: ЖЦП, мес | E28: Ставка, % | F28: 21
B29: Дата старта | C29: 46157 | E29: Льготный период, мес | F29: 0
B34: Собственный капитал | C34: 0
B35: Ставка займа (годовая) | C35: 0.21
B36: Стоимость акционерских денег | C36: 0.25

Sheet PnL (2)
A2: Показатель | B2: KZT | C2: USD
A3: Цена за сотку (Общая), USD | B3: =B48/B5/100/B4 -> 1335080
A4: Курс $ | B4: ='Dashboard все'!C17 -> 500
A5: Земельный участок га | B5: ='Dashboard все'!C16 -> 0.15
A6: Этажность | B6: 12
A7: Реализуемая площадь, м2 | B7: =SUM(B8:B11) -> 149772 | C7: =B7 -> 149772
A8: Квартиры (себес м2 * площадь) | B8: 132335 | C8: =B8 -> 132335
A9: Кладовые помещения | B9: 10789 | C9: =B9 -> 10789
A10: Коммерческие помещения | B10: 2043 | C10: =B10 -> 2043
A11: Паркинги | B11: =B16*15 -> 4605 | C11: =B11 -> 4605
A12: Реализуемое количество, шт | B12: =SUM(B13:B16) -> 4302 | C12: =B12 -> 4302
A13: Квартиры | B13: 2532 | C13: =B13 -> 2532
A14: Кладовые помещения | B14: 1445 | C14: =B14 -> 1445
A15: Коммерческие помещения | B15: 18 | C15: =B15 -> 18
A16: Паркинги | B16: 307 | C16: =B16 -> 307
A17: Средние цены реализации: | B17: =B34/B7 -> 593723.63 | C17: =C34/C7 -> 1187.4473
A18: Квартиры | B18: ='Dashboard (2)'!F16 -> 635000 | C18: =B18/$B$4 -> 1270
A19: Кладовые помещения | B19: ='Dashboard (2)'!F18 -> 150000 | C19: =B19/$B$4 -> 300
A20: Коммерческие помещения | B20: ='Dashboard (2)'!F17 -> 700000 | C20: =B20/$B$4 -> 1400
A21: Паркинги | B21: ='Dashboard (2)'!F19 -> 6000000 | C21: =B21/$B$4 -> 12000
A22: Cебестоимость СМР за м2: | B22: =(B41+B42+B43+B44)/(B8+B9+B10+B11) -> 334817 | C22: =B22/$B$4 -> 669.634
A23: Квартиры | B23: ='Dashboard (2)'!I16 -> 334817 | C23: =B23/$B$4 -> 669.634
A24: Кладовые помещения | B24: 0 | C24: =B24/$B$4 -> 0
A25: Коммерческие помещения | B25: 0 | C25: =B25/$B$4 -> 0
A26: Паркинги | C26: =B26/$B$4 -> 0
A27: Средняя себестоимость (СМР+ПСД+опер.+накл.) | B27: =SUM(B28:B33) -> 475719.02 | C27: =B27/$B$4 -> 951.43803
A28: Строительно-монтажные работы | B28: =B40/(B8+B9+B10+B11) -> 334817 | C28: =B28/$B$4 -> 669.634
A29: Земельный участок | B29: =B48/B7 -> 66855.621 | C29: =B29/$B$4 -> 133.71124
A30: Расходы заказчика | B30: =B50/B7 -> 5022.255 | C30: =B30/$B$4 -> 10.04451
A31: Накладные расходы | B31: =B52/B7 -> 69024.14 | C31: =B31/$B$4 -> 138.04828
A32: Социальная нагрузка | B32: 0 | C32: =B32/$B$4 -> 0
A33: % по кредиту | B33: 0 | C33: =B33/$B$4 -> 0
A34: Выручка итого в т.ч. | B34: =SUM(B35:B38) -> 88923175000 | C34: =B34/B4 -> 177846350
A35: Квартиры | B35: =(B8*B18) -> 84032725000 | C35: =B35/$B$4 -> 168065450
A36: Кладовые помещения | B36: =(B9*B19) -> 1618350000 | C36: =B36/$B$4 -> 3236700
A37: Коммерческие помещения | B37: =(B10*B20) -> 1430100000 | C37: =B37/$B$4 -> 2860200
A38: Паркинги | B38: =(B16*B21) -> 1842000000 | C38: =B38/$B$4 -> 3684000
A39: Расходы итого: | B39: =B40+B48+B50+B52+B62+B66+B68+B70 -> 7.19371e+10 | C39: =B39/$B$4 -> 1.438742e+08
A40: СМР в т.ч.: | B40: =SUM(B41:B47) -> 50146211724 | C40: =B40/$B$4 -> 1.0029242e+08
A41: Квартиры (себес м2 * площадь) | B41: =B7*B23 -> 50146211724
A42: Коммерческие помещения (себес м2 * площадь) | B42: =B25*B7 -> 0 | C42: =B42/$B$4 -> 0
A43: Кладовки (себес м2 * площадь)
A44: Паркинги (себес м2 * площадь)
A45: Снос строении
A46: Изменение целевого назначения
A47: Подключение к сетям
A48: ЗУ в т.ч.: | B48: =B49 -> 10013100000 | C48: =B48/$B$4 -> 20026200
A49: Земельный участок | B49: ='Dashboard (2)'!C19 -> 10013100000 | C49: =B49/$B$4 -> 20026200
A50: ПИР в т.ч.: | B50: =SUM(B51:B51) -> 7.5219318e+08 | C50: =B50/$B$4 -> 1504386.4
A51: ПИР, тг | B51: =B41*0.015 -> 7.5219318e+08 | C51: =C42*0.016 -> 0
A52: Накладные расходы вт.ч. | B52: =SUM(B53:B61) -> 1.0337884e+10 | C52: =B52/$B$4 -> 20675767
A53: Накладные расходы, тг | B53: ='Dashboard (2)'!I17*'PnL (2)'!B7 -> 3.6562608e+09 | C53: =B53/$B$4 -> 7312521.5
A54: Административные расходы проекта, 2% | B54: =B40*1% -> 5.0146212e+08 | C54: =B54/$B$4 -> 1002924.2
A55: Подготовительные работы 1% | B55: 0 | C55: =B55/$B$4 -> 0
A56: Управление проектом | B56: 0 | C56: =B56/$B$4 -> 0
A57: Представительские расходы, тг 1% | B57: 0 | C57: =B57/$B$4 -> 0
A58: Содержание HCG (11+6 этаж), 2,4% | B58: =B34*2.4% -> 2134156200 | C58: =B58/$B$4 -> 4268312.4
A59: Гарантийный Резерв, 0,8% | B59: 0 | C59: =B59/$B$4 -> 0
A60: Ипотека 5% на 30% квартир | B60: =B35*5%*30%*0 -> 0 | C60: =B60/$B$4 -> 0
A61: Расходы на реализацию, тг 4,5% | B61: =B34*4.55% -> 4.0460045e+09 | C61: =B61/$B$4 -> 8092008.9
A62: Соц. Инфраструктура в т.ч.: | B62: =SUM(B63:B65) -> 0 | C62: =B62/$B$4 -> 0
A63: Школа | B63: 0 | C63: =B63/$B$4 -> 0
A64: Дет. Сад | B64: 0 | C64: =B64/$B$4 -> 0
A65: Парк | B65: 0 | C65: =B65/$B$4 -> 0
A66: % по кредиту | B66: =SUM(B67:B67) -> 0 | C66: =B66/$B$4 -> 0
A67: % по кредиту | B67: 0 | C67: =B67/$B$4 -> 0
A68: НДС не разрешенный в зачет | B68: =SUM(B69:B69) -> 0 | C68: =B68/$B$4 -> 0
A69: НДС не разрешенный в зачет
A70: НДС | B70: =SUM(B71:B71) -> 6.8771146e+08 | C70: =B70/$B$4 -> 1375422.9
A71: НДС | B71: =IF('НДС расчет'!C8<0,0,'НДС расчет'!C8) -> 6.8771146e+08 | C71: =B71/$B$4 -> 1375422.9
A72: Прибыль до налогообложения | B72: =B34-B39 -> 1.6986075e+10 | C72: =B72/$B$4 -> 33972150
A73: КПН, 20% | B73: =IF((B72)>0,(B72)*20%,0) -> 3.397215e+09 | C73: =B73/$B$4 -> 6794430 | D73: 7.5388608e+09
A74: Чистая прибыль | B74: =B72-B73 -> 1.358886e+10 | C74: =C72-C73 -> 27177720 | D74: =B74-D73 -> 6.0499993e+09
A75: Рентабельность | B75: =B74/B34 -> 0.15281573 | C75: =C74/C34 -> 0.15281573

Sheet Сравнение2
B2: ASTORIA | C2: PTO | D2: FIN | E2: Difference
B3: Sales | C3: 1.2045988e+10 | D3: 12045988047 | E3: =D3-C3 -> 0.40000153
B4: Land | C4: 817500000 | D4: ='PnL все'!B48 -> 675000000 | E4: =D4-C4 -> -142500000
B5: Direct | C5: 5.0819748e+09 | D5: ='PnL все'!B40 -> 4595567890 | E5: =D5-C5 -> -4.8640688e+08
B6: Indirect | C6: 5.6466386e+08 | D6: ='PnL все'!B53+'PnL все'!B51 -> 644368883 | E6: =D6-C6 -> 79705020
B7: Sales Comission | C7: 3.6137964e+08 | D7: ='PnL все'!B61 -> 487455150 | E7: =D7-C7 -> 1.2607551e+08
B8: HO | D8: ='PnL все'!B58 -> 257119200 | E8: =D8-C8 -> 257119200
B9: Administrative costs | D9: ='PnL все'!B54 -> 45955679 | E9: =D9-C9 -> 45955679
B10: Finance | D10: ='PnL все'!B66 -> 112218750 | E10: =D10-C10 -> 112218750
B11: General expenses | C11: 1.0238277e+09 | E11: =D11-C11 -> -1.0238277e+09
B12: Tax | C12: 8.3527516e+08 | D12: ='PnL все'!B70+'PnL все'!B73 -> 1.3292921e+09 | E12: =D12-C12 -> 4.9401689e+08
B13: Net profit | C13: =C3-C4-C5-C6-C7-C8-C9--C10-C12-C11 -> 3.3613669e+09 | D13: =D3-D4-D5-D6-D7-D8-D9-D10-D12-D11 -> 3.8990104e+09 | E13: =D13-C13 -> 5.3764357e+08

Sheet DCF (2)
D3: =YEAR(D6) -> 2026 | E3: =YEAR(E6) -> 2026 | F3: =YEAR(F6) -> 2026 | G3: =YEAR(G6) -> 2026 | H3: =YEAR(H6) -> 2026 | I3: =YEAR(I6) -> 2026 | J3: =YEAR(J6) -> 2027 | K3: =YEAR(K6) -> 2027 | ... KQ3: =YEAR(KQ6) -> 2051
D4: 1 | E4: =D4+1 -> 2 | F4: =E4+1 -> 3 | G4: =F4+1 -> 4 | H4: =G4+1 -> 5 | I4: =H4+1 -> 6 | J4: =I4+1 -> 7 | K4: =J4+1 -> 8 | L4: =K4+1 -> 9 | ... KQ4: =KP4+1 -> 300
D5: =MONTH(D6) -> 7 | E5: =MONTH(E6) -> 8 | F5: =MONTH(F6) -> 9 | G5: =MONTH(G6) -> 10 | H5: =MONTH(H6) -> 11 | I5: =MONTH(I6) -> 12 | J5: =MONTH(J6) -> 1 | K5: =MONTH(K6) -> 2 | ... KQ5: =MONTH(KQ6) -> 6
B6: Дисконтированные денежные потоки | C6: Total | D6: ='Dashboard все'!C29 -> 46204 | E6: =EDATE(D6,1) -> 46235 | F6: =EDATE(E6,1) -> 46266 | G6: =EDATE(F6,1) -> 46296 | H6: =EDATE(G6,1) -> 46327 | I6: =EDATE(H6,1) -> 46357 | J6: =EDATE(I6,1) -> 46388 | K6: =EDATE(J6,1) -> 46419 | L6: =EDATE(K6,1) -> 46447 | ... KQ6: =EDATE(KP6,1) -> 55305
B7: Поступления по операционной деятельности | C7: =SUM(D7:KQ7) -> 10713300000 | D7: =SUM(D8:D8) -> 321399000 | E7: =SUM(E8:E8) -> 321399000 | F7: =SUM(F8:F8) -> 321399000 | G7: =SUM(G8:G8) -> 321399000 | H7: =SUM(H8:H8) -> 332112300 | I7: =SUM(I8:I8) -> 332112300 | J7: =SUM(J8:J8) -> 332112300 | K7: =SUM(K8:K8) -> 332112300 | ... KQ7: =SUM(KQ8:KQ8) -> 0
B8: Релизация помещений | C8: =SUM(D8:KQ8) -> 10713300000 | D8: =Sales!E15 -> 321399000 | E8: =Sales!F15 -> 321399000 | F8: =Sales!G15 -> 321399000 | G8: =Sales!H15 -> 321399000 | H8: =Sales!I15 -> 332112300 | I8: =Sales!J15 -> 332112300 | J8: =Sales!K15 -> 332112300 | K8: =Sales!L15 -> 332112300 | ... GB8: =Sales!GC15 -> 0 | GC8: =Sales!FU36 -> 0 | GD8: =Sales!FV36 -> 0 | GE8: =Sales!FW36 -> 0 | GF8: =Sales!FX36 -> 0 | GG8: =Sales!FY36 -> 0 | GH8: =Sales!FZ36 -> 0 | GI8: =Sales!GA36 -> 0 | GJ8: =Sales!GB36 -> 0 | ... KQ8: =Sales!KI36 -> 0
B9: Выбытие по операционной деятельности | C9: =SUM(D9:KQ9) -> 6.0484095e+10 | D9: =SUM(D10:D10) -> 0 | E9: =SUM(E10:E10) -> 1.8145229e+08 | F9: =SUM(F10:F10) -> 1.8145229e+08 | G9: =SUM(G10:G10) -> 1.8145229e+08 | H9: =SUM(H10:H10) -> 1.8145229e+08 | I9: =SUM(I10:I10) -> 2.4193638e+08 | J9: =SUM(J10:J10) -> 9.3750348e+08 | K9: =SUM(K10:K10) -> 9.3750348e+08 | ... KQ9: =SUM(KQ10:KQ10) -> 0
B10: Расходы проекта | C10: =SUM(D10:KQ10) -> 6.0484095e+10 | D10: ='Costs (2)'!E19 -> 0 | E10: ='Costs (2)'!F19 -> 1.8145229e+08 | F10: ='Costs (2)'!G19 -> 1.8145229e+08 | G10: ='Costs (2)'!H19 -> 1.8145229e+08 | H10: ='Costs (2)'!I19 -> 1.8145229e+08 | I10: ='Costs (2)'!J19 -> 2.4193638e+08 | J10: ='Costs (2)'!K19 -> 9.3750348e+08 | K10: ='Costs (2)'!L19 -> 9.3750348e+08 | ... DZ10: ='Costs (2)'!EA19 -> 0 | EA10: ='Costs (2)'!EC19 -> 0 | EB10: ='Costs (2)'!ED19 -> 0 | EC10: ='Costs (2)'!EE19 -> 0 | ED10: ='Costs (2)'!EF19 -> 0 | EE10: ='Costs (2)'!EG19 -> 0 | EF10: ='Costs (2)'!EH19 -> 0 | EG10: ='Costs (2)'!EI19 -> 0 | EH10: ='Costs (2)'!EJ19 -> 0 | ... EU10: ='Costs (2)'!EW19 -> 0 | EV10: =Costs!EQ37 -> 0 | EW10: =Costs!ER37 -> 0 | EX10: =Costs!ES37 -> 0 | EY10: =Costs!ET37 -> 0 | EZ10: =Costs!EU37 -> 0 | FA10: =Costs!EV37 -> 0 | FB10: =Costs!EW37 -> 0 | FC10: =Costs!EX37 -> 0 | ... KQ10: =Costs!KL37 -> 0
B11: Операционная прибыль EBITDA | C11: =SUM(D11:KQ11) -> -4.9770795e+10 | D11: =D7-D9 -> 321399000 | E11: =E7-E9 -> 1.3994671e+08 | F11: =F7-F9 -> 1.3994671e+08 | G11: =G7-G9 -> 1.3994671e+08 | H11: =H7-H9 -> 1.5066001e+08 | I11: =I7-I9 -> 90175919 | J11: =J7-J9 -> -6.0539118e+08 | K11: =K7-K9 -> -6.0539118e+08 | ... KQ11: =KQ7-KQ9 -> 0
B12: НДС к уплате | C12: =SUM(D12:KQ12) -> 6.8771146e+08 | D12: {=TRANSPOSE(SUMIFS('Графики (2)'!$I$7:$I$307,'Графики (2)'!$D$7:$D$307,'DCF (2)'!D$6))} -> 0 | E12: {=TRANSPOSE(SUMIFS('Графики (2)'!$I$7:$I$307,'Графики (2)'!$D$7:$D$307,'DCF (2)'!E$6))} -> 0 | F12: {=TRANSPOSE(SUMIFS('Графики (2)'!$I$7:$I$307,'Графики (2)'!$D$7:$D$307,'DCF (2)'!F$6))} -> 17192786 | G12: {=TRANSPOSE(SUMIFS('Графики (2)'!$I$7:$I$307,'Графики (2)'!$D$7:$D$307,'DCF (2)'!G$6))} -> 0 | H12: {=TRANSPOSE(SUMIFS('Графики (2)'!$I$7:$I$307,'Графики (2)'!$D$7:$D$307,'DCF (2)'!H$6))} -> 0 | I12: {=TRANSPOSE(SUMIFS('Графики (2)'!$I$7:$I$307,'Графики (2)'!$D$7:$D$307,'DCF (2)'!I$6))} -> 17192786 | J12: {=TRANSPOSE(SUMIFS('Графики (2)'!$I$7:$I$307,'Графики (2)'!$D$7:$D$307,'DCF (2)'!J$6))} -> 0 | K12: {=TRANSPOSE(SUMIFS('Графики (2)'!$I$7:$I$307,'Графики (2)'!$D$7:$D$307,'DCF (2)'!K$6))} -> 0 | ... EB12: {=TRANSPOSE(SUMIFS('Графики (2)'!$I$7:$I$307,'Графики (2)'!$D$7:$D$307,'DCF (2)'!EB$6))} -> 0 | EC12: {=TRANSPOSE(SUMIFS(Графики!$I$7:$I$306,Графики!$D$7:$D$306,'DCF (2)'!EC6))} -> 0 | ED12: {=TRANSPOSE(SUMIFS(Графики!$I$7:$I$306,Графики!$D$7:$D$306,'DCF (2)'!ED6))} -> 0 | EE12: {=TRANSPOSE(SUMIFS(Графики!$I$7:$I$306,Графики!$D$7:$D$306,'DCF (2)'!EE6))} -> 0 | EF12: {=TRANSPOSE(SUMIFS(Графики!$I$7:$I$306,Графики!$D$7:$D$306,'DCF (2)'!EF6))} -> 0 | EG12: {=TRANSPOSE(SUMIFS(Графики!$I$7:$I$306,Графики!$D$7:$D$306,'DCF (2)'!EG6))} -> 0 | EH12: {=TRANSPOSE(SUMIFS(Графики!$I$7:$I$306,Графики!$D$7:$D$306,'DCF (2)'!EH6))} -> 0 | EI12: {=TRANSPOSE(SUMIFS(Графики!$I$7:$I$306,Графики!$D$7:$D$306,'DCF (2)'!EI6))} -> 0 | EJ12: {=TRANSPOSE(SUMIFS(Графики!$I$7:$I$306,Графики!$D$7:$D$306,'DCF (2)'!EJ6))} -> 0 | ... KQ12: {=TRANSPOSE(SUMIFS(Графики!$I$7:$I$306,Графики!$D$7:$D$306,'DCF (2)'!KQ6))} -> 0
B13: КПН | C13: =SUM(D13:KQ13) -> 3.397215e+09 | D13: {=TRANSPOSE(SUMIFS('Графики (2)'!$H$7:$H$306,'Графики (2)'!$D$7:$D$306,'DCF (2)'!D$6))} -> 0 | E13: {=TRANSPOSE(SUMIFS('Графики (2)'!$H$7:$H$306,'Графики (2)'!$D$7:$D$306,'DCF (2)'!E$6))} -> 0 | F13: {=TRANSPOSE(SUMIFS('Графики (2)'!$H$7:$H$306,'Графики (2)'!$D$7:$D$306,'DCF (2)'!F$6))} -> 0 | G13: {=TRANSPOSE(SUMIFS('Графики (2)'!$H$7:$H$306,'Графики (2)'!$D$7:$D$306,'DCF (2)'!G$6))} -> 0 | H13: {=TRANSPOSE(SUMIFS('Графики (2)'!$H$7:$H$306,'Графики (2)'!$D$7:$D$306,'DCF (2)'!H$6))} -> 0 | I13: {=TRANSPOSE(SUMIFS('Графики (2)'!$H$7:$H$306,'Графики (2)'!$D$7:$D$306,'DCF (2)'!I$6))} -> 0 | J13: {=TRANSPOSE(SUMIFS('Графики (2)'!$H$7:$H$306,'Графики (2)'!$D$7:$D$306,'DCF (2)'!J$6))} -> 0 | K13: {=TRANSPOSE(SUMIFS('Графики (2)'!$H$7:$H$306,'Графики (2)'!$D$7:$D$306,'DCF (2)'!K$6))} -> 0 | ... DV13: {=TRANSPOSE(SUMIFS('Графики (2)'!$H$7:$H$306,'Графики (2)'!$D$7:$D$306,'DCF (2)'!DV$6))} -> 0 | DW13: {=TRANSPOSE(SUMIFS(Графики!$H$7:$H$306,Графики!$D$7:$D$306,'DCF (2)'!DW$6))} -> 0 | DX13: {=TRANSPOSE(SUMIFS(Графики!$H$7:$H$306,Графики!$D$7:$D$306,'DCF (2)'!DX$6))} -> 0 | DY13: {=TRANSPOSE(SUMIFS(Графики!$H$7:$H$306,Графики!$D$7:$D$306,'DCF (2)'!DY$6))} -> 0 | DZ13: {=TRANSPOSE(SUMIFS(Графики!$H$7:$H$306,Графики!$D$7:$D$306,'DCF (2)'!DZ$6))} -> 0 | EA13: {=TRANSPOSE(SUMIFS(Графики!$H$7:$H$306,Графики!$D$7:$D$306,'DCF (2)'!EA$6))} -> 0 | EB13: {=TRANSPOSE(SUMIFS(Графики!$H$7:$H$306,Графики!$D$7:$D$306,'DCF (2)'!EB$6))} -> 0 | EC13: {=TRANSPOSE(SUMIFS(Графики!$H$7:$H$306,Графики!$D$7:$D$306,'DCF (2)'!EC$6))} -> 0 | ED13: {=TRANSPOSE(SUMIFS(Графики!$H$7:$H$306,Графики!$D$7:$D$306,'DCF (2)'!ED$6))} -> 0 | ... KQ13: {=TRANSPOSE(SUMIFS(Графики!$H$7:$H$306,Графики!$D$7:$D$306,'DCF (2)'!KQ$6))} -> 0
B14: Вознаграждение по займам | C14: =SUM(D14:KQ14) -> 0 | D14: {=TRANSPOSE(SUMIFS(Графики!$J$7:$J$306,Графики!$D$7:$D$306,'DCF (2)'!D$6))*0} -> 0 | E14: {=TRANSPOSE(SUMIFS(Графики!$J$7:$J$306,Графики!$D$7:$D$306,'DCF (2)'!E$6))*0} -> 0 | F14: {=TRANSPOSE(SUMIFS(Графики!$J$7:$J$306,Графики!$D$7:$D$306,'DCF (2)'!F$6))*0} -> 0 | G14: {=TRANSPOSE(SUMIFS(Графики!$J$7:$J$306,Графики!$D$7:$D$306,'DCF (2)'!G$6))*0} -> 0 | H14: {=TRANSPOSE(SUMIFS(Графики!$J$7:$J$306,Графики!$D$7:$D$306,'DCF (2)'!H$6))*0} -> 0 | I14: {=TRANSPOSE(SUMIFS(Графики!$J$7:$J$306,Графики!$D$7:$D$306,'DCF (2)'!I$6))*0} -> 0 | J14: {=TRANSPOSE(SUMIFS(Графики!$J$7:$J$306,Графики!$D$7:$D$306,'DCF (2)'!J$6))*0} -> 0 | K14: {=TRANSPOSE(SUMIFS(Графики!$J$7:$J$306,Графики!$D$7:$D$306,'DCF (2)'!K$6))*0} -> 0 | ... CI14: {=TRANSPOSE(SUMIFS(Графики!$J$7:$J$306,Графики!$D$7:$D$306,'DCF (2)'!CI$6))*0} -> 0 | CJ14: {=TRANSPOSE(SUMIFS(Графики!$J$7:$J$306,Графики!$D$7:$D$306,'DCF (2)'!CJ$6))} -> 0 | CK14: {=TRANSPOSE(SUMIFS(Графики!$J$7:$J$306,Графики!$D$7:$D$306,'DCF (2)'!CK$6))} -> 0 | CL14: {=TRANSPOSE(SUMIFS(Графики!$J$7:$J$306,Графики!$D$7:$D$306,'DCF (2)'!CL$6))} -> 0 | CM14: {=TRANSPOSE(SUMIFS(Графики!$J$7:$J$306,Графики!$D$7:$D$306,'DCF (2)'!CM$6))} -> 0 | CN14: {=TRANSPOSE(SUMIFS(Графики!$J$7:$J$306,Графики!$D$7:$D$306,'DCF (2)'!CN$6))} -> 0 | CO14: {=TRANSPOSE(SUMIFS(Графики!$J$7:$J$306,Графики!$D$7:$D$306,'DCF (2)'!CO$6))} -> 0 | CP14: {=TRANSPOSE(SUMIFS(Графики!$J$7:$J$306,Графики!$D$7:$D$306,'DCF (2)'!CP$6))} -> 0 | CQ14: {=TRANSPOSE(SUMIFS(Графики!$J$7:$J$306,Графики!$D$7:$D$306,'DCF (2)'!CQ$6))} -> 0 | ... KQ14: {=TRANSPOSE(SUMIFS(Графики!$J$7:$J$306,Графики!$D$7:$D$306,'DCF (2)'!KQ$6))} -> 0
B15: Свободный денежный поток по опер. деятельности | C15: =SUM(D15:KQ15) -> -5.3855722e+10 | D15: =D11-SUM(D12:D14) -> 321399000 | E15: =E11-SUM(E12:E14) -> 1.3994671e+08 | F15: =F11-SUM(F12:F14) -> 1.2275393e+08 | G15: =G11-SUM(G12:G14) -> 1.3994671e+08 | H15: =H11-SUM(H12:H14) -> 1.5066001e+08 | I15: =I11-SUM(I12:I14) -> 72983132 | J15: =J11-SUM(J12:J14) -> -6.0539118e+08 | K15: =K11-SUM(K12:K14) -> -6.0539118e+08 | ... KQ15: =KQ11-SUM(KQ12:KQ14) -> 0
B17: Приобретение ЗУ | C17: =SUM(D17:KQ17) -> 10013100000 | D17: {=TRANSPOSE(SUMIFS('Графики (2)'!$E$7:$E$306,'Графики (2)'!$D$7:$D$306,'DCF (2)'!D$6))} -> 5006550000 | E17: {=TRANSPOSE(SUMIFS('Графики (2)'!$E$7:$E$306,'Графики (2)'!$D$7:$D$306,'DCF (2)'!E$6))} -> 0 | F17: {=TRANSPOSE(SUMIFS('Графики (2)'!$E$7:$E$306,'Графики (2)'!$D$7:$D$306,'DCF (2)'!F$6))} -> 0 | G17: {=TRANSPOSE(SUMIFS('Графики (2)'!$E$7:$E$306,'Графики (2)'!$D$7:$D$306,'DCF (2)'!G$6))} -> 0 | H17: {=TRANSPOSE(SUMIFS('Графики (2)'!$E$7:$E$306,'Графики (2)'!$D$7:$D$306,'DCF (2)'!H$6))} -> 0 | I17: {=TRANSPOSE(SUMIFS('Графики (2)'!$E$7:$E$306,'Графики (2)'!$D$7:$D$306,'DCF (2)'!I$6))} -> 0 | J17: {=TRANSPOSE(SUMIFS('Графики (2)'!$E$7:$E$306,'Графики (2)'!$D$7:$D$306,'DCF (2)'!J$6))} -> 0 | K17: {=TRANSPOSE(SUMIFS('Графики (2)'!$E$7:$E$306,'Графики (2)'!$D$7:$D$306,'DCF (2)'!K$6))} -> 0 | ... FE17: {=TRANSPOSE(SUMIFS('Графики (2)'!$E$7:$E$306,'Графики (2)'!$D$7:$D$306,'DCF (2)'!FE$6))} -> 0 | FF17: {=TRANSPOSE(SUMIFS(Графики!$E$7:$E$306,Графики!$D$7:$D$306,'DCF (2)'!FF$6))} -> 0 | FG17: {=TRANSPOSE(SUMIFS(Графики!$E$7:$E$306,Графики!$D$7:$D$306,'DCF (2)'!FG$6))} -> 0 | FH17: {=TRANSPOSE(SUMIFS(Графики!$E$7:$E$306,Графики!$D$7:$D$306,'DCF (2)'!FH$6))} -> 0 | FI17: {=TRANSPOSE(SUMIFS(Графики!$E$7:$E$306,Графики!$D$7:$D$306,'DCF (2)'!FI$6))} -> 0 | FJ17: {=TRANSPOSE(SUMIFS(Графики!$E$7:$E$306,Графики!$D$7:$D$306,'DCF (2)'!FJ$6))} -> 0 | FK17: {=TRANSPOSE(SUMIFS(Графики!$E$7:$E$306,Графики!$D$7:$D$306,'DCF (2)'!FK$6))} -> 0 | FL17: {=TRANSPOSE(SUMIFS(Графики!$E$7:$E$306,Графики!$D$7:$D$306,'DCF (2)'!FL$6))} -> 0 | FM17: {=TRANSPOSE(SUMIFS(Графики!$E$7:$E$306,Графики!$D$7:$D$306,'DCF (2)'!FM$6))} -> 0 | ... KQ17: {=TRANSPOSE(SUMIFS(Графики!$E$7:$E$306,Графики!$D$7:$D$306,'DCF (2)'!KQ$6))} -> 0
B18: Соц нагрузка | C18: =SUM(D18:KQ18) -> 0 | D18: {=TRANSPOSE(SUMIFS(Графики!$G$7:$G$306,Графики!$D$7:$D$306,'DCF (2)'!D$6))} -> 0 | E18: {=TRANSPOSE(SUMIFS(Графики!$G$7:$G$306,Графики!$D$7:$D$306,'DCF (2)'!E$6))} -> 0 | F18: {=TRANSPOSE(SUMIFS(Графики!$G$7:$G$306,Графики!$D$7:$D$306,'DCF (2)'!F$6))} -> 0 | G18: {=TRANSPOSE(SUMIFS(Графики!$G$7:$G$306,Графики!$D$7:$D$306,'DCF (2)'!G$6))} -> 0 | H18: {=TRANSPOSE(SUMIFS(Графики!$G$7:$G$306,Графики!$D$7:$D$306,'DCF (2)'!H$6))} -> 0 | I18: {=TRANSPOSE(SUMIFS(Графики!$G$7:$G$306,Графики!$D$7:$D$306,'DCF (2)'!I$6))} -> 0 | J18: {=TRANSPOSE(SUMIFS(Графики!$G$7:$G$306,Графики!$D$7:$D$306,'DCF (2)'!J$6))} -> 0 | K18: {=TRANSPOSE(SUMIFS(Графики!$G$7:$G$306,Графики!$D$7:$D$306,'DCF (2)'!K$6))} -> 0 | ... JY18: {=TRANSPOSE(SUMIFS(Графики!$G$7:$G$306,Графики!$D$7:$D$306,'DCF (2)'!JY$6))} -> 0 | JZ18: {=TRANSPOSE(SUMIFS(Графики!$E$7:$E$306,Графики!$D$7:$D$306,'DCF (2)'!JZ$6))} -> 0 | KA18: {=TRANSPOSE(SUMIFS(Графики!$G$7:$G$306,Графики!$D$7:$D$306,'DCF (2)'!KA$6))} -> 0 | KB18: {=TRANSPOSE(SUMIFS(Графики!$G$7:$G$306,Графики!$D$7:$D$306,'DCF (2)'!KB$6))} -> 0 | KC18: {=TRANSPOSE(SUMIFS(Графики!$G$7:$G$306,Графики!$D$7:$D$306,'DCF (2)'!KC$6))} -> 0 | KD18: {=TRANSPOSE(SUMIFS(Графики!$G$7:$G$306,Графики!$D$7:$D$306,'DCF (2)'!KD$6))} -> 0 | KE18: {=TRANSPOSE(SUMIFS(Графики!$G$7:$G$306,Графики!$D$7:$D$306,'DCF (2)'!KE$6))} -> 0 | KF18: {=TRANSPOSE(SUMIFS(Графики!$G$7:$G$306,Графики!$D$7:$D$306,'DCF (2)'!KF$6))} -> 0 | KG18: {=TRANSPOSE(SUMIFS(Графики!$G$7:$G$306,Графики!$D$7:$D$306,'DCF (2)'!KG$6))} -> 0 | KH18: {=TRANSPOSE(SUMIFS(Графики!$G$7:$G$306,Графики!$D$7:$D$306,'DCF (2)'!KH$6))} -> 0 | ... KQ18: {=TRANSPOSE(SUMIFS(Графики!$G$7:$G$306,Графики!$D$7:$D$306,'DCF (2)'!KQ$6))} -> 0
B19: Проектирование | C19: =SUM(D19:KQ19) -> 197152741 | D19: {=TRANSPOSE(SUMIFS(Графики!$F$7:$F$306,Графики!$D$7:$D$306,'DCF (2)'!D$6))} -> 15772219 | E19: {=TRANSPOSE(SUMIFS(Графики!$F$7:$F$306,Графики!$D$7:$D$306,'DCF (2)'!E$6))} -> 15772219 | F19: {=TRANSPOSE(SUMIFS(Графики!$F$7:$F$306,Графики!$D$7:$D$306,'DCF (2)'!F$6))} -> 15772219 | G19: {=TRANSPOSE(SUMIFS(Графики!$F$7:$F$306,Графики!$D$7:$D$306,'DCF (2)'!G$6))} -> 15772219 | H19: {=TRANSPOSE(SUMIFS(Графики!$F$7:$F$306,Графики!$D$7:$D$306,'DCF (2)'!H$6))} -> 15772219 | I19: {=TRANSPOSE(SUMIFS(Графики!$F$7:$F$306,Графики!$D$7:$D$306,'DCF (2)'!I$6))} -> 15772219 | J19: {=TRANSPOSE(SUMIFS(Графики!$F$7:$F$306,Графики!$D$7:$D$306,'DCF (2)'!J$6))} -> 15772219 | K19: {=TRANSPOSE(SUMIFS(Графики!$F$7:$F$306,Графики!$D$7:$D$306,'DCF (2)'!K$6))} -> 15772219 | ... KQ19: {=TRANSPOSE(SUMIFS(Графики!$F$7:$F$306,Графики!$D$7:$D$306,'DCF (2)'!KQ$6))} -> 0
B20: Свободный денежный поток от инвестиционной деятельности | C20: =SUM(D20:KQ20) -> -1.0210253e+10 | D20: =-SUM(D17:D19) -> -5.0223222e+09 | E20: =-SUM(E17:E19) -> -15772219 | F20: =-SUM(F17:F19) -> -15772219 | G20: =-SUM(G17:G19) -> -15772219 | H20: =-SUM(H17:H19) -> -15772219 | I20: =-SUM(I17:I19) -> -15772219 | J20: =-SUM(J17:J19) -> -15772219 | K20: =-SUM(K17:K19) -> -15772219 | ... KQ20: =-SUM(KQ17:KQ19) -> 0
B22: FCFF | C22: =SUM(D22:KQ22) -> -6.4065974e+10 | D22: =D15+D20 -> -4.7009232e+09 | E22: =E15+E20 -> 1.2417449e+08 | F22: =F15+F20 -> 1.0698171e+08 | G22: =G15+G20 -> 1.2417449e+08 | H22: =H15+H20 -> 1.3488779e+08 | I22: =I15+I20 -> 57210913 | J22: =J15+J20 -> -6.211634e+08 | K22: =K15+K20 -> -6.211634e+08 | ... KQ22: =KQ15+KQ20 -> 0
B24: Поступление по фин.деят (ОД) | C24: =SUM(D24:KQ24) -> 0 | D24: ='Dashboard (2)'!F24 -> 0
B25: Equity | C25: =SUM(D25:KQ25) -> 10013100000 | D25: =5006550000*2 -> 10013100000
B26: Партнеры/рассрочка | C26: =SUM(D26:KQ26) -> 0
B27: Оттоки по фин.деят (ОД) | C27: =SUM(D27:KQ27) -> 0 | D27: {=TRANSPOSE(SUMIFS(Графики!$K$7:$K$306,Графики!$D$7:$D$306,'DCF (2)'!D$6))*0} -> 0 | E27: {=TRANSPOSE(SUMIFS(Графики!$K$7:$K$306,Графики!$D$7:$D$306,'DCF (2)'!E$6))*0} -> 0 | F27: {=TRANSPOSE(SUMIFS(Графики!$K$7:$K$306,Графики!$D$7:$D$306,'DCF (2)'!F$6))*0} -> 0 | G27: {=TRANSPOSE(SUMIFS(Графики!$K$7:$K$306,Графики!$D$7:$D$306,'DCF (2)'!G$6))*0} -> 0 | H27: {=TRANSPOSE(SUMIFS(Графики!$K$7:$K$306,Графики!$D$7:$D$306,'DCF (2)'!H$6))*0} -> 0 | I27: {=TRANSPOSE(SUMIFS(Графики!$K$7:$K$306,Графики!$D$7:$D$306,'DCF (2)'!I$6))*0} -> 0 | J27: {=TRANSPOSE(SUMIFS(Графики!$K$7:$K$306,Графики!$D$7:$D$306,'DCF (2)'!J$6))*0} -> 0 | K27: {=TRANSPOSE(SUMIFS(Графики!$K$7:$K$306,Графики!$D$7:$D$306,'DCF (2)'!K$6))*0} -> 0 | ... CN27: {=TRANSPOSE(SUMIFS(Графики!$K$7:$K$306,Графики!$D$7:$D$306,'DCF (2)'!CN$6))*0} -> 0 | CO27: {=TRANSPOSE(SUMIFS(Графики!$K$7:$K$306,Графики!$D$7:$D$306,'DCF (2)'!CO$6))} -> 0 | CP27: {=TRANSPOSE(SUMIFS(Графики!$K$7:$K$306,Графики!$D$7:$D$306,'DCF (2)'!CP$6))} -> 0 | CQ27: {=TRANSPOSE(SUMIFS(Графики!$K$7:$K$306,Графики!$D$7:$D$306,'DCF (2)'!CQ$6))} -> 0 | CR27: {=TRANSPOSE(SUMIFS(Графики!$K$7:$K$306,Графики!$D$7:$D$306,'DCF (2)'!CR$6))} -> 0 | CS27: {=TRANSPOSE(SUMIFS(Графики!$K$7:$K$306,Графики!$D$7:$D$306,'DCF (2)'!CS$6))} -> 0 | CT27: {=TRANSPOSE(SUMIFS(Графики!$K$7:$K$306,Графики!$D$7:$D$306,'DCF (2)'!CT$6))} -> 0 | CU27: {=TRANSPOSE(SUMIFS(Графики!$K$7:$K$306,Графики!$D$7:$D$306,'DCF (2)'!CU$6))} -> 0 | CV27: {=TRANSPOSE(SUMIFS(Графики!$K$7:$K$306,Графики!$D$7:$D$306,'DCF (2)'!CV$6))} -> 0 | ... KQ27: {=TRANSPOSE(SUMIFS(Графики!$K$7:$K$306,Графики!$D$7:$D$306,'DCF (2)'!KQ$6))} -> 0
B28: Возврат Equity | C28: =SUM(D28:KQ28) -> 10013100000 | CI28: =5006550000*2 -> 10013100000
B29: Возврат партнеры/рассрочка | C29: =SUM(D29:KQ29) -> 0
B30: Выплата ДВД | C30: =SUM(D30:KQ30) -> 0
B31: Свободный денежный поток от ФИН деятельности | C31: =SUM(D31:KQ31) -> 0 | D31: =D24+D25+D26-D27-D28-D30-D29 -> 10013100000 | E31: =E24+E25+E26-E27-E28-E30-E29 -> 0 | F31: =F24+F25+F26-F27-F28-F30-F29 -> 0 | G31: =G24+G25+G26-G27-G28-G30-G29 -> 0 | H31: =H24+H25+H26-H27-H28-H30-H29 -> 0 | I31: =I24+I25+I26-I27-I28-I30-I29 -> 0 | J31: =J24+J25+J26-J27-J28-J30-J29 -> 0 | K31: =K24+K25+K26-K27-K28-K30-K29 -> 0 | ... KQ31: =KQ24+KQ25+KQ26-KQ27-KQ28-KQ30-KQ29 -> 0
B33: FCFE | C33: =SUM(D33:KQ33) -> -6.4065974e+10 | D33: =D22+D31 -> 5.3121768e+09 | E33: =E22+E31 -> 1.2417449e+08 | F33: =F22+F31 -> 1.0698171e+08 | G33: =G22+G31 -> 1.2417449e+08 | H33: =H22+H31 -> 1.3488779e+08 | I33: =I22+I31 -> 57210913 | J33: =J22+J31 -> -6.211634e+08 | K33: =K22+K31 -> -6.211634e+08 | ... KQ33: =KQ22+KQ31 -> 0
B36: Накопительный денежный поток | C36: KZT | D36: =D33 -> 5.3121768e+09 | E36: =D36+E33 -> 5.4363513e+09 | F36: =E36+F33 -> 5.543333e+09 | G36: =F36+G33 -> 5.6675075e+09 | H36: =G36+H33 -> 5.8023953e+09 | I36: =H36+I33 -> 5.8596062e+09 | J36: =I36+J33 -> 5.2384428e+09 | K36: =J36+K33 -> 4.6172794e+09 | L36: =K36+L33 -> 3.9896365e+09 | ... KQ36: =KP36+KQ33 -> -6.4065974e+10
B37: Дисконтированный поток | C37: KZT | D37: =D22/(1+$C$49)^D4 -> -4.620072e+09 | E37: =E22/(1+$C$49)^E4 -> 1.1993987e+08 | F37: =F22/(1+$C$49)^F4 -> 1.0155616e+08 | G37: =G22/(1+$C$49)^G4 -> 1.1584965e+08 | H37: =H22/(1+$C$49)^H4 -> 1.2368031e+08 | I37: =I22/(1+$C$49)^I4 -> 51555188 | J37: =J22/(1+$C$49)^J4 -> -5.501295e+08 | K37: =K22/(1+$C$49)^K4 -> -5.4066781e+08 | ... KQ37: =KQ22/(1+$C$49)^KQ4 -> 0
B38: Накопительный денежный поток | C38: KZT | D38: =D37 -> -4.620072e+09 | E38: =E37 -> 1.1993987e+08 | F38: =F37 -> 1.0155616e+08 | G38: =G37 -> 1.1584965e+08 | H38: =H37 -> 1.2368031e+08 | I38: =I37 -> 51555188 | J38: =J37 -> -5.501295e+08 | K38: =K37 -> -5.4066781e+08 | ... KQ38: =KQ37 -> 0
B39: Индекс окупаемости, мес | C39: {=MATCH(TRUE,D36:JX36>=C25,0)} -> #N/A | D39: =IF(D38<0,1,0) -> 1 | E39: =IF(E38<0,1,0) -> 0 | F39: =IF(F38<0,1,0) -> 0 | G39: =IF(G38<0,1,0) -> 0 | H39: =IF(H38<0,1,0) -> 0 | I39: =IF(I38<0,1,0) -> 0 | J39: =IF(J38<0,1,0) -> 1 | K39: =IF(K38<0,1,0) -> 1 | ... KQ39: =IF(KQ38<0,1,0) -> 0
B42: Equity discount rate | C42: =18%/12 -> 0.015
B43: IRR FCFF | C43: =IRR(D53:D61) -> #NUM! | D43: =C43*12 -> #NUM!
B44: NPV FCFF | C44: =NPV(C42,E22:CD22)+D22 -> -3.1318888e+10
B46: ROE | C46: =IFERROR(C22/C25, 0) -> -6.3982158
B47: ROI | C47: =IFERROR(C22/SUM(C24:C26),0) -> -6.3982158
B48: DPP | C48: =C39 -> #N/A
B49: WACC месячный | C49: =21%/12 -> 0.0175
B50: ROI | C50: =IFERROR(C22/SUM(C24:C26),0) -> -6.3982158
C53: 2026 | D53: =SUM(D22:K22) -> -5.3958206e+09
C54: 2027 | D54: =SUM(L22:W22) -> -4.8032938e+09
C55: 2028 | D55: =SUM(X22:AI22) -> -6.2213665e+09
C56: 2029 | D56: =SUM(AJ22:AU22) -> -1.0176674e+10
C57: 2030 | D57: =SUM(AV22:BG22) -> -1.0206916e+10
C58: 2031 | D58: =SUM(BH22:BS22) -> -1.0206916e+10
C59: 2032 | D59: =SUM(BT22:CE22) -> -9.1439474e+09
C60: 2033 | D60: =SUM(CF22:CQ22) -> -6.8231045e+09
C61: 2034 | D61: =SUM(CR22:DC22) -> -1.0879357e+09

Sheet Графики (2)
H1: =H3-H2 -> 0
F2: =SUBTOTAL(9,F7:F306) -> 197152741 | G2: =SUBTOTAL(9,G7:G306) -> 0 | H2: =SUBTOTAL(9,H7:H306) -> 3.397215e+09 | I2: =SUBTOTAL(9,I7:I306) -> 6.8771146e+08 | J2: =SUBTOTAL(9,J7:J306) -> 112218750 | K2: =SUBTOTAL(9,K7:K306) -> 675000000
E3: ='PnL (2)'!B49 -> 10013100000 | F3: ='PnL все'!B50 -> 197152741 | G3: ='PnL все'!B62 -> 0 | H3: ='PnL (2)'!B73 -> 3.397215e+09 | I3: ='PnL (2)'!B70 -> 6.8771146e+08 | K3: =Credit!D2 -> 675000000
F4: 6
H5: =EDATE(D15,24) -> 47178
E6: Приобретение ЗУ | F6: Проектирование | G6: Соц нагрузка | H6: КПН | I6: НДС к уплате | J6: Вознаграждение по займам | K6: Оттоки по фин.деят (ОД)
B7: 1 | C7: =MONTH(D7) -> 7 | D7: =DCF!D6 -> 46204 | E7: =$E$3*50% -> 5006550000 | F7: =$F$3*8% -> 15772219 | J7: =SUMIF(Credit!$A$12:$A$371,'Графики (2)'!D7,Credit!$D$12:$D$371) -> 11812500 | K7: =SUMIF(Credit!$A$12:$A$371,'Графики (2)'!D7,Credit!$C$12:$C$371) -> 37500000
B8: =B7+1 -> 2 | C8: =MONTH(D8) -> 8 | D8: =EDATE(D7,1) -> 46235 | F8: =$F$3*8% -> 15772219 | J8: =SUMIF(Credit!$A$12:$A$371,'Графики (2)'!D8,Credit!$D$12:$D$371) -> 11156250 | K8: =SUMIF(Credit!$A$12:$A$371,'Графики (2)'!D8,Credit!$C$12:$C$371) -> 37500000
B9: =B8+1 -> 3 | C9: =MONTH(D9) -> 9 | D9: =EDATE(D8,1) -> 46266 | F9: =$F$3*8% -> 15772219 | I9: =$I$3*2.5% -> 17192786 | J9: =SUMIF(Credit!$A$12:$A$371,'Графики (2)'!D9,Credit!$D$12:$D$371) -> 10500000 | K9: =SUMIF(Credit!$A$12:$A$371,'Графики (2)'!D9,Credit!$C$12:$C$371) -> 37500000
B10: =B9+1 -> 4 | C10: =MONTH(D10) -> 10 | D10: =EDATE(D9,1) -> 46296 | F10: =$F$3*8% -> 15772219 | J10: =SUMIF(Credit!$A$12:$A$371,'Графики (2)'!D10,Credit!$D$12:$D$371) -> 9843750 | K10: =SUMIF(Credit!$A$12:$A$371,'Графики (2)'!D10,Credit!$C$12:$C$371) -> 37500000
B11: =B10+1 -> 5 | C11: =MONTH(D11) -> 11 | D11: =EDATE(D10,1) -> 46327 | F11: =$F$3*8% -> 15772219 | J11: =SUMIF(Credit!$A$12:$A$371,'Графики (2)'!D11,Credit!$D$12:$D$371) -> 9187500 | K11: =SUMIF(Credit!$A$12:$A$371,'Графики (2)'!D11,Credit!$C$12:$C$371) -> 37500000
B12: =B11+1 -> 6 | C12: =MONTH(D12) -> 12 | D12: =EDATE(D11,1) -> 46357 | F12: =$F$3*8% -> 15772219 | I12: =$I$3*2.5% -> 17192786 | J12: =SUMIF(Credit!$A$12:$A$371,'Графики (2)'!D12,Credit!$D$12:$D$371) -> 8531250 | K12: =SUMIF(Credit!$A$12:$A$371,'Графики (2)'!D12,Credit!$C$12:$C$371) -> 37500000
B13: =B12+1 -> 7 | C13: =MONTH(D13) -> 1 | D13: =EDATE(D12,1) -> 46388 | F13: =$F$3*8% -> 15772219 | J13: =SUMIF(Credit!$A$12:$A$371,'Графики (2)'!D13,Credit!$D$12:$D$371) -> 7875000 | K13: =SUMIF(Credit!$A$12:$A$371,'Графики (2)'!D13,Credit!$C$12:$C$371) -> 37500000
B14: =B13+1 -> 8 | C14: =MONTH(D14) -> 2 | D14: =EDATE(D13,1) -> 46419 | F14: =$F$3*8% -> 15772219 | J14: =SUMIF(Credit!$A$12:$A$371,'Графики (2)'!D14,Credit!$D$12:$D$371) -> 7218750 | K14: =SUMIF(Credit!$A$12:$A$371,'Графики (2)'!D14,Credit!$C$12:$C$371) -> 37500000
B15: =B14+1 -> 9 | C15: =MONTH(D15) -> 3 | D15: =EDATE(D14,1) -> 46447 | F15: =$F$3*8% -> 15772219 | I15: =$I$3*2.5% -> 17192786 | J15: =SUMIF(Credit!$A$12:$A$371,'Графики (2)'!D15,Credit!$D$12:$D$371) -> 6562500 | K15: =SUMIF(Credit!$A$12:$A$371,'Графики (2)'!D15,Credit!$C$12:$C$371) -> 37500000 | M15: =100/12 -> 8.3333333
B16: =B15+1 -> 10 | C16: =MONTH(D16) -> 4 | D16: =EDATE(D15,1) -> 46478 | F16: =$F$3*8% -> 15772219 | J16: =SUMIF(Credit!$A$12:$A$371,'Графики (2)'!D16,Credit!$D$12:$D$371) -> 5906250 | K16: =SUMIF(Credit!$A$12:$A$371,'Графики (2)'!D16,Credit!$C$12:$C$371) -> 37500000
B17: =B16+1 -> 11 | C17: =MONTH(D17) -> 5 | D17: =EDATE(D16,1) -> 46508 | F17: =$F$3*8% -> 15772219 | J17: =SUMIF(Credit!$A$12:$A$371,'Графики (2)'!D17,Credit!$D$12:$D$371) -> 5250000 | K17: =SUMIF(Credit!$A$12:$A$371,'Графики (2)'!D17,Credit!$C$12:$C$371) -> 37500000 | M17: =8*11 -> 88
B18: =B17+1 -> 12 | C18: =MONTH(D18) -> 6 | D18: =EDATE(D17,1) -> 46539 | F18: =$F$3*12% -> 23658329 | H18: =$H$3*10% -> 3.397215e+08 | I18: =$I$3*2.5% -> 17192786 | J18: =SUMIF(Credit!$A$12:$A$371,'Графики (2)'!D18,Credit!$D$12:$D$371) -> 4593750 | K18: =SUMIF(Credit!$A$12:$A$371,'Графики (2)'!D18,Credit!$C$12:$C$371) -> 37500000
B19: =B18+1 -> 13 | C19: =MONTH(D19) -> 7 | D19: =EDATE(D18,1) -> 46569 | J19: =SUMIF(Credit!$A$12:$A$371,'Графики (2)'!D19,Credit!$D$12:$D$371) -> 3937500 | K19: =SUMIF(Credit!$A$12:$A$371,'Графики (2)'!D19,Credit!$C$12:$C$371) -> 37500000
B20: =B19+1 -> 14 | C20: =MONTH(D20) -> 8 | D20: =EDATE(D19,1) -> 46600 | J20: =SUMIF(Credit!$A$12:$A$371,'Графики (2)'!D20,Credit!$D$12:$D$371) -> 3281250 | K20: =SUMIF(Credit!$A$12:$A$371,'Графики (2)'!D20,Credit!$C$12:$C$371) -> 37500000
B21: =B20+1 -> 15 | C21: =MONTH(D21) -> 9 | D21: =EDATE(D20,1) -> 46631 | I21: =$I$3*2.5% -> 17192786 | J21: =SUMIF(Credit!$A$12:$A$371,'Графики (2)'!D21,Credit!$D$12:$D$371) -> 2625000 | K21: =SUMIF(Credit!$A$12:$A$371,'Графики (2)'!D21,Credit!$C$12:$C$371) -> 37500000
B22: =B21+1 -> 16 | C22: =MONTH(D22) -> 10 | D22: =EDATE(D21,1) -> 46661 | J22: =SUMIF(Credit!$A$12:$A$371,'Графики (2)'!D22,Credit!$D$12:$D$371) -> 1968750 | K22: =SUMIF(Credit!$A$12:$A$371,'Графики (2)'!D22,Credit!$C$12:$C$371) -> 37500000
B23: =B22+1 -> 17 | C23: =MONTH(D23) -> 11 | D23: =EDATE(D22,1) -> 46692 | J23: =SUMIF(Credit!$A$12:$A$371,'Графики (2)'!D23,Credit!$D$12:$D$371) -> 1312500 | K23: =SUMIF(Credit!$A$12:$A$371,'Графики (2)'!D23,Credit!$C$12:$C$371) -> 37500000
B24: =B23+1 -> 18 | C24: =MONTH(D24) -> 12 | D24: =EDATE(D23,1) -> 46722 | I24: =$I$3*2.5% -> 17192786 | J24: =SUMIF(Credit!$A$12:$A$371,'Графики (2)'!D24,Credit!$D$12:$D$371) -> 656250 | K24: =SUMIF(Credit!$A$12:$A$371,'Графики (2)'!D24,Credit!$C$12:$C$371) -> 37500000
B25: =B24+1 -> 19 | C25: =MONTH(D25) -> 1 | D25: =EDATE(D24,1) -> 46753 | J25: =SUMIF(Credit!$A$12:$A$371,'Графики (2)'!D25,Credit!$D$12:$D$371) -> 0 | K25: =SUMIF(Credit!$A$12:$A$371,'Графики (2)'!D25,Credit!$C$12:$C$371) -> 0
B26: =B25+1 -> 20 | C26: =MONTH(D26) -> 2 | D26: =EDATE(D25,1) -> 46784 | J26: =SUMIF(Credit!$A$12:$A$371,'Графики (2)'!D26,Credit!$D$12:$D$371) -> 0 | K26: =SUMIF(Credit!$A$12:$A$371,'Графики (2)'!D26,Credit!$C$12:$C$371) -> 0
B27: =B26+1 -> 21 | C27: =MONTH(D27) -> 3 | D27: =EDATE(D26,1) -> 46813 | I27: =$I$3*2.5% -> 17192786 | J27: =SUMIF(Credit!$A$12:$A$371,'Графики (2)'!D27,Credit!$D$12:$D$371) -> 0 | K27: =SUMIF(Credit!$A$12:$A$371,'Графики (2)'!D27,Credit!$C$12:$C$371) -> 0
B28: =B27+1 -> 22 | C28: =MONTH(D28) -> 4 | D28: =EDATE(D27,1) -> 46844 | J28: =SUMIF(Credit!$A$12:$A$371,'Графики (2)'!D28,Credit!$D$12:$D$371) -> 0 | K28: =SUMIF(Credit!$A$12:$A$371,'Графики (2)'!D28,Credit!$C$12:$C$371) -> 0
B29: =B28+1 -> 23 | C29: =MONTH(D29) -> 5 | D29: =EDATE(D28,1) -> 46874 | J29: =SUMIF(Credit!$A$12:$A$371,'Графики (2)'!D29,Credit!$D$12:$D$371) -> 0 | K29: =SUMIF(Credit!$A$12:$A$371,'Графики (2)'!D29,Credit!$C$12:$C$371) -> 0
B30: =B29+1 -> 24 | C30: =MONTH(D30) -> 6 | D30: =EDATE(D29,1) -> 46905 | G30: =$G$3/24 -> 0 | H30: =$H$3*10% -> 3.397215e+08 | I30: =$I$3*2.5% -> 17192786 | J30: =SUMIF(Credit!$A$12:$A$371,'Графики (2)'!D30,Credit!$D$12:$D$371) -> 0 | K30: =SUMIF(Credit!$A$12:$A$371,'Графики (2)'!D30,Credit!$C$12:$C$371) -> 0
B31: =B30+1 -> 25 | C31: =MONTH(D31) -> 7 | D31: =EDATE(D30,1) -> 46935 | G31: =$G$3/24 -> 0 | J31: =SUMIF(Credit!$A$12:$A$371,'Графики (2)'!D31,Credit!$D$12:$D$371) -> 0 | K31: =SUMIF(Credit!$A$12:$A$371,'Графики (2)'!D31,Credit!$C$12:$C$371) -> 0
B32: =B31+1 -> 26 | C32: =MONTH(D32) -> 8 | D32: =EDATE(D31,1) -> 46966 | G32: =$G$3/24 -> 0 | J32: =SUMIF(Credit!$A$12:$A$371,'Графики (2)'!D32,Credit!$D$12:$D$371) -> 0 | K32: =SUMIF(Credit!$A$12:$A$371,'Графики (2)'!D32,Credit!$C$12:$C$371) -> 0
B33: =B32+1 -> 27 | C33: =MONTH(D33) -> 9 | D33: =EDATE(D32,1) -> 46997 | G33: =$G$3/24 -> 0 | I33: =$I$3*2.5% -> 17192786 | J33: =SUMIF(Credit!$A$12:$A$371,'Графики (2)'!D33,Credit!$D$12:$D$371) -> 0 | K33: =SUMIF(Credit!$A$12:$A$371,'Графики (2)'!D33,Credit!$C$12:$C$371) -> 0
B34: =B33+1 -> 28 | C34: =MONTH(D34) -> 10 | D34: =EDATE(D33,1) -> 47027 | G34: =$G$3/24 -> 0 | J34: =SUMIF(Credit!$A$12:$A$371,'Графики (2)'!D34,Credit!$D$12:$D$371) -> 0 | K34: =SUMIF(Credit!$A$12:$A$371,'Графики (2)'!D34,Credit!$C$12:$C$371) -> 0
B35: =B34+1 -> 29 | C35: =MONTH(D35) -> 11 | D35: =EDATE(D34,1) -> 47058 | G35: =$G$3/24 -> 0 | J35: =SUMIF(Credit!$A$12:$A$371,'Графики (2)'!D35,Credit!$D$12:$D$371) -> 0 | K35: =SUMIF(Credit!$A$12:$A$371,'Графики (2)'!D35,Credit!$C$12:$C$371) -> 0
B36: =B35+1 -> 30 | C36: =MONTH(D36) -> 12 | D36: =EDATE(D35,1) -> 47088 | G36: =$G$3/24 -> 0 | I36: =$I$3*2.5% -> 17192786 | J36: =SUMIF(Credit!$A$12:$A$371,'Графики (2)'!D36,Credit!$D$12:$D$371) -> 0 | K36: =SUMIF(Credit!$A$12:$A$371,'Графики (2)'!D36,Credit!$C$12:$C$371) -> 0 | M36: =100/6 -> 16.666667
B37: =B36+1 -> 31 | C37: =MONTH(D37) -> 1 | D37: =EDATE(D36,1) -> 47119 | G37: =$G$3/24 -> 0 | J37: =SUMIF(Credit!$A$12:$A$371,'Графики (2)'!D37,Credit!$D$12:$D$371) -> 0 | K37: =SUMIF(Credit!$A$12:$A$371,'Графики (2)'!D37,Credit!$C$12:$C$371) -> 0 | M37: 16.666667
B38: =B37+1 -> 32 | C38: =MONTH(D38) -> 2 | D38: =EDATE(D37,1) -> 47150 | G38: =$G$3/24 -> 0 | J38: =SUMIF(Credit!$A$12:$A$371,'Графики (2)'!D38,Credit!$D$12:$D$371) -> 0 | K38: =SUMIF(Credit!$A$12:$A$371,'Графики (2)'!D38,Credit!$C$12:$C$371) -> 0
B39: =B38+1 -> 33 | C39: =MONTH(D39) -> 3 | D39: =EDATE(D38,1) -> 47178 | G39: =$G$3/24 -> 0 | I39: =$I$3*2.5% -> 17192786 | J39: =SUMIF(Credit!$A$12:$A$371,'Графики (2)'!D39,Credit!$D$12:$D$371) -> 0 | K39: =SUMIF(Credit!$A$12:$A$371,'Графики (2)'!D39,Credit!$C$12:$C$371) -> 0
B40: =B39+1 -> 34 | C40: =MONTH(D40) -> 4 | D40: =EDATE(D39,1) -> 47209 | G40: =$G$3/24 -> 0 | J40: =SUMIF(Credit!$A$12:$A$371,'Графики (2)'!D40,Credit!$D$12:$D$371) -> 0 | K40: =SUMIF(Credit!$A$12:$A$371,'Графики (2)'!D40,Credit!$C$12:$C$371) -> 0 | M40: =16*5 -> 80
B41: =B40+1 -> 35 | C41: =MONTH(D41) -> 5 | D41: =EDATE(D40,1) -> 47239 | G41: =$G$3/24 -> 0 | J41: =SUMIF(Credit!$A$12:$A$371,'Графики (2)'!D41,Credit!$D$12:$D$371) -> 0 | K41: =SUMIF(Credit!$A$12:$A$371,'Графики (2)'!D41,Credit!$C$12:$C$371) -> 0
B42: =B41+1 -> 36 | C42: =MONTH(D42) -> 6 | D42: =EDATE(D41,1) -> 47270 | G42: =$G$3/24 -> 0 | H42: =$H$3*10% -> 3.397215e+08 | I42: =$I$3*2.5% -> 17192786 | J42: =SUMIF(Credit!$A$12:$A$371,'Графики (2)'!D42,Credit!$D$12:$D$371) -> 0 | K42: =SUMIF(Credit!$A$12:$A$371,'Графики (2)'!D42,Credit!$C$12:$C$371) -> 0
B43: =B42+1 -> 37 | C43: =MONTH(D43) -> 7 | D43: =EDATE(D42,1) -> 47300 | G43: =$G$3/24 -> 0 | J43: =SUMIF(Credit!$A$12:$A$371,'Графики (2)'!D43,Credit!$D$12:$D$371) -> 0 | K43: =SUMIF(Credit!$A$12:$A$371,'Графики (2)'!D43,Credit!$C$12:$C$371) -> 0 | M43: 1.94757e+08 | O43: 1.8266701e+08
B44: =B43+1 -> 38 | C44: =MONTH(D44) -> 8 | D44: =EDATE(D43,1) -> 47331 | G44: =$G$3/24 -> 0 | J44: =SUMIF(Credit!$A$12:$A$371,'Графики (2)'!D44,Credit!$D$12:$D$371) -> 0 | K44: =SUMIF(Credit!$A$12:$A$371,'Графики (2)'!D44,Credit!$C$12:$C$371) -> 0
B45: =B44+1 -> 39 | C45: =MONTH(D45) -> 9 | D45: =EDATE(D44,1) -> 47362 | G45: =$G$3/24 -> 0 | I45: =$I$3*2.5% -> 17192786 | J45: =SUMIF(Credit!$A$12:$A$371,'Графики (2)'!D45,Credit!$D$12:$D$371) -> 0 | K45: =SUMIF(Credit!$A$12:$A$371,'Графики (2)'!D45,Credit!$C$12:$C$371) -> 0 | O45: =O43/2 -> 91333505
B46: =B45+1 -> 40 | C46: =MONTH(D46) -> 10 | D46: =EDATE(D45,1) -> 47392 | G46: =$G$3/24 -> 0 | J46: =SUMIF(Credit!$A$12:$A$371,'Графики (2)'!D46,Credit!$D$12:$D$371) -> 0 | K46: =SUMIF(Credit!$A$12:$A$371,'Графики (2)'!D46,Credit!$C$12:$C$371) -> 0
B47: =B46+1 -> 41 | C47: =MONTH(D47) -> 11 | D47: =EDATE(D46,1) -> 47423 | G47: =$G$3/24 -> 0 | J47: =SUMIF(Credit!$A$12:$A$371,'Графики (2)'!D47,Credit!$D$12:$D$371) -> 0 | K47: =SUMIF(Credit!$A$12:$A$371,'Графики (2)'!D47,Credit!$C$12:$C$371) -> 0
B48: =B47+1 -> 42 | C48: =MONTH(D48) -> 12 | D48: =EDATE(D47,1) -> 47453 | G48: =$G$3/24 -> 0 | I48: =$I$3*2.5% -> 17192786 | J48: =SUMIF(Credit!$A$12:$A$371,'Графики (2)'!D48,Credit!$D$12:$D$371) -> 0 | K48: =SUMIF(Credit!$A$12:$A$371,'Графики (2)'!D48,Credit!$C$12:$C$371) -> 0 | M48: =I48*3 -> 51578359
B49: =B48+1 -> 43 | C49: =MONTH(D49) -> 1 | D49: =EDATE(D48,1) -> 47484 | G49: =$G$3/24 -> 0 | J49: =SUMIF(Credit!$A$12:$A$371,'Графики (2)'!D49,Credit!$D$12:$D$371) -> 0 | K49: =SUMIF(Credit!$A$12:$A$371,'Графики (2)'!D49,Credit!$C$12:$C$371) -> 0
B50: =B49+1 -> 44 | C50: =MONTH(D50) -> 2 | D50: =EDATE(D49,1) -> 47515 | G50: =$G$3/24 -> 0 | J50: =SUMIF(Credit!$A$12:$A$371,'Графики (2)'!D50,Credit!$D$12:$D$371) -> 0 | K50: =SUMIF(Credit!$A$12:$A$371,'Графики (2)'!D50,Credit!$C$12:$C$371) -> 0
B51: =B50+1 -> 45 | C51: =MONTH(D51) -> 3 | D51: =EDATE(D50,1) -> 47543 | G51: =$G$3/24 -> 0 | I51: =$I$3*2.5% -> 17192786 | J51: =SUMIF(Credit!$A$12:$A$371,'Графики (2)'!D51,Credit!$D$12:$D$371) -> 0 | K51: =SUMIF(Credit!$A$12:$A$371,'Графики (2)'!D51,Credit!$C$12:$C$371) -> 0
B52: =B51+1 -> 46 | C52: =MONTH(D52) -> 4 | D52: =EDATE(D51,1) -> 47574 | G52: =$G$3/24 -> 0 | J52: =SUMIF(Credit!$A$12:$A$371,'Графики (2)'!D52,Credit!$D$12:$D$371) -> 0 | K52: =SUMIF(Credit!$A$12:$A$371,'Графики (2)'!D52,Credit!$C$12:$C$371) -> 0
B53: =B52+1 -> 47 | C53: =MONTH(D53) -> 5 | D53: =EDATE(D52,1) -> 47604 | G53: =$G$3/24 -> 0 | J53: =SUMIF(Credit!$A$12:$A$371,'Графики (2)'!D53,Credit!$D$12:$D$371) -> 0 | K53: =SUMIF(Credit!$A$12:$A$371,'Графики (2)'!D53,Credit!$C$12:$C$371) -> 0
B54: =B53+1 -> 48 | C54: =MONTH(D54) -> 6 | D54: =EDATE(D53,1) -> 47635 | H54: =$H$3*10% -> 3.397215e+08 | I54: =$I$3*2.5% -> 17192786 | J54: =SUMIF(Credit!$A$12:$A$371,'Графики (2)'!D54,Credit!$D$12:$D$371) -> 0 | K54: =SUMIF(Credit!$A$12:$A$371,'Графики (2)'!D54,Credit!$C$12:$C$371) -> 0
B55: =B54+1 -> 49 | C55: =MONTH(D55) -> 7 | D55: =EDATE(D54,1) -> 47665 | J55: =SUMIF(Credit!$A$12:$A$371,'Графики (2)'!D55,Credit!$D$12:$D$371) -> 0 | K55: =SUMIF(Credit!$A$12:$A$371,'Графики (2)'!D55,Credit!$C$12:$C$371) -> 0
B56: =B55+1 -> 50 | C56: =MONTH(D56) -> 8 | D56: =EDATE(D55,1) -> 47696 | J56: =SUMIF(Credit!$A$12:$A$371,'Графики (2)'!D56,Credit!$D$12:$D$371) -> 0 | K56: =SUMIF(Credit!$A$12:$A$371,'Графики (2)'!D56,Credit!$C$12:$C$371) -> 0
B57: =B56+1 -> 51 | C57: =MONTH(D57) -> 9 | D57: =EDATE(D56,1) -> 47727 | I57: =$I$3*2.5% -> 17192786 | J57: =SUMIF(Credit!$A$12:$A$371,'Графики (2)'!D57,Credit!$D$12:$D$371) -> 0 | K57: =SUMIF(Credit!$A$12:$A$371,'Графики (2)'!D57,Credit!$C$12:$C$371) -> 0
B58: =B57+1 -> 52 | C58: =MONTH(D58) -> 10 | D58: =EDATE(D57,1) -> 47757 | J58: =SUMIF(Credit!$A$12:$A$371,'Графики (2)'!D58,Credit!$D$12:$D$371) -> 0 | K58: =SUMIF(Credit!$A$12:$A$371,'Графики (2)'!D58,Credit!$C$12:$C$371) -> 0
B59: =B58+1 -> 53 | C59: =MONTH(D59) -> 11 | D59: =EDATE(D58,1) -> 47788 | J59: =SUMIF(Credit!$A$12:$A$371,'Графики (2)'!D59,Credit!$D$12:$D$371) -> 0 | K59: =SUMIF(Credit!$A$12:$A$371,'Графики (2)'!D59,Credit!$C$12:$C$371) -> 0
B60: =B59+1 -> 54 | C60: =MONTH(D60) -> 12 | D60: =EDATE(D59,1) -> 47818 | I60: =$I$3*2.5% -> 17192786 | J60: =SUMIF(Credit!$A$12:$A$371,'Графики (2)'!D60,Credit!$D$12:$D$371) -> 0 | K60: =SUMIF(Credit!$A$12:$A$371,'Графики (2)'!D60,Credit!$C$12:$C$371) -> 0
B61: =B60+1 -> 55 | C61: =MONTH(D61) -> 1 | D61: =EDATE(D60,1) -> 47849 | J61: =SUMIF(Credit!$A$12:$A$371,'Графики (2)'!D61,Credit!$D$12:$D$371) -> 0 | K61: =SUMIF(Credit!$A$12:$A$371,'Графики (2)'!D61,Credit!$C$12:$C$371) -> 0
B62: =B61+1 -> 56 | C62: =MONTH(D62) -> 2 | D62: =EDATE(D61,1) -> 47880 | J62: =SUMIF(Credit!$A$12:$A$371,'Графики (2)'!D62,Credit!$D$12:$D$371) -> 0 | K62: =SUMIF(Credit!$A$12:$A$371,'Графики (2)'!D62,Credit!$C$12:$C$371) -> 0
B63: =B62+1 -> 57 | C63: =MONTH(D63) -> 3 | D63: =EDATE(D62,1) -> 47908 | I63: =$I$3*2.5% -> 17192786 | J63: =SUMIF(Credit!$A$12:$A$371,'Графики (2)'!D63,Credit!$D$12:$D$371) -> 0 | K63: =SUMIF(Credit!$A$12:$A$371,'Графики (2)'!D63,Credit!$C$12:$C$371) -> 0
B64: =B63+1 -> 58 | C64: =MONTH(D64) -> 4 | D64: =EDATE(D63,1) -> 47939 | J64: =SUMIF(Credit!$A$12:$A$371,'Графики (2)'!D64,Credit!$D$12:$D$371) -> 0 | K64: =SUMIF(Credit!$A$12:$A$371,'Графики (2)'!D64,Credit!$C$12:$C$371) -> 0
B65: =B64+1 -> 59 | C65: =MONTH(D65) -> 5 | D65: =EDATE(D64,1) -> 47969 | J65: =SUMIF(Credit!$A$12:$A$371,'Графики (2)'!D65,Credit!$D$12:$D$371) -> 0 | K65: =SUMIF(Credit!$A$12:$A$371,'Графики (2)'!D65,Credit!$C$12:$C$371) -> 0
B66: =B65+1 -> 60 | C66: =MONTH(D66) -> 6 | D66: =EDATE(D65,1) -> 48000 | H66: =$H$3*10% -> 3.397215e+08 | I66: =$I$3*2.5% -> 17192786 | J66: =SUMIF(Credit!$A$12:$A$371,'Графики (2)'!D66,Credit!$D$12:$D$371) -> 0 | K66: =SUMIF(Credit!$A$12:$A$371,'Графики (2)'!D66,Credit!$C$12:$C$371) -> 0
B67: =B66+1 -> 61 | C67: =MONTH(D67) -> 7 | D67: =EDATE(D66,1) -> 48030 | J67: =SUMIF(Credit!$A$12:$A$371,'Графики (2)'!D67,Credit!$D$12:$D$371) -> 0 | K67: =SUMIF(Credit!$A$12:$A$371,'Графики (2)'!D67,Credit!$C$12:$C$371) -> 0
B68: =B67+1 -> 62 | C68: =MONTH(D68) -> 8 | D68: =EDATE(D67,1) -> 48061 | J68: =SUMIF(Credit!$A$12:$A$371,'Графики (2)'!D68,Credit!$D$12:$D$371) -> 0 | K68: =SUMIF(Credit!$A$12:$A$371,'Графики (2)'!D68,Credit!$C$12:$C$371) -> 0
B69: =B68+1 -> 63 | C69: =MONTH(D69) -> 9 | D69: =EDATE(D68,1) -> 48092 | I69: =$I$3*2.5% -> 17192786 | J69: =SUMIF(Credit!$A$12:$A$371,'Графики (2)'!D69,Credit!$D$12:$D$371) -> 0 | K69: =SUMIF(Credit!$A$12:$A$371,'Графики (2)'!D69,Credit!$C$12:$C$371) -> 0
B70: =B69+1 -> 64 | C70: =MONTH(D70) -> 10 | D70: =EDATE(D69,1) -> 48122 | J70: =SUMIF(Credit!$A$12:$A$371,'Графики (2)'!D70,Credit!$D$12:$D$371) -> 0 | K70: =SUMIF(Credit!$A$12:$A$371,'Графики (2)'!D70,Credit!$C$12:$C$371) -> 0
B71: =B70+1 -> 65 | C71: =MONTH(D71) -> 11 | D71: =EDATE(D70,1) -> 48153 | J71: =SUMIF(Credit!$A$12:$A$371,'Графики (2)'!D71,Credit!$D$12:$D$371) -> 0 | K71: =SUMIF(Credit!$A$12:$A$371,'Графики (2)'!D71,Credit!$C$12:$C$371) -> 0
B72: =B71+1 -> 66 | C72: =MONTH(D72) -> 12 | D72: =EDATE(D71,1) -> 48183 | I72: =$I$3*2.5% -> 17192786 | J72: =SUMIF(Credit!$A$12:$A$371,'Графики (2)'!D72,Credit!$D$12:$D$371) -> 0 | K72: =SUMIF(Credit!$A$12:$A$371,'Графики (2)'!D72,Credit!$C$12:$C$371) -> 0
B73: =B72+1 -> 67 | C73: =MONTH(D73) -> 1 | D73: =EDATE(D72,1) -> 48214 | J73: =SUMIF(Credit!$A$12:$A$371,'Графики (2)'!D73,Credit!$D$12:$D$371) -> 0 | K73: =SUMIF(Credit!$A$12:$A$371,'Графики (2)'!D73,Credit!$C$12:$C$371) -> 0
B74: =B73+1 -> 68 | C74: =MONTH(D74) -> 2 | D74: =EDATE(D73,1) -> 48245 | J74: =SUMIF(Credit!$A$12:$A$371,'Графики (2)'!D74,Credit!$D$12:$D$371) -> 0 | K74: =SUMIF(Credit!$A$12:$A$371,'Графики (2)'!D74,Credit!$C$12:$C$371) -> 0
B75: =B74+1 -> 69 | C75: =MONTH(D75) -> 3 | D75: =EDATE(D74,1) -> 48274 | I75: =$I$3*2.5% -> 17192786 | J75: =SUMIF(Credit!$A$12:$A$371,'Графики (2)'!D75,Credit!$D$12:$D$371) -> 0 | K75: =SUMIF(Credit!$A$12:$A$371,'Графики (2)'!D75,Credit!$C$12:$C$371) -> 0
B76: =B75+1 -> 70 | C76: =MONTH(D76) -> 4 | D76: =EDATE(D75,1) -> 48305 | J76: =SUMIF(Credit!$A$12:$A$371,'Графики (2)'!D76,Credit!$D$12:$D$371) -> 0 | K76: =SUMIF(Credit!$A$12:$A$371,'Графики (2)'!D76,Credit!$C$12:$C$371) -> 0
B77: =B76+1 -> 71 | C77: =MONTH(D77) -> 5 | D77: =EDATE(D76,1) -> 48335 | J77: =SUMIF(Credit!$A$12:$A$371,'Графики (2)'!D77,Credit!$D$12:$D$371) -> 0 | K77: =SUMIF(Credit!$A$12:$A$371,'Графики (2)'!D77,Credit!$C$12:$C$371) -> 0
B78: =B77+1 -> 72 | C78: =MONTH(D78) -> 6 | D78: =EDATE(D77,1) -> 48366 | H78: =$H$3*10% -> 3.397215e+08 | I78: =$I$3*2.5% -> 17192786 | J78: =SUMIF(Credit!$A$12:$A$371,'Графики (2)'!D78,Credit!$D$12:$D$371) -> 0 | K78: =SUMIF(Credit!$A$12:$A$371,'Графики (2)'!D78,Credit!$C$12:$C$371) -> 0
B79: =B78+1 -> 73 | C79: =MONTH(D79) -> 7 | D79: =EDATE(D78,1) -> 48396 | J79: =SUMIF(Credit!$A$12:$A$371,'Графики (2)'!D79,Credit!$D$12:$D$371) -> 0 | K79: =SUMIF(Credit!$A$12:$A$371,'Графики (2)'!D79,Credit!$C$12:$C$371) -> 0
B80: =B79+1 -> 74 | C80: =MONTH(D80) -> 8 | D80: =EDATE(D79,1) -> 48427 | J80: =SUMIF(Credit!$A$12:$A$371,'Графики (2)'!D80,Credit!$D$12:$D$371) -> 0 | K80: =SUMIF(Credit!$A$12:$A$371,'Графики (2)'!D80,Credit!$C$12:$C$371) -> 0
B81: =B80+1 -> 75 | C81: =MONTH(D81) -> 9 | D81: =EDATE(D80,1) -> 48458 | I81: =$I$3*5% -> 34385573 | J81: =SUMIF(Credit!$A$12:$A$371,'Графики (2)'!D81,Credit!$D$12:$D$371) -> 0 | K81: =SUMIF(Credit!$A$12:$A$371,'Графики (2)'!D81,Credit!$C$12:$C$371) -> 0
B82: =B81+1 -> 76 | C82: =MONTH(D82) -> 10 | D82: =EDATE(D81,1) -> 48488 | J82: =SUMIF(Credit!$A$12:$A$371,'Графики (2)'!D82,Credit!$D$12:$D$371) -> 0 | K82: =SUMIF(Credit!$A$12:$A$371,'Графики (2)'!D82,Credit!$C$12:$C$371) -> 0
B83: =B82+1 -> 77 | C83: =MONTH(D83) -> 11 | D83: =EDATE(D82,1) -> 48519 | J83: =SUMIF(Credit!$A$12:$A$371,'Графики (2)'!D83,Credit!$D$12:$D$371) -> 0 | K83: =SUMIF(Credit!$A$12:$A$371,'Графики (2)'!D83,Credit!$C$12:$C$371) -> 0
B84: =B83+1 -> 78 | C84: =MONTH(D84) -> 12 | D84: =EDATE(D83,1) -> 48549 | I84: =$I$3*5% -> 34385573 | J84: =SUMIF(Credit!$A$12:$A$371,'Графики (2)'!D84,Credit!$D$12:$D$371) -> 0 | K84: =SUMIF(Credit!$A$12:$A$371,'Графики (2)'!D84,Credit!$C$12:$C$371) -> 0
B85: =B84+1 -> 79 | C85: =MONTH(D85) -> 1 | D85: =EDATE(D84,1) -> 48580 | J85: =SUMIF(Credit!$A$12:$A$371,'Графики (2)'!D85,Credit!$D$12:$D$371) -> 0 | K85: =SUMIF(Credit!$A$12:$A$371,'Графики (2)'!D85,Credit!$C$12:$C$371) -> 0
B86: =B85+1 -> 80 | C86: =MONTH(D86) -> 2 | D86: =EDATE(D85,1) -> 48611 | J86: =SUMIF(Credit!$A$12:$A$371,'Графики (2)'!D86,Credit!$D$12:$D$371) -> 0 | K86: =SUMIF(Credit!$A$12:$A$371,'Графики (2)'!D86,Credit!$C$12:$C$371) -> 0
B87: =B86+1 -> 81 | C87: =MONTH(D87) -> 3 | D87: =EDATE(D86,1) -> 48639 | I87: =$I$3*5% -> 34385573 | J87: =SUMIF(Credit!$A$12:$A$371,'Графики (2)'!D87,Credit!$D$12:$D$371) -> 0 | K87: =SUMIF(Credit!$A$12:$A$371,'Графики (2)'!D87,Credit!$C$12:$C$371) -> 0
B88: =B87+1 -> 82 | C88: =MONTH(D88) -> 4 | D88: =EDATE(D87,1) -> 48670 | J88: =SUMIF(Credit!$A$12:$A$371,'Графики (2)'!D88,Credit!$D$12:$D$371) -> 0 | K88: =SUMIF(Credit!$A$12:$A$371,'Графики (2)'!D88,Credit!$C$12:$C$371) -> 0
B89: =B88+1 -> 83 | C89: =MONTH(D89) -> 5 | D89: =EDATE(D88,1) -> 48700 | E89: =$E$3*50% -> 5006550000 | J89: =SUMIF(Credit!$A$12:$A$371,'Графики (2)'!D89,Credit!$D$12:$D$371) -> 0 | K89: =SUMIF(Credit!$A$12:$A$371,'Графики (2)'!D89,Credit!$C$12:$C$371) -> 0
B90: =B89+1 -> 84 | C90: =MONTH(D90) -> 6 | D90: =EDATE(D89,1) -> 48731 | H90: =$H$3*10% -> 3.397215e+08 | I90: =$I$3*5% -> 34385573 | J90: =SUMIF(Credit!$A$12:$A$371,'Графики (2)'!D90,Credit!$D$12:$D$371) -> 0 | K90: =SUMIF(Credit!$A$12:$A$371,'Графики (2)'!D90,Credit!$C$12:$C$371) -> 0
B91: =B90+1 -> 85 | C91: =MONTH(D91) -> 7 | D91: =EDATE(D90,1) -> 48761 | J91: =SUMIF(Credit!$A$12:$A$371,'Графики (2)'!D91,Credit!$D$12:$D$371) -> 0 | K91: =SUMIF(Credit!$A$12:$A$371,'Графики (2)'!D91,Credit!$C$12:$C$371) -> 0
B92: =B91+1 -> 86 | C92: =MONTH(D92) -> 8 | D92: =EDATE(D91,1) -> 48792 | J92: =SUMIF(Credit!$A$12:$A$371,'Графики (2)'!D92,Credit!$D$12:$D$371) -> 0 | K92: =SUMIF(Credit!$A$12:$A$371,'Графики (2)'!D92,Credit!$C$12:$C$371) -> 0
B93: =B92+1 -> 87 | C93: =MONTH(D93) -> 9 | D93: =EDATE(D92,1) -> 48823 | I93: =$I$3*5% -> 34385573 | J93: =SUMIF(Credit!$A$12:$A$371,'Графики (2)'!D93,Credit!$D$12:$D$371) -> 0 | K93: =SUMIF(Credit!$A$12:$A$371,'Графики (2)'!D93,Credit!$C$12:$C$371) -> 0
B94: =B93+1 -> 88 | C94: =MONTH(D94) -> 10 | D94: =EDATE(D93,1) -> 48853 | J94: =SUMIF(Credit!$A$12:$A$371,'Графики (2)'!D94,Credit!$D$12:$D$371) -> 0 | K94: =SUMIF(Credit!$A$12:$A$371,'Графики (2)'!D94,Credit!$C$12:$C$371) -> 0
B95: =B94+1 -> 89 | C95: =MONTH(D95) -> 11 | D95: =EDATE(D94,1) -> 48884 | J95: =SUMIF(Credit!$A$12:$A$371,'Графики (2)'!D95,Credit!$D$12:$D$371) -> 0 | K95: =SUMIF(Credit!$A$12:$A$371,'Графики (2)'!D95,Credit!$C$12:$C$371) -> 0
B96: =B95+1 -> 90 | C96: =MONTH(D96) -> 12 | D96: =EDATE(D95,1) -> 48914 | I96: =$I$3*5% -> 34385573 | J96: =SUMIF(Credit!$A$12:$A$371,'Графики (2)'!D96,Credit!$D$12:$D$371) -> 0 | K96: =SUMIF(Credit!$A$12:$A$371,'Графики (2)'!D96,Credit!$C$12:$C$371) -> 0
B97: =B96+1 -> 91 | C97: =MONTH(D97) -> 1 | D97: =EDATE(D96,1) -> 48945 | J97: =SUMIF(Credit!$A$12:$A$371,'Графики (2)'!D97,Credit!$D$12:$D$371) -> 0 | K97: =SUMIF(Credit!$A$12:$A$371,'Графики (2)'!D97,Credit!$C$12:$C$371) -> 0
B98: =B97+1 -> 92 | C98: =MONTH(D98) -> 2 | D98: =EDATE(D97,1) -> 48976 | J98: =SUMIF(Credit!$A$12:$A$371,'Графики (2)'!D98,Credit!$D$12:$D$371) -> 0 | K98: =SUMIF(Credit!$A$12:$A$371,'Графики (2)'!D98,Credit!$C$12:$C$371) -> 0
B99: =B98+1 -> 93 | C99: =MONTH(D99) -> 3 | D99: =EDATE(D98,1) -> 49004 | I99: =$I$3*5% -> 34385573 | J99: =SUMIF(Credit!$A$12:$A$371,'Графики (2)'!D99,Credit!$D$12:$D$371) -> 0 | K99: =SUMIF(Credit!$A$12:$A$371,'Графики (2)'!D99,Credit!$C$12:$C$371) -> 0
B100: =B99+1 -> 94 | C100: =MONTH(D100) -> 4 | D100: =EDATE(D99,1) -> 49035 | J100: =SUMIF(Credit!$A$12:$A$371,'Графики (2)'!D100,Credit!$D$12:$D$371) -> 0 | K100: =SUMIF(Credit!$A$12:$A$371,'Графики (2)'!D100,Credit!$C$12:$C$371) -> 0
...

Sheet Costs (2)
L1: Months
C2: Реализуемая площадь | D2: ='Dashboard все'!C25 -> 6901 | L2: 1 - 4 | M2: 0.003 | N2: 4 | O2: =M2*N2 -> 0.012
C3: Площадь одной очереди | D3: ='Dashboard все'!C26 -> 6901 | L3: 5 | M3: 0.004 | N3: 1 | O3: =M3*N3 -> 0.004
C4: Количество очередей | D4: 1 | L4: 6 - 10 | M4: 0.0155 | N4: =10-6+1 -> 5 | O4: =M4*N4 -> 0.0775
C5: СМР + Накладные | D5: ='PnL (2)'!B40+'PnL (2)'!B52 -> 6.0484095e+10 | L5: 11 - 28 | M5: 0.012 | N5: =28-11+1 -> 18 | O5: =M5*N5 -> 0.216
C6: Расходы на 1 очередь | D6: =D5/D4 -> 6.0484095e+10 | L6: 29-32 | M6: 0.013 | N6: =32-29+1 -> 4 | O6: =M6*N6 -> 0.052
L7: 33-77 | M7: 0.0135 | N7: =77-33+1 -> 45 | O7: =M7*N7 -> 0.6075
L10: 78-84 | M10: =O10/N10 -> 0.0044285714 | N10: =84-78+1 -> 7 | O10: =O11-O2-O3-O4-O5-O6-O7-O8-O9 -> 0.031
L11: Total | M11: 0.01 | N11: =SUM(N2:N10) -> 84 | O11: 1
C16: =C15/D6 -> 0
E17: ='DCF (2)'!D6 -> 46204 | F17: ='DCF (2)'!E6 -> 46235 | G17: ='DCF (2)'!F6 -> 46266 | H17: ='DCF (2)'!G6 -> 46296 | I17: ='DCF (2)'!H6 -> 46327 | J17: ='DCF (2)'!I6 -> 46357 | K17: ='DCF (2)'!J6 -> 46388 | L17: ='DCF (2)'!K6 -> 46419 | ... ET17: ='DCF (2)'!ES6 -> 50618
B18: =SUM(B19:B38) -> 6.0484095e+10 | D18: Очередь | F18: 1 | G18: =F18+1 -> 2 | H18: =G18+1 -> 3 | I18: =H18+1 -> 4 | J18: =I18+1 -> 5 | K18: =J18+1 -> 6 | L18: =K18+1 -> 7 | M18: =L18+1 -> 8 | N18: =M18+1 -> 9 | ... ET18: =ES18+1 -> 145
B19: =SUM(F19:ET19) -> 6.0484095e+10 | C19: =IF(D19<=$D$4,1,0) -> 1 | D19: 1 | F19: =$M$2*$D$6 -> 1.8145229e+08 | G19: =$M$2*$D$6 -> 1.8145229e+08 | H19: =$M$2*$D$6 -> 1.8145229e+08 | I19: =$M$2*$D$6 -> 1.8145229e+08 | J19: =$M$3*$D$6 -> 2.4193638e+08 | K19: =$M$4*$D$6 -> 9.3750348e+08 | L19: =$M$4*$D$6 -> 9.3750348e+08 | M19: =$M$4*$D$6 -> 9.3750348e+08 | N19: =$M$4*$D$6 -> 9.3750348e+08 | O19: =$M$4*$D$6 -> 9.3750348e+08 | P19: =$M$5*$D$6 -> 7.2580914e+08 | Q19: =$M$5*$D$6 -> 7.2580914e+08 | R19: =$M$5*$D$6 -> 7.2580914e+08 | S19: =$M$5*$D$6 -> 7.2580914e+08 | T19: =$M$5*$D$6 -> 7.2580914e+08 | U19: =$M$5*$D$6 -> 7.2580914e+08 | V19: =$M$5*$D$6 -> 7.2580914e+08 | W19: =$M$5*$D$6 -> 7.2580914e+08 | ... AG19: =$M$5*$D$6 -> 7.2580914e+08 | AH19: =$M$6*$D$6 -> 7.8629324e+08 | AI19: =$M$6*$D$6 -> 7.8629324e+08 | AJ19: =$M$6*$D$6 -> 7.8629324e+08 | AK19: =$M$6*$D$6 -> 7.8629324e+08 | AL19: =$M$7*$D$6 -> 8.1653529e+08 | AM19: =$M$7*$D$6 -> 8.1653529e+08 | AN19: =$M$7*$D$6 -> 8.1653529e+08 | AO19: =$M$7*$D$6 -> 8.1653529e+08 | AP19: =$M$7*$D$6 -> 8.1653529e+08 | AQ19: =$M$7*$D$6 -> 8.1653529e+08 | AR19: =$M$7*$D$6 -> 8.1653529e+08 | AS19: =$M$7*$D$6 -> 8.1653529e+08 | ... CD19: =$M$7*$D$6 -> 8.1653529e+08 | CE19: =$M$10*$D$6 -> 2.6785814e+08 | CF19: =$M$10*$D$6 -> 2.6785814e+08 | CG19: =$M$10*$D$6 -> 2.6785814e+08 | CH19: =$M$10*$D$6 -> 2.6785814e+08 | CI19: =$M$10*$D$6 -> 2.6785814e+08 | CJ19: =$M$10*$D$6 -> 2.6785814e+08 | CK19: =$M$10*$D$6 -> 2.6785814e+08
B20: =SUM(H20:ET20) -> 0 | C20: =IF(D20<=$D$4,1,0) -> 0 | D20: =D19+C19 -> 2 | N20: =IF($C20=1,H$19,0) -> 0 | O20: =IF($C$20=1,I19,0) -> 0 | P20: =IF($C$20=1,J19,0) -> 0 | Q20: =IF($C$20=1,K19,0) -> 0 | R20: =IF($C$20=1,L19,0) -> 0 | S20: =IF($C$20=1,M19,0) -> 0 | T20: =IF($C$20=1,N19,0) -> 0 | U20: =IF($C$20=1,O19,0) -> 0 | V20: =IF($C$20=1,P19,0) -> 0 | ... AK20: =IF($C$20=1,AE19,0) -> 0
B21: =SUM(H21:ET21) -> 0 | C21: =IF(D21<=$D$4,1,0) -> 0 | D21: 3 | T21: =IF($C21=1,H$19,0) -> 0 | U21: =IF($C21=1,I$19,0) -> 0 | V21: =IF($C21=1,J$19,0) -> 0 | W21: =IF($C21=1,K$19,0) -> 0 | X21: =IF($C21=1,L$19,0) -> 0 | Y21: =IF($C21=1,M$19,0) -> 0 | Z21: =IF($C21=1,N$19,0) -> 0 | AA21: =IF($C21=1,O$19,0) -> 0 | ... AQ21: =IF($C21=1,AE$19,0) -> 0
B22: =SUM(H22:ET22) -> 0 | C22: =IF(D22<=$D$4,1,0) -> 0 | D22: 4 | Z22: =IF($C22=1,H$19,0) -> 0 | AA22: =IF($C22=1,I$19,0) -> 0 | AB22: =IF($C22=1,J$19,0) -> 0 | AC22: =IF($C22=1,K$19,0) -> 0 | AD22: =IF($C22=1,L$19,0) -> 0 | AE22: =IF($C22=1,M$19,0) -> 0 | AF22: =IF($C22=1,N$19,0) -> 0 | AG22: =IF($C22=1,O$19,0) -> 0 | ... AW22: =IF($C22=1,AE$19,0) -> 0
B23: =SUM(H23:ET23) -> 0 | C23: =IF(D23<=$D$4,1,0) -> 0 | D23: 5 | AF23: =IF($C23=1,H$19,0) -> 0 | AG23: =IF($C23=1,I$19,0) -> 0 | AH23: =IF($C23=1,J$19,0) -> 0 | AI23: =IF($C23=1,K$19,0) -> 0 | AJ23: =IF($C23=1,L$19,0) -> 0 | AK23: =IF($C23=1,M$19,0) -> 0 | AL23: =IF($C23=1,N$19,0) -> 0 | AM23: =IF($C23=1,O$19,0) -> 0 | ... BC23: =IF($C23=1,AE$19,0) -> 0
B24: =SUM(H24:ET24) -> 0 | C24: =IF(D24<=$D$4,1,0) -> 0 | D24: 6 | AL24: =IF($C24=1,H$19,0) -> 0 | AM24: =IF($C24=1,I$19,0) -> 0 | AN24: =IF($C24=1,J$19,0) -> 0 | AO24: =IF($C24=1,K$19,0) -> 0 | AP24: =IF($C24=1,L$19,0) -> 0 | AQ24: =IF($C24=1,M$19,0) -> 0 | AR24: =IF($C24=1,N$19,0) -> 0 | AS24: =IF($C24=1,O$19,0) -> 0 | ... BI24: =IF($C24=1,AE$19,0) -> 0
B25: =SUM(H25:ET25) -> 0 | C25: =IF(D25<=$D$4,1,0) -> 0 | D25: 7 | AR25: =IF($C25=1,H$19,0) -> 0 | AS25: =IF($C25=1,I$19,0) -> 0 | AT25: =IF($C25=1,J$19,0) -> 0 | AU25: =IF($C25=1,K$19,0) -> 0 | AV25: =IF($C25=1,L$19,0) -> 0 | AW25: =IF($C25=1,M$19,0) -> 0 | AX25: =IF($C25=1,N$19,0) -> 0 | AY25: =IF($C25=1,O$19,0) -> 0 | ... BO25: =IF($C25=1,AE$19,0) -> 0
B26: =SUM(H26:ET26) -> 0 | C26: =IF(D26<=$D$4,1,0) -> 0 | D26: 8 | AX26: =IF($C26=1,H$19,0) -> 0 | AY26: =IF($C26=1,I$19,0) -> 0 | AZ26: =IF($C26=1,J$19,0) -> 0 | BA26: =IF($C26=1,K$19,0) -> 0 | BB26: =IF($C26=1,L$19,0) -> 0 | BC26: =IF($C26=1,M$19,0) -> 0 | BD26: =IF($C26=1,N$19,0) -> 0 | BE26: =IF($C26=1,O$19,0) -> 0 | ... BU26: =IF($C26=1,AE$19,0) -> 0
B27: =SUM(AF27:ET27) -> 0 | C27: =IF(D27<=$D$4,1,0) -> 0 | D27: 9 | BD27: =IF($C27=1,H$19,0) -> 0 | BE27: =IF($C27=1,I$19,0) -> 0 | BF27: =IF($C27=1,J$19,0) -> 0 | BG27: =IF($C27=1,K$19,0) -> 0 | BH27: =IF($C27=1,L$19,0) -> 0 | BI27: =IF($C27=1,M$19,0) -> 0 | BJ27: =IF($C27=1,N$19,0) -> 0 | BK27: =IF($C27=1,O$19,0) -> 0 | ... CA27: =IF($C27=1,AE$19,0) -> 0
B28: =SUM(AF28:ET28) -> 0 | C28: =IF(D28<=$D$4,1,0) -> 0 | D28: 10 | BJ28: =IF($C28=1,H$19,0) -> 0 | BK28: =IF($C28=1,I$19,0) -> 0 | BL28: =IF($C28=1,J$19,0) -> 0 | BM28: =IF($C28=1,K$19,0) -> 0 | BN28: =IF($C28=1,L$19,0) -> 0 | BO28: =IF($C28=1,M$19,0) -> 0 | BP28: =IF($C28=1,N$19,0) -> 0 | BQ28: =IF($C28=1,O$19,0) -> 0 | ... CG28: =IF($C28=1,AE$19,0) -> 0
B29: =SUM(AF29:ET29) -> 0 | C29: =IF(D29<=$D$4,1,0) -> 0 | D29: 11 | BP29: =IF($C29=1,H$19,0) -> 0 | BQ29: =IF($C29=1,I$19,0) -> 0 | BR29: =IF($C29=1,J$19,0) -> 0 | BS29: =IF($C29=1,K$19,0) -> 0 | BT29: =IF($C29=1,L$19,0) -> 0 | BU29: =IF($C29=1,M$19,0) -> 0 | BV29: =IF($C29=1,N$19,0) -> 0 | BW29: =IF($C29=1,O$19,0) -> 0 | ... CM29: =IF($C29=1,AE$19,0) -> 0
B30: =SUM(H30:ET30) -> 0 | C30: =IF(D30<=$D$4,1,0) -> 0 | D30: 12 | BV30: =IF($C30=1,N$19,0) -> 0 | BW30: =IF($C30=1,O$19,0) -> 0 | BX30: =IF($C30=1,P$19,0) -> 0 | BY30: =IF($C30=1,Q$19,0) -> 0 | BZ30: =IF($C30=1,R$19,0) -> 0 | CA30: =IF($C30=1,S$19,0) -> 0 | CB30: =IF($C30=1,T$19,0) -> 0 | CC30: =IF($C30=1,U$19,0) -> 0 | ... CS30: =IF($C30=1,AK$19,0) -> 0
B31: =SUM(H31:ET31) -> 0 | C31: =IF(D31<=$D$4,1,0) -> 0 | D31: 13 | CB31: =IF($C31=1,T$19,0) -> 0 | CC31: =IF($C31=1,U$19,0) -> 0 | CD31: =IF($C31=1,V$19,0) -> 0 | CE31: =IF($C31=1,W$19,0) -> 0 | CF31: =IF($C31=1,X$19,0) -> 0 | CG31: =IF($C31=1,Y$19,0) -> 0 | CH31: =IF($C31=1,Z$19,0) -> 0 | CI31: =IF($C31=1,AA$19,0) -> 0 | ... CY31: =IF($C31=1,AQ$19,0) -> 0
B32: =SUM(H32:ET32) -> 0 | C32: =IF(D32<=$D$4,1,0) -> 0 | D32: 14 | CH32: =IF($C32=1,Z$19,0) -> 0 | CI32: =IF($C32=1,AA$19,0) -> 0 | CJ32: =IF($C32=1,AB$19,0) -> 0 | CK32: =IF($C32=1,AC$19,0) -> 0 | CL32: =IF($C32=1,AD$19,0) -> 0 | CM32: =IF($C32=1,AE$19,0) -> 0 | CN32: =IF($C32=1,AF$19,0) -> 0 | CO32: =IF($C32=1,AG$19,0) -> 0 | ... DE32: =IF($C32=1,AW$19,0) -> 0
B33: =SUM(H33:ET33) -> 0 | C33: =IF(D33<=$D$4,1,0) -> 0 | D33: 15 | CN33: =IF($C33=1,AF$19,0) -> 0 | CO33: =IF($C33=1,AG$19,0) -> 0 | CP33: =IF($C33=1,AH$19,0) -> 0 | CQ33: =IF($C33=1,AI$19,0) -> 0 | CR33: =IF($C33=1,AJ$19,0) -> 0 | CS33: =IF($C33=1,AK$19,0) -> 0 | CT33: =IF($C33=1,AL$19,0) -> 0 | CU33: =IF($C33=1,AM$19,0) -> 0 | ... DK33: =IF($C33=1,BC$19,0) -> 0
B34: =SUM(H34:ET34) -> 0 | C34: =IF(D34<=$D$4,1,0) -> 0 | D34: 16 | CT34: =IF($C34=1,AL$19,0) -> 0 | CU34: =IF($C34=1,AM$19,0) -> 0 | CV34: =IF($C34=1,AN$19,0) -> 0 | CW34: =IF($C34=1,AO$19,0) -> 0 | CX34: =IF($C34=1,AP$19,0) -> 0 | CY34: =IF($C34=1,AQ$19,0) -> 0 | CZ34: =IF($C34=1,AR$19,0) -> 0 | DA34: =IF($C34=1,AS$19,0) -> 0 | ... DQ34: =IF($C34=1,BI$19,0) -> 0
B35: =SUM(H35:ET35) -> 0 | C35: =IF(D35<=$D$4,1,0) -> 0 | D35: 17 | CZ35: =IF($C35=1,AR$19,0) -> 0 | DA35: =IF($C35=1,AS$19,0) -> 0 | DB35: =IF($C35=1,AT$19,0) -> 0 | DC35: =IF($C35=1,AU$19,0) -> 0 | DD35: =IF($C35=1,AV$19,0) -> 0 | DE35: =IF($C35=1,AW$19,0) -> 0 | DF35: =IF($C35=1,AX$19,0) -> 0 | DG35: =IF($C35=1,AY$19,0) -> 0 | ... DW35: =IF($C35=1,BO$19,0) -> 0
B36: =SUM(H36:ET36) -> 0 | C36: =IF(D36<=$D$4,1,0) -> 0 | D36: 18 | DF36: =IF($C36=1,AX$19,0) -> 0 | DG36: =IF($C36=1,AY$19,0) -> 0 | DH36: =IF($C36=1,AZ$19,0) -> 0 | DI36: =IF($C36=1,BA$19,0) -> 0 | DJ36: =IF($C36=1,BB$19,0) -> 0 | DK36: =IF($C36=1,BC$19,0) -> 0 | DL36: =IF($C36=1,BD$19,0) -> 0 | DM36: =IF($C36=1,BE$19,0) -> 0 | ... EC36: =IF($C36=1,BU$19,0) -> 0
B37: =SUM(H37:ET37) -> 0 | C37: =IF(D37<=$D$4,1,0) -> 0 | D37: 19 | DL37: =IF($C37=1,BD$19,0) -> 0 | DM37: =IF($C37=1,BE$19,0) -> 0 | DN37: =IF($C37=1,BF$19,0) -> 0 | DO37: =IF($C37=1,BG$19,0) -> 0 | DP37: =IF($C37=1,BH$19,0) -> 0 | DQ37: =IF($C37=1,BI$19,0) -> 0 | DR37: =IF($C37=1,BJ$19,0) -> 0 | DS37: =IF($C37=1,BK$19,0) -> 0 | ... EI37: =IF($C37=1,CA$19,0) -> 0
B38: =SUM(H38:ET38) -> 0 | C38: =IF(D38<=$D$4,1,0) -> 0 | D38: 20 | DR38: =IF($C38=1,BJ$19,0) -> 0 | DS38: =IF($C38=1,BK$19,0) -> 0 | DT38: =IF($C38=1,BL$19,0) -> 0 | DU38: =IF($C38=1,BM$19,0) -> 0 | DV38: =IF($C38=1,BN$19,0) -> 0 | DW38: =IF($C38=1,BO$19,0) -> 0 | DX38: =IF($C38=1,BP$19,0) -> 0 | DY38: =IF($C38=1,BQ$19,0) -> 0 | ... EO38: =IF($C38=1,CG$19,0) -> 0
D40: Total | F40: =SUM(F19:F38) -> 1.8145229e+08 | G40: =SUM(G19:G38) -> 1.8145229e+08 | H40: =SUM(H19:H38) -> 1.8145229e+08 | I40: =SUM(I19:I38) -> 1.8145229e+08 | J40: =SUM(J19:J38) -> 2.4193638e+08 | K40: =SUM(K19:K38) -> 9.3750348e+08 | L40: =SUM(L19:L38) -> 9.3750348e+08 | M40: =SUM(M19:M38) -> 9.3750348e+08 | ... ET40: =SUM(ET19:ET38) -> 0

Sheet черн
I1: Months
C2: Реализуемая площадь | D2: ='Dashboard все'!C25 -> 6901 | I2: 1 - 6 | J2: 0.0029 | K2: =6-1+1 -> 6 | L2: =J2*K2 -> 0.0174
C3: Площадь одной очереди | D3: ='Dashboard все'!C26 -> 6901 | I3: 7-12 | J3: 0.003 | K3: =12-7+1 -> 6 | L3: =J3*K3 -> 0.018
C4: Количество очередей | D4: 7 | F4: 50% сразу | I4: 13-16 | J4: 0.004 | K4: =16-13+1 -> 4 | L4: =J4*K4 -> 0.016
C5: Итого продажи | D5: ='PnL все'!B34 -> 10713300000 | I5: 17-19 | J5: 0.008 | K5: =19-17+1 -> 3 | L5: =J5*K5 -> 0.024
C6: Продажи на 1 очередь | D6: =D5/D4 -> 1.5304714e+09 | I6: 20-22 | J6: 0.0095 | K6: =22-20+1 -> 3 | L6: =J6*K6 -> 0.0285
I7: 23-25 | J7: 0.011 | K7: =25-23+1 -> 3 | L7: =J7*K7 -> 0.033
I8: 26-32 | J8: 0.0115 | K8: =32-26+1 -> 7 | L8: =J8*K8 -> 0.0805
D9: 3.994e-05 | I9: 33-36 | J9: 0.0125 | K9: =36-33+1 -> 4 | L9: =J9*K9 -> 0.05
E10: =B20/D6 -> -6 | I10: 37-42 | J10: 0.0132 | K10: =42-37+1 -> 6 | L10: =J10*K10 -> 0.0792
I11: 43-48 | J11: 0.0134 | K11: =48-43+1 -> 6 | L11: =J11*K11 -> 0.0804
I12: 49-55 | J12: 0.0135 | K12: =55-49+1 -> 7 | L12: =J12*K12 -> 0.0945
I13: 56-64 | J13: 0.0145 | K13: =64-56+1 -> 9 | L13: =J13*K13 -> 0.1305
I14: 65-75 | J14: 0.015 | K14: =75-65+1 -> 11 | L14: =J14*K14 -> 0.165
I15: 76-84 | J15: =L15/K15 -> 0.020333333 | K15: =84-76+1 -> 9 | L15: =L17-L2-L3-L4-L5-L6-L7-L8-L9-L10-L11-L12-L13-L14 -> 0.183
K17: =SUM(K2:K16) -> 84 | L17: 1
D19: =B20/D6 -> -6 | I19: Total | J19: =SUM(J2:J14) -> 0.132 | K19: =SUM(K2:K10) -> 42 | L19: 1
B20: =D6-B22 -> -9.1828286e+09
E21: =DCF!D6 -> 46204 | F21: =EDATE(E21,1) -> 46235 | G21: =EDATE(F21,1) -> 46266 | H21: =EDATE(G21,1) -> 46296 | I21: =EDATE(H21,1) -> 46327 | J21: =EDATE(I21,1) -> 46357 | K21: =EDATE(J21,1) -> 46388 | L21: =EDATE(K21,1) -> 46419 | M21: =EDATE(L21,1) -> 46447 | ... EQ21: =EDATE(EP21,1) -> 50526
B22: =SUM(B23:B42) -> 1.07133e+10 | D22: Очередь | E22: 1 | F22: =E22+1 -> 2 | G22: =F22+1 -> 3 | H22: =G22+1 -> 4 | I22: =H22+1 -> 5 | J22: =I22+1 -> 6 | K22: =J22+1 -> 7 | L22: =K22+1 -> 8 | M22: =L22+1 -> 9 | ... EQ22: =EP22+1 -> 143
B23: =SUM(E23:EQ23) -> 1.5304714e+09 | C23: =IF(D23<=$D$4,1,0) -> 1 | D23: 1 | E23: =$J$2*$D$6 -> 4438367.1 | F23: =$J$2*$D$6 -> 4438367.1 | G23: =$J$2*$D$6 -> 4438367.1 | H23: =$J$2*$D$6 -> 4438367.1 | I23: =$J$2*$D$6 -> 4438367.1 | J23: =$J$2*$D$6 -> 4438367.1 | K23: =$J$3*$D$6 -> 4591414.3 | L23: =$J$3*$D$6 -> 4591414.3 | M23: =$J$3*$D$6 -> 4591414.3 | N23: =$J$3*$D$6 -> 4591414.3 | O23: =$J$3*$D$6 -> 4591414.3 | P23: =$J$3*$D$6 -> 4591414.3 | Q23: =$J$4*$D$6 -> 6121885.7 | R23: =$J$4*$D$6 -> 6121885.7 | S23: =$J$4*$D$6 -> 6121885.7 | T23: =$J$4*$D$6 -> 6121885.7 | U23: =$J$5*$D$6 -> 12243771 | V23: =$J$5*$D$6 -> 12243771 | W23: =$J$5*$D$6 -> 12243771 | X23: =$J$6*$D$6 -> 14539479 | Y23: =$J$6*$D$6 -> 14539479 | Z23: =$J$6*$D$6 -> 14539479 | AA23: =$J$7*$D$6 -> 16835186 | AB23: =$J$7*$D$6 -> 16835186 | AC23: =$J$7*$D$6 -> 16835186 | AD23: =$J$8*$D$6 -> 17600421 | AE23: =$J$8*$D$6 -> 17600421 | AF23: =$J$8*$D$6 -> 17600421 | AG23: =$J$8*$D$6 -> 17600421 | AH23: =$J$8*$D$6 -> 17600421 | AI23: =$J$8*$D$6 -> 17600421 | AJ23: =$J$8*$D$6 -> 17600421 | AK23: =$J$9*$D$6 -> 19130893 | AL23: =$J$9*$D$6 -> 19130893 | AM23: =$J$9*$D$6 -> 19130893 | AN23: =$J$9*$D$6 -> 19130893 | AO23: =$J$10*$D$6 -> 20202223 | AP23: =$J$10*$D$6 -> 20202223 | AQ23: =$J$10*$D$6 -> 20202223 | AR23: =$J$10*$D$6 -> 20202223 | AS23: =$J$10*$D$6 -> 20202223 | AT23: =$J$10*$D$6 -> 20202223 | AU23: =$J$11*$D$6 -> 20508317 | AV23: =$J$11*$D$6 -> 20508317 | AW23: =$J$11*$D$6 -> 20508317 | AX23: =$J$11*$D$6 -> 20508317 | AY23: =$J$11*$D$6 -> 20508317 | AZ23: =$J$11*$D$6 -> 20508317 | BA23: =$J$12*$D$6 -> 20661364 | BB23: =$J$12*$D$6 -> 20661364 | BC23: =$J$12*$D$6 -> 20661364 | BD23: =$J$12*$D$6 -> 20661364 | BE23: =$J$12*$D$6 -> 20661364 | BF23: =$J$12*$D$6 -> 20661364 | BG23: =$J$12*$D$6 -> 20661364 | BH23: =$J$13*$D$6 -> 22191836 | BI23: =$J$13*$D$6 -> 22191836 | BJ23: =$J$13*$D$6 -> 22191836 | BK23: =$J$13*$D$6 -> 22191836 | BL23: =$J$13*$D$6 -> 22191836 | BM23: =$J$13*$D$6 -> 22191836 | BN23: =$J$13*$D$6 -> 22191836 | BO23: =$J$13*$D$6 -> 22191836 | BP23: =$J$13*$D$6 -> 22191836 | BQ23: =$J$14*$D$6 -> 22957071 | BR23: =$J$14*$D$6 -> 22957071 | BS23: =$J$14*$D$6 -> 22957071 | BT23: =$J$14*$D$6 -> 22957071 | BU23: =$J$14*$D$6 -> 22957071 | BV23: =$J$14*$D$6 -> 22957071 | BW23: =$J$14*$D$6 -> 22957071 | BX23: =$J$14*$D$6 -> 22957071 | ... CA23: =$J$14*$D$6 -> 22957071 | CB23: =$J$15*$D$6 -> 31119586 | CC23: =$J$15*$D$6 -> 31119586 | CD23: =$J$15*$D$6 -> 31119586 | CE23: =$J$15*$D$6 -> 31119586 | CF23: =$J$15*$D$6 -> 31119586 | CG23: =$J$15*$D$6 -> 31119586 | CH23: =$J$15*$D$6 -> 31119586 | CI23: =$J$15*$D$6 -> 31119586 | CJ23: =$J$15*$D$6 -> 31119586
B24: =SUM(E24:EQ24) -> 1.5304714e+09 | C24: =IF(D24<=$D$4,1,0) -> 1 | D24: =D23+C23 -> 2 | K24: =IF($C24=1,E$23,0) -> 4438367.1 | L24: =IF($C$24=1,F23,0) -> 4438367.1 | M24: =IF($C$24=1,G23,0) -> 4438367.1 | N24: =IF($C$24=1,H23,0) -> 4438367.1 | O24: =IF($C$24=1,I23,0) -> 4438367.1 | P24: =IF($C$24=1,J23,0) -> 4438367.1 | Q24: =IF($C$24=1,K23,0) -> 4591414.3 | R24: =IF($C$24=1,L23,0) -> 4591414.3 | S24: =IF($C$24=1,M23,0) -> 4591414.3 | ... CY24: =IF($C$24=1,CS23,0) -> 0
B25: =SUM(E25:EQ25) -> 1.5304714e+09 | C25: =IF(D25<=$D$4,1,0) -> 1 | D25: 3 | Q25: =IF($C25=1,E$23,0) -> 4438367.1 | R25: =IF($C25=1,F$23,0) -> 4438367.1 | S25: =IF($C25=1,G$23,0) -> 4438367.1 | T25: =IF($C25=1,H$23,0) -> 4438367.1 | U25: =IF($C25=1,I$23,0) -> 4438367.1 | V25: =IF($C25=1,J$23,0) -> 4438367.1 | W25: =IF($C25=1,K$23,0) -> 4591414.3 | X25: =IF($C25=1,L$23,0) -> 4591414.3 | ... DI25: =IF($C25=1,CW$23,0) -> 0
B26: =SUM(E26:EQ26) -> 1.5304714e+09 | C26: =IF(D26<=$D$4,1,0) -> 1 | D26: 4 | W26: =IF($C26=1,E$23,0) -> 4438367.1 | X26: =IF($C26=1,F$23,0) -> 4438367.1 | Y26: =IF($C26=1,G$23,0) -> 4438367.1 | Z26: =IF($C26=1,H$23,0) -> 4438367.1 | AA26: =IF($C26=1,I$23,0) -> 4438367.1 | AB26: =IF($C26=1,J$23,0) -> 4438367.1 | AC26: =IF($C26=1,K$23,0) -> 4591414.3 | AD26: =IF($C26=1,L$23,0) -> 4591414.3 | ... DX26: =IF($C26=1,DF$23,0) -> 0
B27: =SUM(E27:EQ27) -> 1.5304714e+09 | C27: =IF(D27<=$D$4,1,0) -> 1 | D27: 5 | AC27: =IF($C27=1,E$23,0) -> 4438367.1 | AD27: =IF($C27=1,F$23,0) -> 4438367.1 | AE27: =IF($C27=1,G$23,0) -> 4438367.1 | AF27: =IF($C27=1,H$23,0) -> 4438367.1 | AG27: =IF($C27=1,I$23,0) -> 4438367.1 | AH27: =IF($C27=1,J$23,0) -> 4438367.1 | AI27: =IF($C27=1,K$23,0) -> 4591414.3 | AJ27: =IF($C27=1,L$23,0) -> 4591414.3 | ... DS27: =IF($C27=1,CU$23,0) -> 0
B28: =SUM(E28:EQ28) -> 1.5304714e+09 | C28: =IF(D28<=$D$4,1,0) -> 1 | D28: 6 | AI28: =IF($C28=1,E$23,0) -> 4438367.1 | AJ28: =IF($C28=1,F$23,0) -> 4438367.1 | AK28: =IF($C28=1,G$23,0) -> 4438367.1 | AL28: =IF($C28=1,H$23,0) -> 4438367.1 | AM28: =IF($C28=1,I$23,0) -> 4438367.1 | AN28: =IF($C28=1,J$23,0) -> 4438367.1 | AO28: =IF($C28=1,K$23,0) -> 4591414.3 | AP28: =IF($C28=1,L$23,0) -> 4591414.3 | ... ED28: =IF($C28=1,CZ$23,0) -> 0
B29: =SUM(E29:EQ29) -> 1.5304714e+09 | C29: =IF(D29<=$D$4,1,0) -> 1 | D29: 7 | AO29: =IF($C29=1,E$23,0) -> 4438367.1 | AP29: =IF($C29=1,F$23,0) -> 4438367.1 | AQ29: =IF($C29=1,G$23,0) -> 4438367.1 | AR29: =IF($C29=1,H$23,0) -> 4438367.1 | AS29: =IF($C29=1,I$23,0) -> 4438367.1 | AT29: =IF($C29=1,J$23,0) -> 4438367.1 | AU29: =IF($C29=1,K$23,0) -> 4591414.3 | AV29: =IF($C29=1,L$23,0) -> 4591414.3 | ... EP29: =IF($C29=1,DF$23,0) -> 0
B30: =SUM(E30:EQ30) -> 0 | C30: =IF(D30<=$D$4,1,0) -> 0 | D30: 8 | AU30: =IF($C30=1,E$23,0) -> 0 | AV30: =IF($C30=1,F$23,0) -> 0 | AW30: =IF($C30=1,G$23,0) -> 0 | AX30: =IF($C30=1,H$23,0) -> 0 | AY30: =IF($C30=1,I$23,0) -> 0 | AZ30: =IF($C30=1,J$23,0) -> 0 | BA30: =IF($C30=1,K$23,0) -> 0 | BB30: =IF($C30=1,L$23,0) -> 0 | ... BR30: =IF($C30=1,AB$23,0) -> 0
B31: =SUM(AC31:EQ31) -> 0 | C31: =IF(D31<=$D$4,1,0) -> 0 | D31: 9 | BA31: =IF($C31=1,E$23,0) -> 0 | BB31: =IF($C31=1,F$23,0) -> 0 | BC31: =IF($C31=1,G$23,0) -> 0 | BD31: =IF($C31=1,H$23,0) -> 0 | BE31: =IF($C31=1,I$23,0) -> 0 | BF31: =IF($C31=1,J$23,0) -> 0 | BG31: =IF($C31=1,K$23,0) -> 0 | BH31: =IF($C31=1,L$23,0) -> 0 | ... BX31: =IF($C31=1,AB$23,0) -> 0
B32: =SUM(AC32:EQ32) -> 0 | C32: =IF(D32<=$D$4,1,0) -> 0 | D32: 10 | BG32: =IF($C32=1,E$23,0) -> 0 | BH32: =IF($C32=1,F$23,0) -> 0 | BI32: =IF($C32=1,G$23,0) -> 0 | BJ32: =IF($C32=1,H$23,0) -> 0 | BK32: =IF($C32=1,I$23,0) -> 0 | BL32: =IF($C32=1,J$23,0) -> 0 | BM32: =IF($C32=1,K$23,0) -> 0 | BN32: =IF($C32=1,L$23,0) -> 0 | ... CD32: =IF($C32=1,AB$23,0) -> 0
B33: =SUM(AC33:EQ33) -> 0 | C33: =IF(D33<=$D$4,1,0) -> 0 | D33: 11 | BM33: =IF($C33=1,E$23,0) -> 0 | BN33: =IF($C33=1,F$23,0) -> 0 | BO33: =IF($C33=1,G$23,0) -> 0 | BP33: =IF($C33=1,H$23,0) -> 0 | BQ33: =IF($C33=1,I$23,0) -> 0 | BR33: =IF($C33=1,J$23,0) -> 0 | BS33: =IF($C33=1,K$23,0) -> 0 | BT33: =IF($C33=1,L$23,0) -> 0 | ... CJ33: =IF($C33=1,AB$23,0) -> 0
B34: =SUM(E34:EQ34) -> 0 | C34: =IF(D34<=$D$4,1,0) -> 0 | D34: 12 | BS34: =IF($C34=1,K$23,0) -> 0 | BT34: =IF($C34=1,L$23,0) -> 0 | BU34: =IF($C34=1,M$23,0) -> 0 | BV34: =IF($C34=1,N$23,0) -> 0 | BW34: =IF($C34=1,O$23,0) -> 0 | BX34: =IF($C34=1,P$23,0) -> 0 | BY34: =IF($C34=1,Q$23,0) -> 0 | BZ34: =IF($C34=1,R$23,0) -> 0 | ... CP34: =IF($C34=1,AH$23,0) -> 0
B35: =SUM(E35:EQ35) -> 0 | C35: =IF(D35<=$D$4,1,0) -> 0 | D35: 13 | BY35: =IF($C35=1,Q$23,0) -> 0 | BZ35: =IF($C35=1,R$23,0) -> 0 | CA35: =IF($C35=1,S$23,0) -> 0 | CB35: =IF($C35=1,T$23,0) -> 0 | CC35: =IF($C35=1,U$23,0) -> 0 | CD35: =IF($C35=1,V$23,0) -> 0 | CE35: =IF($C35=1,W$23,0) -> 0 | CF35: =IF($C35=1,X$23,0) -> 0 | ... CV35: =IF($C35=1,AN$23,0) -> 0
B36: =SUM(E36:EQ36) -> 0 | C36: =IF(D36<=$D$4,1,0) -> 0 | D36: 14 | CE36: =IF($C36=1,W$23,0) -> 0 | CF36: =IF($C36=1,X$23,0) -> 0 | CG36: =IF($C36=1,Y$23,0) -> 0 | CH36: =IF($C36=1,Z$23,0) -> 0 | CI36: =IF($C36=1,AA$23,0) -> 0 | CJ36: =IF($C36=1,AB$23,0) -> 0 | CK36: =IF($C36=1,AC$23,0) -> 0 | CL36: =IF($C36=1,AD$23,0) -> 0 | ... DB36: =IF($C36=1,AT$23,0) -> 0
B37: =SUM(E37:EQ37) -> 0 | C37: =IF(D37<=$D$4,1,0) -> 0 | D37: 15 | CK37: =IF($C37=1,AC$23,0) -> 0 | CL37: =IF($C37=1,AD$23,0) -> 0 | CM37: =IF($C37=1,AE$23,0) -> 0 | CN37: =IF($C37=1,AF$23,0) -> 0 | CO37: =IF($C37=1,AG$23,0) -> 0 | CP37: =IF($C37=1,AH$23,0) -> 0 | CQ37: =IF($C37=1,AI$23,0) -> 0 | CR37: =IF($C37=1,AJ$23,0) -> 0 | ... DH37: =IF($C37=1,AZ$23,0) -> 0
B38: =SUM(E38:EQ38) -> 0 | C38: =IF(D38<=$D$4,1,0) -> 0 | D38: 16 | CQ38: =IF($C38=1,AI$23,0) -> 0 | CR38: =IF($C38=1,AJ$23,0) -> 0 | CS38: =IF($C38=1,AK$23,0) -> 0 | CT38: =IF($C38=1,AL$23,0) -> 0 | CU38: =IF($C38=1,AM$23,0) -> 0 | CV38: =IF($C38=1,AN$23,0) -> 0 | CW38: =IF($C38=1,AO$23,0) -> 0 | CX38: =IF($C38=1,AP$23,0) -> 0 | ... DN38: =IF($C38=1,BF$23,0) -> 0
B39: =SUM(E39:EQ39) -> 0 | C39: =IF(D39<=$D$4,1,0) -> 0 | D39: 17 | CW39: =IF($C39=1,AO$23,0) -> 0 | CX39: =IF($C39=1,AP$23,0) -> 0 | CY39: =IF($C39=1,AQ$23,0) -> 0 | CZ39: =IF($C39=1,AR$23,0) -> 0 | DA39: =IF($C39=1,AS$23,0) -> 0 | DB39: =IF($C39=1,AT$23,0) -> 0 | DC39: =IF($C39=1,AU$23,0) -> 0 | DD39: =IF($C39=1,AV$23,0) -> 0 | ... DT39: =IF($C39=1,BL$23,0) -> 0
B40: =SUM(E40:EQ40) -> 0 | C40: =IF(D40<=$D$4,1,0) -> 0 | D40: 18 | DC40: =IF($C40=1,AU$23,0) -> 0 | DD40: =IF($C40=1,AV$23,0) -> 0 | DE40: =IF($C40=1,AW$23,0) -> 0 | DF40: =IF($C40=1,AX$23,0) -> 0 | DG40: =IF($C40=1,AY$23,0) -> 0 | DH40: =IF($C40=1,AZ$23,0) -> 0 | DI40: =IF($C40=1,BA$23,0) -> 0 | DJ40: =IF($C40=1,BB$23,0) -> 0 | ... DZ40: =IF($C40=1,BR$23,0) -> 0
B41: =SUM(E41:EQ41) -> 0 | C41: =IF(D41<=$D$4,1,0) -> 0 | D41: 19 | DI41: =IF($C41=1,BA$23,0) -> 0 | DJ41: =IF($C41=1,BB$23,0) -> 0 | DK41: =IF($C41=1,BC$23,0) -> 0 | DL41: =IF($C41=1,BD$23,0) -> 0 | DM41: =IF($C41=1,BE$23,0) -> 0 | DN41: =IF($C41=1,BF$23,0) -> 0 | DO41: =IF($C41=1,BG$23,0) -> 0 | DP41: =IF($C41=1,BH$23,0) -> 0 | ... EF41: =IF($C41=1,BX$23,0) -> 0
B42: =SUM(E42:EQ42) -> 0 | C42: =IF(D42<=$D$4,1,0) -> 0 | D42: 20 | DO42: =IF($C42=1,BG$23,0) -> 0 | DP42: =IF($C42=1,BH$23,0) -> 0 | DQ42: =IF($C42=1,BI$23,0) -> 0 | DR42: =IF($C42=1,BJ$23,0) -> 0 | DS42: =IF($C42=1,BK$23,0) -> 0 | DT42: =IF($C42=1,BL$23,0) -> 0 | DU42: =IF($C42=1,BM$23,0) -> 0 | DV42: =IF($C42=1,BN$23,0) -> 0 | ... EL42: =IF($C42=1,CD$23,0) -> 0
D44: Total | E44: =SUM(E23:E42) -> 4438367.1 | F44: =SUM(F23:F42) -> 4438367.1 | G44: =SUM(G23:G42) -> 4438367.1 | H44: =SUM(H23:H42) -> 4438367.1 | I44: =SUM(I23:I42) -> 4438367.1 | J44: =SUM(J23:J42) -> 4438367.1 | K44: =SUM(K23:K42) -> 9029781.4 | L44: =SUM(L23:L42) -> 9029781.4 | ... EQ44: =SUM(EQ23:EQ42) -> 0

Sheet Итог Сцен.
A3: Итоговые показатели | B3: Сценарий 1 | C3: Сценарий 2 (ЗУ 50%)
A4: Net Profit | B4: ='Dashboard все'!C4 -> 2.5663224e+09 | C4: ='Dashboard (2)'!C4/2 -> 6.79443e+09
A5: ROS, % | B5: ='Dashboard все'!C5 -> 0.23954546 | C5: ='Dashboard (2)'!C5 -> 0.15281573
A6: ROE (Отдача на капитал) | B6: ='Dashboard все'!C6 -> 0 | C6: ='Dashboard (2)'!C6 -> -6.3982158
A7: WACC (Годовой) | B7: ='Dashboard все'!C7 -> 0.21 | C7: ='Dashboard (2)'!C7 -> 0.21
A8: IRR (Минимальная ставка доходности) | B8: ='Dashboard все'!C8 -> 15.142248 | C8: ='Dashboard (2)'!C8 -> #NUM!
A9: NPV | B9: ='Dashboard все'!C9 -> 1.8777444e+09 | C9: ='Dashboard (2)'!C9/2 -> -1.5659444e+10
A10: PP | B10: ='Dashboard все'!C10 -> 1 | C10: ='Dashboard (2)'!C10 -> #N/A
A11: DPP | B11: ='Dashboard все'!C11 -> 1 | C11: ='Dashboard (2)'!C11 -> #N/A
